code
   argcount 0
   nlocals 0
   stacksize 823
   flags 0040
   code
      6400006401006c00005a0000640200640300640400640500640600640700
      640800640900640a00640b00640c00640d00640e00640f00641000641100
      641200641300641400641500641600641700641800641900641a00641b00
      641c00640700641d00641e00641f00642000642100642200642300642400
      641f00642500642600642700642800641d00642000642900642a00642b00
      642c00642d00641a00641300642e00641200642f00643000643100643200
      643300643400640700643500643600643700643800643800643900641000
      643a00643b00643c00642900643d00643e00643f00641a00644000644100
      644200644300644400644500642600644600642300644700644800641000
      643200644900644a00644b00644c00644d00644e00644f00645000641000
      645100645200645300645400645500643300645600645700645800645900
      645a00645b00645c00643000644000644c00645d00645e00645f00646000
      646100646200643300641600646300645200646400644300646500646600
      643700643a00645600646700646400643100646800646900646a00641900
      646b00646c00645200646800646d00646e00646f00646f00643700647000
      647100647200641900643300643600641000641800641900643f00645400
      640b00646900645700640700647300647400647500647600647700645900
      647800647900647a00647b00647c00647d00647e00647f00648000646900
      643300641700643900644600648100640d00648200645f00648300648400
      645900648500646200643b00648600645f00648700642b00647500648800
      646400648900645200648a00648b00648c00648d00640400645c00644d00
      648e00643d00647f00648f00649000645e00649100642300649200649300
      649400649500649600642100648300648100649700643a00649800643e00
      644c00648700646700643d00640400645200649900648c00648500646b00
      640500643f00647900643500649a00649b00646d00649c00649d00649e00
      648600649f00649f00642500645f0064a00064a100646b00647a00643a00
      64880064230064050064a20064a30064300064a400640a00642100640c00
      640d00643600643800648b0064110064a500641d0064a60064150064a700
      64a800646600641900641a0064890064a900643f0064aa00641e0064a000
      64ab0064ac0064ad0064250064ae00648700643e0064ab00646e0064af00
      64550064b00064b100644b0064b200647600643300642000640e00649400
      644500640f0064a80064310064920064b30064b20064850064b400643b00
      64b50064b600643800641000648100640700643600642c0064b600643d00
      64b50064b70064710064ae0064150064b800649100645400645f0064b900
      641d0064830064770064b80064100064ba00646f00641a00649500643600
      64880064aa0064a30064bb0064a700642500643900645300648c0064bc00
      64790064bd0064b90064be00645900648800640a00645c0064080064bf00
      64c00064c100642e00645f0064c200649500647200644800640900643800
      64300064c30064030064c40064c50064c600644500641500649b00648e00
      641d0064c700648e0064c80064c900648b0064ca00646b0064c700645200
      646d0064b50064cb00643700648e0064820064280064210064ad00646500
      648b0064a70064cc0064170064470064cd0064ce00640d00646000645100
      64cf0064080064960064270064040064d000643c0064d10064d200645900
      64d300640b0064a90064680064930064b300642a0064570064d400647d00
      64c80064a30064560064d50064d60064bf0064ca00640600646f0064c900
      647f00642a00640b00643200648800643000643400649b0064a10064d700
      640900641600645200645900641300648e00643f00644e00648f0064b900
      646700645f00640c00643000640600644900647100644c00643d0064c400
      641000647200647200644700643e00640900641900648100644500643800
      641800646d0064420064850064d80064880064220064cd0064710064d900
      64990064420064480064cb00640a00640600641c00641100642500649000
      64470064ac00646500647400643d0064920064da0064db0064dc00649e00
      648f0064dd0064b40064de00640c00640d0064d100643900643600648200
      64610064db00649300645b0064df00648400642500641900641a0064c600
      64ca0064280064a00064c500649500645f0064e000646b00646f0064da00
      645a00644800642100643800641700648700646600645e0064840064df00
      647600648b0064e100640e00645900646000640b00641a00644f00646c00
      642e0064b50064aa0064350064cb00649d0064ae0064c600642d00641000
      642200646f00647700641b00641900644c0064680064700064e200644100
      64810064a90064de0064260064930064ce0064830064b10064e300641000
      64ba0064100064e40064210064e500648f0064aa0064460064500064c400
      647d00646d0064e600641e00645a0064ad0064720064ca00640a0064bf00
      649e00642200645c00640800645900646e0064020064490064170064d800
      64e70064620064b10064cb00646e00646100647b0064430064b500647600
      64530064030064850064de00640300641c00646800641900641b0064a600
      648b00645a00641e0064ce0064e800648d00645200646f00645e0064a200
      644f00648a00643a0064470064c800642d0064e90064190064460064b300
      64ea00646900643c0064bc00642e00642e0064260064b500643900645900
      64cc00640d0064650064a300645e00648300647d00642a0064bd00648600
      64cd0064a200642700648200643c00647e0064ce0064eb0064760064d100
      64400064b40064e40064b00064800064070064870064ec00648500647500
      64ed00643400647700648a0064810064090064ee00645200644800641300
      648e00643f00644b00648f00645f0064490064ef00646a00646400645600
      64df00644a0064340064450064270064d600643a0064af00643300644000
      640c00642a0064c400643d0064e80064c400646d0064420064850064f000
      640500643f00643c0064af0064d70064b000646d0064250064ae00641100
      640600641a00646000647d0064db0064f10064aa00643700647c0064af00
      64030064040064ba0064080064d800644f0064e20064f200647d0064ae00
      640900640e00644c00641000645a00643a00641c00647b0064150064b300
      64e700649d0064a900649500647600640300641700641a00644700649300
      64600064dc0064490064790064bf00649f00646b0064110064400064c700
      648400643300640900646c00642b00649900643c0064850064b500642d00
      641900647e00644f00641d00644b0064df006489006737035a010064f300
      5a020064c70064c7006602005c02005a03005a040064af00640300640400
      640500640600640700640800640900640a0064de00640c00640d00640e00
      644c00641000641100641200641c00647b00641500641600641700642500
      641900641a0064890064300064e70064aa00641e0064a000645a0064c700
      64d10064230064cb0064c200642500647000642700642800646c00640900
      64290064f40064a700642c00647900647200640b00642e0064a000640e00
      64300064970064320064330064760064aa0064350064cb0064d100643800
      64c600642d0064100064ab0064bf00645400642900644500643e00643f00
      64310064cb0064410064810064a900644400644500644600643a00642300
      64480064b80064100064ba00641000644a0064ba0064ea00644d0064b700
      64e00064500064c400647d00643900645300648c0064bc00643300649e00
      64b90064be00645900646800642200645c0064080064bf00644c00644500
      642e00645f0064c20064170064620064b10064cb00646300645b00647500
      64430064b50064760064370064f400641f0064670064a50064be00646800
      641900641b0064190064890064700064f50064680064160064e800645200
      646f00645e0064130064710064200064ce0064330064e800642d0064e900
      641900640200642c0064b500646900643c0064bc00647300644900644f00
      64440064b80064590064cc00640d00649d00647b00646600648300647d00
      642a0064020064460064330064a200642700648200648100646a00640600
      645f0064540064f60064590064b700640600646f0064c900640700648700
      64ec00648000648800643000643400647700648a0064ae00641b00648c00
      640400642900641300648e00643f00646000641a0064ab00645e00643100
      642c00640800649300641400647100644c00643d00649900648100643f00
      647200644700643e00640c00642a0064c400643d0064630064c400646d00
      64420064850064f700640500643f00643c0064af0064f800646d00646d00
      64250064ae0064c90064860064c10064110064250064900064f90064a100
      642500649a0067ff005a05007865006503006506006501008301006b0500
      72eb0c506e00006504006506006505008301006b050072060d64c7005a04
      006e0000650200650700650100650300196505006504001941830100375a
      0200650300649200375a0300650400649200375a040071d50c576500006a
      0800650200830100640100045564010053
  1           0 LOAD_CONST               0 (-1)
              3 LOAD_CONST               1 (None)
              6 IMPORT_NAME              0 (marshal)
              9 STORE_NAME               0 (marshal)

  2          12 LOAD_CONST               2 (6)
             15 LOAD_CONST               3 (110)
             18 LOAD_CONST               4 (165)
             21 LOAD_CONST               5 (42)
             24 LOAD_CONST               6 (96)
             27 LOAD_CONST               7 (70)
             30 LOAD_CONST               8 (13)
             33 LOAD_CONST               9 (198)
             36 LOAD_CONST              10 (86)
             39 LOAD_CONST              11 (252)
             42 LOAD_CONST              12 (168)
             45 LOAD_CONST              13 (197)
             48 LOAD_CONST              14 (220)
             51 LOAD_CONST              15 (191)
             54 LOAD_CONST              16 (128)
             57 LOAD_CONST              17 (74)
             60 LOAD_CONST              18 (66)
             63 LOAD_CONST              19 (83)
             66 LOAD_CONST              20 (132)
             69 LOAD_CONST              21 (55)
             72 LOAD_CONST              22 (190)
             75 LOAD_CONST              23 (35)
             78 LOAD_CONST              24 (146)
             81 LOAD_CONST              25 (25)
             84 LOAD_CONST              26 (72)
             87 LOAD_CONST              27 (169)
             90 LOAD_CONST              28 (32)
             93 LOAD_CONST               7 (70)
             96 LOAD_CONST              29 (68)
             99 LOAD_CONST              30 (189)
            102 LOAD_CONST              31 (95)
            105 LOAD_CONST              32 (113)
            108 LOAD_CONST              33 (121)
            111 LOAD_CONST              34 (87)
            114 LOAD_CONST              35 (171)
            117 LOAD_CONST              36 (210)
            120 LOAD_CONST              31 (95)
            123 LOAD_CONST              37 (246)
            126 LOAD_CONST              38 (2)
            129 LOAD_CONST              39 (176)
            132 LOAD_CONST              40 (3)
            135 LOAD_CONST              29 (68)
            138 LOAD_CONST              32 (113)
            141 LOAD_CONST              41 (199)
            144 LOAD_CONST              42 (120)
            147 LOAD_CONST              43 (236)
            150 LOAD_CONST              44 (207)
            153 LOAD_CONST              45 (229)
            156 LOAD_CONST              26 (72)
            159 LOAD_CONST              19 (83)
            162 LOAD_CONST              46 (224)
            165 LOAD_CONST              18 (66)
            168 LOAD_CONST              47 (222)
            171 LOAD_CONST              48 (104)
            174 LOAD_CONST              49 (44)
            177 LOAD_CONST              50 (114)
            180 LOAD_CONST              51 (200)
            183 LOAD_CONST              52 (139)
            186 LOAD_CONST               7 (70)
            189 LOAD_CONST              53 (50)
            192 LOAD_CONST              54 (221)
            195 LOAD_CONST              55 (130)
            198 LOAD_CONST              56 (145)
            201 LOAD_CONST              56 (145)
            204 LOAD_CONST              57 (213)
            207 LOAD_CONST              16 (128)
            210 LOAD_CONST              58 (100)
            213 LOAD_CONST              59 (218)
            216 LOAD_CONST              60 (160)
            219 LOAD_CONST              41 (199)
            222 LOAD_CONST              61 (8)
            225 LOAD_CONST              62 (154)
            228 LOAD_CONST              63 (17)
            231 LOAD_CONST              26 (72)
            234 LOAD_CONST              64 (178)
            237 LOAD_CONST              65 (23)
            240 LOAD_CONST              66 (195)
            243 LOAD_CONST              67 (65)
            246 LOAD_CONST              68 (138)
            249 LOAD_CONST              69 (109)
            252 LOAD_CONST              38 (2)
            255 LOAD_CONST              70 (103)
            258 LOAD_CONST              35 (171)
            261 LOAD_CONST              71 (188)
            264 LOAD_CONST              72 (214)
            267 LOAD_CONST              16 (128)
            270 LOAD_CONST              50 (114)
            273 LOAD_CONST              73 (133)
            276 LOAD_CONST              74 (98)
            279 LOAD_CONST              75 (115)
            282 LOAD_CONST              76 (255)
            285 LOAD_CONST              77 (89)
            288 LOAD_CONST              78 (85)
            291 LOAD_CONST              79 (105)
            294 LOAD_CONST              80 (108)
            297 LOAD_CONST              16 (128)
            300 LOAD_CONST              81 (235)
            303 LOAD_CONST              82 (209)
            306 LOAD_CONST              83 (232)
            309 LOAD_CONST              84 (170)
            312 LOAD_CONST              85 (78)
            315 LOAD_CONST              51 (200)
            318 LOAD_CONST              86 (112)
            321 LOAD_CONST              87 (196)
            324 LOAD_CONST              88 (36)
            327 LOAD_CONST              89 (192)
            330 LOAD_CONST              90 (57)
            333 LOAD_CONST              91 (82)
            336 LOAD_CONST              92 (163)
            339 LOAD_CONST              48 (104)
            342 LOAD_CONST              64 (178)
            345 LOAD_CONST              76 (255)
            348 LOAD_CONST              93 (7)
            351 LOAD_CONST              94 (231)
            354 LOAD_CONST              95 (77)
            357 LOAD_CONST              96 (56)
            360 LOAD_CONST              97 (38)
            363 LOAD_CONST              98 (97)
            366 LOAD_CONST              51 (200)
            369 LOAD_CONST              22 (190)
            372 LOAD_CONST              99 (226)
            375 LOAD_CONST              82 (209)
            378 LOAD_CONST             100 (127)
            381 LOAD_CONST              67 (65)
            384 LOAD_CONST             101 (164)
            387 LOAD_CONST             102 (230)
            390 LOAD_CONST              55 (130)
            393 LOAD_CONST              58 (100)
            396 LOAD_CONST              86 (112)
            399 LOAD_CONST             103 (148)
            402 LOAD_CONST             100 (127)
            405 LOAD_CONST              49 (44)
            408 LOAD_CONST             104 (99)
            411 LOAD_CONST             105 (125)
            414 LOAD_CONST             106 (174)
            417 LOAD_CONST              25 (25)
            420 LOAD_CONST             107 (247)
            423 LOAD_CONST             108 (60)
            426 LOAD_CONST              82 (209)
            429 LOAD_CONST             104 (99)
            432 LOAD_CONST             109 (167)
            435 LOAD_CONST             110 (144)
            438 LOAD_CONST             111 (219)
            441 LOAD_CONST             111 (219)
            444 LOAD_CONST              55 (130)
            447 LOAD_CONST             112 (88)
            450 LOAD_CONST             113 (12)
            453 LOAD_CONST             114 (21)
            456 LOAD_CONST              25 (25)
            459 LOAD_CONST              51 (200)
            462 LOAD_CONST              54 (221)
            465 LOAD_CONST              16 (128)
            468 LOAD_CONST              24 (146)
            471 LOAD_CONST              25 (25)
            474 LOAD_CONST              63 (17)
            477 LOAD_CONST              84 (170)
            480 LOAD_CONST              11 (252)
            483 LOAD_CONST             105 (125)
            486 LOAD_CONST              87 (196)
            489 LOAD_CONST               7 (70)
            492 LOAD_CONST             115 (131)
            495 LOAD_CONST             116 (156)
            498 LOAD_CONST             117 (126)
            501 LOAD_CONST             118 (239)
            504 LOAD_CONST             119 (223)
            507 LOAD_CONST              89 (192)
            510 LOAD_CONST             120 (33)
            513 LOAD_CONST             121 (161)
            516 LOAD_CONST             122 (248)
            519 LOAD_CONST             123 (122)
            522 LOAD_CONST             124 (241)
            525 LOAD_CONST             125 (159)
            528 LOAD_CONST             126 (215)
            531 LOAD_CONST             127 (47)
            534 LOAD_CONST             128 (119)
            537 LOAD_CONST             105 (125)
            540 LOAD_CONST              51 (200)
            543 LOAD_CONST              23 (35)
            546 LOAD_CONST              57 (213)
            549 LOAD_CONST              70 (103)
            552 LOAD_CONST             129 (244)
            555 LOAD_CONST              13 (197)
            558 LOAD_CONST             130 (106)
            561 LOAD_CONST              95 (77)
            564 LOAD_CONST             131 (216)
            567 LOAD_CONST             132 (61)
            570 LOAD_CONST              89 (192)
            573 LOAD_CONST             133 (48)
            576 LOAD_CONST              98 (97)
            579 LOAD_CONST              59 (218)
            582 LOAD_CONST             134 (19)
            585 LOAD_CONST              95 (77)
            588 LOAD_CONST             135 (28)
            591 LOAD_CONST              43 (236)
            594 LOAD_CONST             117 (126)
            597 LOAD_CONST             136 (10)
            600 LOAD_CONST             100 (127)
            603 LOAD_CONST             137 (238)
            606 LOAD_CONST              82 (209)
            609 LOAD_CONST             138 (9)
            612 LOAD_CONST             139 (129)
            615 LOAD_CONST             140 (204)
            618 LOAD_CONST             141 (206)
            621 LOAD_CONST               4 (165)
            624 LOAD_CONST              92 (163)
            627 LOAD_CONST              77 (89)
            630 LOAD_CONST             142 (124)
            633 LOAD_CONST              61 (8)
            636 LOAD_CONST             127 (47)
            639 LOAD_CONST             143 (45)
            642 LOAD_CONST             144 (63)
            645 LOAD_CONST              94 (231)
            648 LOAD_CONST             145 (59)
            651 LOAD_CONST              35 (171)
            654 LOAD_CONST             146 (1)
            657 LOAD_CONST             147 (20)
            660 LOAD_CONST             148 (147)
            663 LOAD_CONST             149 (75)
            666 LOAD_CONST             150 (183)
            669 LOAD_CONST              33 (121)
            672 LOAD_CONST             131 (216)
            675 LOAD_CONST             129 (244)
            678 LOAD_CONST             151 (73)
            681 LOAD_CONST              58 (100)
            684 LOAD_CONST             152 (166)
            687 LOAD_CONST              62 (154)
            690 LOAD_CONST              76 (255)
            693 LOAD_CONST             135 (28)
            696 LOAD_CONST             103 (148)
            699 LOAD_CONST              61 (8)
            702 LOAD_CONST               4 (165)
            705 LOAD_CONST              82 (209)
            708 LOAD_CONST             153 (194)
            711 LOAD_CONST             140 (204)
            714 LOAD_CONST             133 (48)
            717 LOAD_CONST             107 (247)
            720 LOAD_CONST               5 (42)
            723 LOAD_CONST              63 (17)
            726 LOAD_CONST             121 (161)
            729 LOAD_CONST              53 (50)
            732 LOAD_CONST             154 (249)
            735 LOAD_CONST             155 (186)
            738 LOAD_CONST             109 (167)
            741 LOAD_CONST             156 (242)
            744 LOAD_CONST             157 (243)
            747 LOAD_CONST             158 (102)
            750 LOAD_CONST             134 (19)
            753 LOAD_CONST             159 (64)
            756 LOAD_CONST             159 (64)
            759 LOAD_CONST              37 (246)
            762 LOAD_CONST              95 (77)
            765 LOAD_CONST             160 (24)
            768 LOAD_CONST             161 (123)
            771 LOAD_CONST             107 (247)
            774 LOAD_CONST             122 (248)
            777 LOAD_CONST              58 (100)
            780 LOAD_CONST             136 (10)
            783 LOAD_CONST              35 (171)
            786 LOAD_CONST               5 (42)
            789 LOAD_CONST             162 (39)
            792 LOAD_CONST             163 (14)
            795 LOAD_CONST              48 (104)
            798 LOAD_CONST             164 (201)
            801 LOAD_CONST              10 (86)
            804 LOAD_CONST              33 (121)
            807 LOAD_CONST              12 (168)
            810 LOAD_CONST              13 (197)
            813 LOAD_CONST              54 (221)
            816 LOAD_CONST              56 (145)
            819 LOAD_CONST             139 (129)
            822 LOAD_CONST              17 (74)
            825 LOAD_CONST             165 (26)
            828 LOAD_CONST              29 (68)
            831 LOAD_CONST             166 (117)
            834 LOAD_CONST              21 (55)
            837 LOAD_CONST             167 (237)
            840 LOAD_CONST             168 (11)
            843 LOAD_CONST             102 (230)
            846 LOAD_CONST              25 (25)
            849 LOAD_CONST              26 (72)
            852 LOAD_CONST             137 (238)
            855 LOAD_CONST             169 (27)
            858 LOAD_CONST              63 (17)
            861 LOAD_CONST             170 (69)
            864 LOAD_CONST              30 (189)
            867 LOAD_CONST             160 (24)
            870 LOAD_CONST             171 (52)
            873 LOAD_CONST             172 (91)
            876 LOAD_CONST             173 (173)
            879 LOAD_CONST              37 (246)
            882 LOAD_CONST             174 (150)
            885 LOAD_CONST             135 (28)
            888 LOAD_CONST              62 (154)
            891 LOAD_CONST             171 (52)
            894 LOAD_CONST             110 (144)
            897 LOAD_CONST             175 (101)
            900 LOAD_CONST              85 (78)
            903 LOAD_CONST             176 (175)
            906 LOAD_CONST             177 (162)
            909 LOAD_CONST              75 (115)
            912 LOAD_CONST             178 (137)
            915 LOAD_CONST             118 (239)
            918 LOAD_CONST              51 (200)
            921 LOAD_CONST              32 (113)
            924 LOAD_CONST              14 (220)
            927 LOAD_CONST             148 (147)
            930 LOAD_CONST              69 (109)
            933 LOAD_CONST              15 (191)
            936 LOAD_CONST             168 (11)
            939 LOAD_CONST              49 (44)
            942 LOAD_CONST             146 (1)
            945 LOAD_CONST             179 (187)
            948 LOAD_CONST             178 (137)
            951 LOAD_CONST             133 (48)
            954 LOAD_CONST             180 (94)
            957 LOAD_CONST              59 (218)
            960 LOAD_CONST             181 (254)
            963 LOAD_CONST             182 (177)
            966 LOAD_CONST              56 (145)
            969 LOAD_CONST              16 (128)
            972 LOAD_CONST             129 (244)
            975 LOAD_CONST               7 (70)
            978 LOAD_CONST              54 (221)
            981 LOAD_CONST              44 (207)
            984 LOAD_CONST             182 (177)
            987 LOAD_CONST              61 (8)
            990 LOAD_CONST             181 (254)
            993 LOAD_CONST             183 (49)
            996 LOAD_CONST             113 (12)
            999 LOAD_CONST             174 (150)
           1002 LOAD_CONST              21 (55)
           1005 LOAD_CONST             184 (212)
           1008 LOAD_CONST             145 (59)
           1011 LOAD_CONST              84 (170)
           1014 LOAD_CONST              95 (77)
           1017 LOAD_CONST             185 (71)
           1020 LOAD_CONST              29 (68)
           1023 LOAD_CONST             131 (216)
           1026 LOAD_CONST             119 (223)
           1029 LOAD_CONST             184 (212)
           1032 LOAD_CONST              16 (128)
           1035 LOAD_CONST             186 (22)
           1038 LOAD_CONST             111 (219)
           1041 LOAD_CONST              26 (72)
           1044 LOAD_CONST             149 (75)
           1047 LOAD_CONST              54 (221)
           1050 LOAD_CONST             136 (10)
           1053 LOAD_CONST             170 (69)
           1056 LOAD_CONST             163 (14)
           1059 LOAD_CONST             187 (30)
           1062 LOAD_CONST             167 (237)
           1065 LOAD_CONST              37 (246)
           1068 LOAD_CONST              57 (213)
           1071 LOAD_CONST              83 (232)
           1074 LOAD_CONST             140 (204)
           1077 LOAD_CONST             188 (76)
           1080 LOAD_CONST             121 (161)
           1083 LOAD_CONST             189 (84)
           1086 LOAD_CONST             185 (71)
           1089 LOAD_CONST             190 (37)
           1092 LOAD_CONST              89 (192)
           1095 LOAD_CONST             136 (10)
           1098 LOAD_CONST              10 (86)
           1101 LOAD_CONST              92 (163)
           1104 LOAD_CONST               8 (13)
           1107 LOAD_CONST             191 (180)
           1110 LOAD_CONST             192 (140)
           1113 LOAD_CONST             193 (43)
           1116 LOAD_CONST              46 (224)
           1119 LOAD_CONST              95 (77)
           1122 LOAD_CONST             194 (93)
           1125 LOAD_CONST             149 (75)
           1128 LOAD_CONST             114 (21)
           1131 LOAD_CONST              72 (214)
           1134 LOAD_CONST               9 (198)
           1137 LOAD_CONST              56 (145)
           1140 LOAD_CONST              48 (104)
           1143 LOAD_CONST             195 (81)
           1146 LOAD_CONST               3 (110)
           1149 LOAD_CONST             196 (153)
           1152 LOAD_CONST             197 (157)
           1155 LOAD_CONST             198 (227)
           1158 LOAD_CONST              69 (109)
           1161 LOAD_CONST              21 (55)
           1164 LOAD_CONST             155 (186)
           1167 LOAD_CONST             142 (124)
           1170 LOAD_CONST              29 (68)
           1173 LOAD_CONST             199 (0)
           1176 LOAD_CONST             142 (124)
           1179 LOAD_CONST             200 (203)
           1182 LOAD_CONST             201 (118)
           1185 LOAD_CONST             139 (129)
           1188 LOAD_CONST             202 (51)
           1191 LOAD_CONST             107 (247)
           1194 LOAD_CONST             199 (0)
           1197 LOAD_CONST              82 (209)
           1200 LOAD_CONST             109 (167)
           1203 LOAD_CONST             181 (254)
           1206 LOAD_CONST             203 (182)
           1209 LOAD_CONST              55 (130)
           1212 LOAD_CONST             142 (124)
           1215 LOAD_CONST             130 (106)
           1218 LOAD_CONST              40 (3)
           1221 LOAD_CONST              33 (121)
           1224 LOAD_CONST             173 (173)
           1227 LOAD_CONST             101 (164)
           1230 LOAD_CONST             139 (129)
           1233 LOAD_CONST             167 (237)
           1236 LOAD_CONST             204 (54)
           1239 LOAD_CONST              23 (35)
           1242 LOAD_CONST              71 (188)
           1245 LOAD_CONST             205 (193)
           1248 LOAD_CONST             206 (16)
           1251 LOAD_CONST              13 (197)
           1254 LOAD_CONST              96 (56)
           1257 LOAD_CONST              81 (235)
           1260 LOAD_CONST             207 (234)
           1263 LOAD_CONST               8 (13)
           1266 LOAD_CONST             150 (183)
           1269 LOAD_CONST              39 (176)
           1272 LOAD_CONST               4 (165)
           1275 LOAD_CONST             208 (90)
           1278 LOAD_CONST              60 (160)
           1281 LOAD_CONST             209 (135)
           1284 LOAD_CONST             210 (31)
           1287 LOAD_CONST              89 (192)
           1290 LOAD_CONST             211 (185)
           1293 LOAD_CONST              11 (252)
           1296 LOAD_CONST             169 (27)
           1299 LOAD_CONST             104 (99)
           1302 LOAD_CONST             147 (20)
           1305 LOAD_CONST             179 (187)
           1308 LOAD_CONST              42 (120)
           1311 LOAD_CONST              87 (196)
           1314 LOAD_CONST             212 (5)
           1317 LOAD_CONST             125 (159)
           1320 LOAD_CONST             200 (203)
           1323 LOAD_CONST             163 (14)
           1326 LOAD_CONST              86 (112)
           1329 LOAD_CONST             213 (143)
           1332 LOAD_CONST             214 (134)
           1335 LOAD_CONST             191 (180)
           1338 LOAD_CONST             202 (51)
           1341 LOAD_CONST               6 (96)
           1344 LOAD_CONST             111 (219)
           1347 LOAD_CONST             201 (118)
           1350 LOAD_CONST             127 (47)
           1353 LOAD_CONST              42 (120)
           1356 LOAD_CONST              11 (252)
           1359 LOAD_CONST              50 (114)
           1362 LOAD_CONST             136 (10)
           1365 LOAD_CONST              48 (104)
           1368 LOAD_CONST              52 (139)
           1371 LOAD_CONST             155 (186)
           1374 LOAD_CONST             161 (123)
           1377 LOAD_CONST             215 (228)
           1380 LOAD_CONST               9 (198)
           1383 LOAD_CONST              22 (190)
           1386 LOAD_CONST              82 (209)
           1389 LOAD_CONST              89 (192)
           1392 LOAD_CONST              19 (83)
           1395 LOAD_CONST             142 (124)
           1398 LOAD_CONST              63 (17)
           1401 LOAD_CONST              78 (85)
           1404 LOAD_CONST             143 (45)
           1407 LOAD_CONST             185 (71)
           1410 LOAD_CONST             103 (148)
           1413 LOAD_CONST              95 (77)
           1416 LOAD_CONST              12 (168)
           1419 LOAD_CONST              48 (104)
           1422 LOAD_CONST               6 (96)
           1425 LOAD_CONST              73 (133)
           1428 LOAD_CONST             113 (12)
           1431 LOAD_CONST              76 (255)
           1434 LOAD_CONST              61 (8)
           1437 LOAD_CONST             196 (153)
           1440 LOAD_CONST              16 (128)
           1443 LOAD_CONST             114 (21)
           1446 LOAD_CONST             114 (21)
           1449 LOAD_CONST              71 (188)
           1452 LOAD_CONST              62 (154)
           1455 LOAD_CONST               9 (198)
           1458 LOAD_CONST              25 (25)
           1461 LOAD_CONST             129 (244)
           1464 LOAD_CONST              69 (109)
           1467 LOAD_CONST              56 (145)
           1470 LOAD_CONST              24 (146)
           1473 LOAD_CONST             109 (167)
           1476 LOAD_CONST              66 (195)
           1479 LOAD_CONST             133 (48)
           1482 LOAD_CONST             216 (41)
           1485 LOAD_CONST             136 (10)
           1488 LOAD_CONST              34 (87)
           1491 LOAD_CONST             205 (193)
           1494 LOAD_CONST             113 (12)
           1497 LOAD_CONST             217 (251)
           1500 LOAD_CONST             153 (194)
           1503 LOAD_CONST              66 (195)
           1506 LOAD_CONST              72 (214)
           1509 LOAD_CONST             203 (182)
           1512 LOAD_CONST              10 (86)
           1515 LOAD_CONST               6 (96)
           1518 LOAD_CONST              28 (32)
           1521 LOAD_CONST              17 (74)
           1524 LOAD_CONST              37 (246)
           1527 LOAD_CONST             144 (63)
           1530 LOAD_CONST              71 (188)
           1533 LOAD_CONST             172 (91)
           1536 LOAD_CONST             101 (164)
           1539 LOAD_CONST             116 (156)
           1542 LOAD_CONST              61 (8)
           1545 LOAD_CONST             146 (1)
           1548 LOAD_CONST             218 (211)
           1551 LOAD_CONST             219 (79)
           1554 LOAD_CONST             220 (4)
           1557 LOAD_CONST             158 (102)
           1560 LOAD_CONST             143 (45)
           1563 LOAD_CONST             221 (181)
           1566 LOAD_CONST             180 (94)
           1569 LOAD_CONST             222 (250)
           1572 LOAD_CONST              12 (168)
           1575 LOAD_CONST              13 (197)
           1578 LOAD_CONST             209 (135)
           1581 LOAD_CONST              57 (213)
           1584 LOAD_CONST              54 (221)
           1587 LOAD_CONST             130 (106)
           1590 LOAD_CONST              97 (38)
           1593 LOAD_CONST             219 (79)
           1596 LOAD_CONST             147 (20)
           1599 LOAD_CONST              91 (82)
           1602 LOAD_CONST             223 (205)
           1605 LOAD_CONST             132 (61)
           1608 LOAD_CONST              37 (246)
           1611 LOAD_CONST              25 (25)
           1614 LOAD_CONST              26 (72)
           1617 LOAD_CONST             198 (227)
           1620 LOAD_CONST             202 (51)
           1623 LOAD_CONST              40 (3)
           1626 LOAD_CONST             160 (24)
           1629 LOAD_CONST             197 (157)
           1632 LOAD_CONST             149 (75)
           1635 LOAD_CONST              95 (77)
           1638 LOAD_CONST             224 (111)
           1641 LOAD_CONST             107 (247)
           1644 LOAD_CONST             111 (219)
           1647 LOAD_CONST             218 (211)
           1650 LOAD_CONST              90 (57)
           1653 LOAD_CONST              72 (214)
           1656 LOAD_CONST              33 (121)
           1659 LOAD_CONST              56 (145)
           1662 LOAD_CONST              23 (35)
           1665 LOAD_CONST             135 (28)
           1668 LOAD_CONST             102 (230)
           1671 LOAD_CONST              94 (231)
           1674 LOAD_CONST             132 (61)
           1677 LOAD_CONST             223 (205)
           1680 LOAD_CONST             118 (239)
           1683 LOAD_CONST             139 (129)
           1686 LOAD_CONST             225 (53)
           1689 LOAD_CONST              14 (220)
           1692 LOAD_CONST              89 (192)
           1695 LOAD_CONST              96 (56)
           1698 LOAD_CONST              11 (252)
           1701 LOAD_CONST              26 (72)
           1704 LOAD_CONST              79 (105)
           1707 LOAD_CONST             108 (60)
           1710 LOAD_CONST              46 (224)
           1713 LOAD_CONST             181 (254)
           1716 LOAD_CONST             170 (69)
           1719 LOAD_CONST              53 (50)
           1722 LOAD_CONST             203 (182)
           1725 LOAD_CONST             157 (243)
           1728 LOAD_CONST             174 (150)
           1731 LOAD_CONST             198 (227)
           1734 LOAD_CONST              45 (229)
           1737 LOAD_CONST              16 (128)
           1740 LOAD_CONST              34 (87)
           1743 LOAD_CONST             111 (219)
           1746 LOAD_CONST             119 (223)
           1749 LOAD_CONST              27 (169)
           1752 LOAD_CONST              25 (25)
           1755 LOAD_CONST              76 (255)
           1758 LOAD_CONST             104 (99)
           1761 LOAD_CONST             112 (88)
           1764 LOAD_CONST             226 (179)
           1767 LOAD_CONST              65 (23)
           1770 LOAD_CONST             129 (244)
           1773 LOAD_CONST             169 (27)
           1776 LOAD_CONST             222 (250)
           1779 LOAD_CONST              38 (2)
           1782 LOAD_CONST             147 (20)
           1785 LOAD_CONST             206 (16)
           1788 LOAD_CONST             131 (216)
           1791 LOAD_CONST             177 (162)
           1794 LOAD_CONST             227 (208)
           1797 LOAD_CONST              16 (128)
           1800 LOAD_CONST             186 (22)
           1803 LOAD_CONST              16 (128)
           1806 LOAD_CONST             228 (18)
           1809 LOAD_CONST              33 (121)
           1812 LOAD_CONST             229 (142)
           1815 LOAD_CONST             143 (45)
           1818 LOAD_CONST             170 (69)
           1821 LOAD_CONST              70 (103)
           1824 LOAD_CONST              80 (108)
           1827 LOAD_CONST             196 (153)
           1830 LOAD_CONST             125 (159)
           1833 LOAD_CONST             109 (167)
           1836 LOAD_CONST             230 (141)
           1839 LOAD_CONST              30 (189)
           1842 LOAD_CONST              90 (57)
           1845 LOAD_CONST             173 (173)
           1848 LOAD_CONST             114 (21)
           1851 LOAD_CONST             202 (51)
           1854 LOAD_CONST              10 (86)
           1857 LOAD_CONST             191 (180)
           1860 LOAD_CONST             158 (102)
           1863 LOAD_CONST              34 (87)
           1866 LOAD_CONST              92 (163)
           1869 LOAD_CONST               8 (13)
           1872 LOAD_CONST              89 (192)
           1875 LOAD_CONST             110 (144)
           1878 LOAD_CONST               2 (6)
           1881 LOAD_CONST              73 (133)
           1884 LOAD_CONST              23 (35)
           1887 LOAD_CONST             216 (41)
           1890 LOAD_CONST             231 (34)
           1893 LOAD_CONST              98 (97)
           1896 LOAD_CONST             177 (162)
           1899 LOAD_CONST             203 (182)
           1902 LOAD_CONST             110 (144)
           1905 LOAD_CONST              97 (38)
           1908 LOAD_CONST             123 (122)
           1911 LOAD_CONST              67 (65)
           1914 LOAD_CONST             181 (254)
           1917 LOAD_CONST             118 (239)
           1920 LOAD_CONST              83 (232)
           1923 LOAD_CONST               3 (110)
           1926 LOAD_CONST             133 (48)
           1929 LOAD_CONST             222 (250)
           1932 LOAD_CONST               3 (110)
           1935 LOAD_CONST              28 (32)
           1938 LOAD_CONST             104 (99)
           1941 LOAD_CONST              25 (25)
           1944 LOAD_CONST              27 (169)
           1947 LOAD_CONST             166 (117)
           1950 LOAD_CONST             139 (129)
           1953 LOAD_CONST              90 (57)
           1956 LOAD_CONST              30 (189)
           1959 LOAD_CONST             206 (16)
           1962 LOAD_CONST             232 (202)
           1965 LOAD_CONST             141 (206)
           1968 LOAD_CONST              82 (209)
           1971 LOAD_CONST             111 (219)
           1974 LOAD_CONST              94 (231)
           1977 LOAD_CONST             162 (39)
           1980 LOAD_CONST              79 (105)
           1983 LOAD_CONST             138 (9)
           1986 LOAD_CONST              58 (100)
           1989 LOAD_CONST              71 (188)
           1992 LOAD_CONST             200 (203)
           1995 LOAD_CONST              45 (229)
           1998 LOAD_CONST             233 (158)
           2001 LOAD_CONST              25 (25)
           2004 LOAD_CONST              70 (103)
           2007 LOAD_CONST             179 (187)
           2010 LOAD_CONST             234 (253)
           2013 LOAD_CONST             105 (125)
           2016 LOAD_CONST              60 (160)
           2019 LOAD_CONST             188 (76)
           2022 LOAD_CONST              46 (224)
           2025 LOAD_CONST              46 (224)
           2028 LOAD_CONST              38 (2)
           2031 LOAD_CONST             181 (254)
           2034 LOAD_CONST              57 (213)
           2037 LOAD_CONST              89 (192)
           2040 LOAD_CONST             204 (54)
           2043 LOAD_CONST              13 (197)
           2046 LOAD_CONST             101 (164)
           2049 LOAD_CONST             163 (14)
           2052 LOAD_CONST              94 (231)
           2055 LOAD_CONST             131 (216)
           2058 LOAD_CONST             125 (159)
           2061 LOAD_CONST              42 (120)
           2064 LOAD_CONST             189 (84)
           2067 LOAD_CONST             134 (19)
           2070 LOAD_CONST             205 (193)
           2073 LOAD_CONST             162 (39)
           2076 LOAD_CONST              39 (176)
           2079 LOAD_CONST             130 (106)
           2082 LOAD_CONST              60 (160)
           2085 LOAD_CONST             126 (215)
           2088 LOAD_CONST             206 (16)
           2091 LOAD_CONST             235 (40)
           2094 LOAD_CONST             118 (239)
           2097 LOAD_CONST             209 (135)
           2100 LOAD_CONST              64 (178)
           2103 LOAD_CONST             180 (94)
           2106 LOAD_CONST             228 (18)
           2109 LOAD_CONST             176 (175)
           2112 LOAD_CONST             128 (119)
           2115 LOAD_CONST               7 (70)
           2118 LOAD_CONST             135 (28)
           2121 LOAD_CONST             236 (136)
           2124 LOAD_CONST             133 (48)
           2127 LOAD_CONST             117 (126)
           2130 LOAD_CONST             237 (107)
           2133 LOAD_CONST              52 (139)
           2136 LOAD_CONST             119 (223)
           2139 LOAD_CONST             138 (9)
           2142 LOAD_CONST             129 (244)
           2145 LOAD_CONST               9 (198)
           2148 LOAD_CONST             238 (184)
           2151 LOAD_CONST              82 (209)
           2154 LOAD_CONST              72 (214)
           2157 LOAD_CONST              19 (83)
           2160 LOAD_CONST             142 (124)
           2163 LOAD_CONST              63 (17)
           2166 LOAD_CONST              75 (115)
           2169 LOAD_CONST             143 (45)
           2172 LOAD_CONST              95 (77)
           2175 LOAD_CONST              73 (133)
           2178 LOAD_CONST             239 (67)
           2181 LOAD_CONST             106 (174)
           2184 LOAD_CONST             100 (127)
           2187 LOAD_CONST              86 (112)
           2190 LOAD_CONST             223 (205)
           2193 LOAD_CONST              74 (98)
           2196 LOAD_CONST              52 (139)
           2199 LOAD_CONST              69 (109)
           2202 LOAD_CONST              39 (176)
           2205 LOAD_CONST             214 (134)
           2208 LOAD_CONST              58 (100)
           2211 LOAD_CONST             175 (101)
           2214 LOAD_CONST              51 (200)
           2217 LOAD_CONST              64 (178)
           2220 LOAD_CONST              12 (168)
           2223 LOAD_CONST              42 (120)
           2226 LOAD_CONST             196 (153)
           2229 LOAD_CONST              61 (8)
           2232 LOAD_CONST             232 (202)
           2235 LOAD_CONST             196 (153)
           2238 LOAD_CONST             109 (167)
           2241 LOAD_CONST              66 (195)
           2244 LOAD_CONST             133 (48)
           2247 LOAD_CONST             240 (92)
           2250 LOAD_CONST               5 (42)
           2253 LOAD_CONST              63 (17)
           2256 LOAD_CONST              60 (160)
           2259 LOAD_CONST             175 (101)
           2262 LOAD_CONST             215 (228)
           2265 LOAD_CONST             176 (175)
           2268 LOAD_CONST             109 (167)
           2271 LOAD_CONST              37 (246)
           2274 LOAD_CONST             174 (150)
           2277 LOAD_CONST              17 (74)
           2280 LOAD_CONST               6 (96)
           2283 LOAD_CONST              26 (72)
           2286 LOAD_CONST              96 (56)
           2289 LOAD_CONST             125 (159)
           2292 LOAD_CONST             219 (79)
           2295 LOAD_CONST             241 (149)
           2298 LOAD_CONST             170 (69)
           2301 LOAD_CONST              55 (130)
           2304 LOAD_CONST             124 (241)
           2307 LOAD_CONST             175 (101)
           2310 LOAD_CONST               3 (110)
           2313 LOAD_CONST               4 (165)
           2316 LOAD_CONST             186 (22)
           2319 LOAD_CONST               8 (13)
           2322 LOAD_CONST             216 (41)
           2325 LOAD_CONST              79 (105)
           2328 LOAD_CONST             226 (179)
           2331 LOAD_CONST             242 (58)
           2334 LOAD_CONST             125 (159)
           2337 LOAD_CONST             174 (150)
           2340 LOAD_CONST               9 (198)
           2343 LOAD_CONST              14 (220)
           2346 LOAD_CONST              76 (255)
           2349 LOAD_CONST              16 (128)
           2352 LOAD_CONST              90 (57)
           2355 LOAD_CONST              58 (100)
           2358 LOAD_CONST              28 (32)
           2361 LOAD_CONST             123 (122)
           2364 LOAD_CONST              21 (55)
           2367 LOAD_CONST             179 (187)
           2370 LOAD_CONST             231 (34)
           2373 LOAD_CONST             157 (243)
           2376 LOAD_CONST             169 (27)
           2379 LOAD_CONST             149 (75)
           2382 LOAD_CONST             118 (239)
           2385 LOAD_CONST               3 (110)
           2388 LOAD_CONST              23 (35)
           2391 LOAD_CONST              26 (72)
           2394 LOAD_CONST              71 (188)
           2397 LOAD_CONST             147 (20)
           2400 LOAD_CONST              96 (56)
           2403 LOAD_CONST             220 (4)
           2406 LOAD_CONST              73 (133)
           2409 LOAD_CONST             121 (161)
           2412 LOAD_CONST             191 (180)
           2415 LOAD_CONST             159 (64)
           2418 LOAD_CONST             107 (247)
           2421 LOAD_CONST              17 (74)
           2424 LOAD_CONST              64 (178)
           2427 LOAD_CONST             199 (0)
           2430 LOAD_CONST             132 (61)
           2433 LOAD_CONST              51 (200)
           2436 LOAD_CONST               9 (198)
           2439 LOAD_CONST             108 (60)
           2442 LOAD_CONST              43 (236)
           2445 LOAD_CONST             153 (194)
           2448 LOAD_CONST              60 (160)
           2451 LOAD_CONST             133 (48)
           2454 LOAD_CONST             181 (254)
           2457 LOAD_CONST              45 (229)
           2460 LOAD_CONST              25 (25)
           2463 LOAD_CONST             126 (215)
           2466 LOAD_CONST              79 (105)
           2469 LOAD_CONST              29 (68)
           2472 LOAD_CONST              75 (115)
           2475 LOAD_CONST             223 (205)
           2478 LOAD_CONST             137 (238)
           2481 BUILD_LIST             823
           2484 STORE_NAME               1 (d)

  3        2487 LOAD_CONST             243 ('')
           2490 STORE_NAME               2 (e)

  4        2493 LOAD_CONST             199 (0)
           2496 LOAD_CONST             199 (0)
           2499 BUILD_TUPLE              2
           2502 UNPACK_SEQUENCE          2
           2505 STORE_NAME               3 (i)
           2508 STORE_NAME               4 (j)

  5        2511 LOAD_CONST             175 (101)
           2514 LOAD_CONST               3 (110)
           2517 LOAD_CONST               4 (165)
           2520 LOAD_CONST               5 (42)
           2523 LOAD_CONST               6 (96)
           2526 LOAD_CONST               7 (70)
           2529 LOAD_CONST               8 (13)
           2532 LOAD_CONST               9 (198)
           2535 LOAD_CONST              10 (86)
           2538 LOAD_CONST             222 (250)
           2541 LOAD_CONST              12 (168)
           2544 LOAD_CONST              13 (197)
           2547 LOAD_CONST              14 (220)
           2550 LOAD_CONST              76 (255)
           2553 LOAD_CONST              16 (128)
           2556 LOAD_CONST              17 (74)
           2559 LOAD_CONST              18 (66)
           2562 LOAD_CONST              28 (32)
           2565 LOAD_CONST             123 (122)
           2568 LOAD_CONST              21 (55)
           2571 LOAD_CONST              22 (190)
           2574 LOAD_CONST              23 (35)
           2577 LOAD_CONST              37 (246)
           2580 LOAD_CONST              25 (25)
           2583 LOAD_CONST              26 (72)
           2586 LOAD_CONST             137 (238)
           2589 LOAD_CONST              48 (104)
           2592 LOAD_CONST             231 (34)
           2595 LOAD_CONST             170 (69)
           2598 LOAD_CONST              30 (189)
           2601 LOAD_CONST             160 (24)
           2604 LOAD_CONST              90 (57)
           2607 LOAD_CONST             199 (0)
           2610 LOAD_CONST             209 (135)
           2613 LOAD_CONST              35 (171)
           2616 LOAD_CONST             203 (182)
           2619 LOAD_CONST             194 (93)
           2622 LOAD_CONST              37 (246)
           2625 LOAD_CONST             112 (88)
           2628 LOAD_CONST              39 (176)
           2631 LOAD_CONST              40 (3)
           2634 LOAD_CONST             108 (60)
           2637 LOAD_CONST               9 (198)
           2640 LOAD_CONST              41 (199)
           2643 LOAD_CONST             244 (29)
           2646 LOAD_CONST             167 (237)
           2649 LOAD_CONST              44 (207)
           2652 LOAD_CONST             121 (161)
           2655 LOAD_CONST             114 (21)
           2658 LOAD_CONST              11 (252)
           2661 LOAD_CONST              46 (224)
           2664 LOAD_CONST             160 (24)
           2667 LOAD_CONST              14 (220)
           2670 LOAD_CONST              48 (104)
           2673 LOAD_CONST             151 (73)
           2676 LOAD_CONST              50 (114)
           2679 LOAD_CONST              51 (200)
           2682 LOAD_CONST             118 (239)
           2685 LOAD_CONST             170 (69)
           2688 LOAD_CONST              53 (50)
           2691 LOAD_CONST             203 (182)
           2694 LOAD_CONST             209 (135)
           2697 LOAD_CONST              56 (145)
           2700 LOAD_CONST             198 (227)
           2703 LOAD_CONST              45 (229)
           2706 LOAD_CONST              16 (128)
           2709 LOAD_CONST             171 (52)
           2712 LOAD_CONST             191 (180)
           2715 LOAD_CONST              84 (170)
           2718 LOAD_CONST              41 (199)
           2721 LOAD_CONST              69 (109)
           2724 LOAD_CONST              62 (154)
           2727 LOAD_CONST              63 (17)
           2730 LOAD_CONST              49 (44)
           2733 LOAD_CONST             203 (182)
           2736 LOAD_CONST              65 (23)
           2739 LOAD_CONST             129 (244)
           2742 LOAD_CONST             169 (27)
           2745 LOAD_CONST              68 (138)
           2748 LOAD_CONST              69 (109)
           2751 LOAD_CONST              70 (103)
           2754 LOAD_CONST              58 (100)
           2757 LOAD_CONST              35 (171)
           2760 LOAD_CONST              72 (214)
           2763 LOAD_CONST             184 (212)
           2766 LOAD_CONST              16 (128)
           2769 LOAD_CONST             186 (22)
           2772 LOAD_CONST              16 (128)
           2775 LOAD_CONST              74 (98)
           2778 LOAD_CONST             186 (22)
           2781 LOAD_CONST             234 (253)
           2784 LOAD_CONST              77 (89)
           2787 LOAD_CONST             183 (49)
           2790 LOAD_CONST             224 (111)
           2793 LOAD_CONST              80 (108)
           2796 LOAD_CONST             196 (153)
           2799 LOAD_CONST             125 (159)
           2802 LOAD_CONST              57 (213)
           2805 LOAD_CONST              83 (232)
           2808 LOAD_CONST             140 (204)
           2811 LOAD_CONST             188 (76)
           2814 LOAD_CONST              51 (200)
           2817 LOAD_CONST             158 (102)
           2820 LOAD_CONST             185 (71)
           2823 LOAD_CONST             190 (37)
           2826 LOAD_CONST              89 (192)
           2829 LOAD_CONST             104 (99)
           2832 LOAD_CONST              34 (87)
           2835 LOAD_CONST              92 (163)
           2838 LOAD_CONST               8 (13)
           2841 LOAD_CONST             191 (180)
           2844 LOAD_CONST              76 (255)
           2847 LOAD_CONST              69 (109)
           2850 LOAD_CONST              46 (224)
           2853 LOAD_CONST              95 (77)
           2856 LOAD_CONST             194 (93)
           2859 LOAD_CONST              23 (35)
           2862 LOAD_CONST              98 (97)
           2865 LOAD_CONST             177 (162)
           2868 LOAD_CONST             203 (182)
           2871 LOAD_CONST              99 (226)
           2874 LOAD_CONST              91 (82)
           2877 LOAD_CONST             117 (126)
           2880 LOAD_CONST              67 (65)
           2883 LOAD_CONST             181 (254)
           2886 LOAD_CONST             118 (239)
           2889 LOAD_CONST              55 (130)
           2892 LOAD_CONST             244 (29)
           2895 LOAD_CONST              31 (95)
           2898 LOAD_CONST             103 (148)
           2901 LOAD_CONST             165 (26)
           2904 LOAD_CONST             190 (37)
           2907 LOAD_CONST             104 (99)
           2910 LOAD_CONST              25 (25)
           2913 LOAD_CONST              27 (169)
           2916 LOAD_CONST              25 (25)
           2919 LOAD_CONST             137 (238)
           2922 LOAD_CONST             112 (88)
           2925 LOAD_CONST             245 (217)
           2928 LOAD_CONST             104 (99)
           2931 LOAD_CONST              22 (190)
           2934 LOAD_CONST             232 (202)
           2937 LOAD_CONST              82 (209)
           2940 LOAD_CONST             111 (219)
           2943 LOAD_CONST              94 (231)
           2946 LOAD_CONST              19 (83)
           2949 LOAD_CONST             113 (12)
           2952 LOAD_CONST              32 (113)
           2955 LOAD_CONST             206 (16)
           2958 LOAD_CONST              51 (200)
           2961 LOAD_CONST             232 (202)
           2964 LOAD_CONST              45 (229)
           2967 LOAD_CONST             233 (158)
           2970 LOAD_CONST              25 (25)
           2973 LOAD_CONST               2 (6)
           2976 LOAD_CONST              44 (207)
           2979 LOAD_CONST             181 (254)
           2982 LOAD_CONST             105 (125)
           2985 LOAD_CONST              60 (160)
           2988 LOAD_CONST             188 (76)
           2991 LOAD_CONST             115 (131)
           2994 LOAD_CONST              73 (133)
           2997 LOAD_CONST              79 (105)
           3000 LOAD_CONST              68 (138)
           3003 LOAD_CONST             184 (212)
           3006 LOAD_CONST              89 (192)
           3009 LOAD_CONST             204 (54)
           3012 LOAD_CONST              13 (197)
           3015 LOAD_CONST             157 (243)
           3018 LOAD_CONST             123 (122)
           3021 LOAD_CONST             102 (230)
           3024 LOAD_CONST             131 (216)
           3027 LOAD_CONST             125 (159)
           3030 LOAD_CONST              42 (120)
           3033 LOAD_CONST               2 (6)
           3036 LOAD_CONST              70 (103)
           3039 LOAD_CONST              51 (200)
           3042 LOAD_CONST             162 (39)
           3045 LOAD_CONST              39 (176)
           3048 LOAD_CONST             130 (106)
           3051 LOAD_CONST             129 (244)
           3054 LOAD_CONST             106 (174)
           3057 LOAD_CONST               6 (96)
           3060 LOAD_CONST              95 (77)
           3063 LOAD_CONST              84 (170)
           3066 LOAD_CONST             246 (245)
           3069 LOAD_CONST              89 (192)
           3072 LOAD_CONST             183 (49)
           3075 LOAD_CONST               6 (96)
           3078 LOAD_CONST             111 (219)
           3081 LOAD_CONST             201 (118)
           3084 LOAD_CONST               7 (70)
           3087 LOAD_CONST             135 (28)
           3090 LOAD_CONST             236 (136)
           3093 LOAD_CONST             128 (119)
           3096 LOAD_CONST             136 (10)
           3099 LOAD_CONST              48 (104)
           3102 LOAD_CONST              52 (139)
           3105 LOAD_CONST             119 (223)
           3108 LOAD_CONST             138 (9)
           3111 LOAD_CONST             174 (150)
           3114 LOAD_CONST              27 (169)
           3117 LOAD_CONST             140 (204)
           3120 LOAD_CONST               4 (165)
           3123 LOAD_CONST              41 (199)
           3126 LOAD_CONST              19 (83)
           3129 LOAD_CONST             142 (124)
           3132 LOAD_CONST              63 (17)
           3135 LOAD_CONST              96 (56)
           3138 LOAD_CONST              26 (72)
           3141 LOAD_CONST             171 (52)
           3144 LOAD_CONST              94 (231)
           3147 LOAD_CONST              49 (44)
           3150 LOAD_CONST              44 (207)
           3153 LOAD_CONST               8 (13)
           3156 LOAD_CONST             147 (20)
           3159 LOAD_CONST              20 (132)
           3162 LOAD_CONST             113 (12)
           3165 LOAD_CONST              76 (255)
           3168 LOAD_CONST              61 (8)
           3171 LOAD_CONST             153 (194)
           3174 LOAD_CONST             129 (244)
           3177 LOAD_CONST              63 (17)
           3180 LOAD_CONST             114 (21)
           3183 LOAD_CONST              71 (188)
           3186 LOAD_CONST              62 (154)
           3189 LOAD_CONST              12 (168)
           3192 LOAD_CONST              42 (120)
           3195 LOAD_CONST             196 (153)
           3198 LOAD_CONST              61 (8)
           3201 LOAD_CONST              99 (226)
           3204 LOAD_CONST             196 (153)
           3207 LOAD_CONST             109 (167)
           3210 LOAD_CONST              66 (195)
           3213 LOAD_CONST             133 (48)
           3216 LOAD_CONST             247 (116)
           3219 LOAD_CONST               5 (42)
           3222 LOAD_CONST              63 (17)
           3225 LOAD_CONST              60 (160)
           3228 LOAD_CONST             175 (101)
           3231 LOAD_CONST             248 (151)
           3234 LOAD_CONST             109 (167)
           3237 LOAD_CONST             109 (167)
           3240 LOAD_CONST              37 (246)
           3243 LOAD_CONST             174 (150)
           3246 LOAD_CONST             201 (118)
           3249 LOAD_CONST             134 (19)
           3252 LOAD_CONST             193 (43)
           3255 LOAD_CONST              17 (74)
           3258 LOAD_CONST              37 (246)
           3261 LOAD_CONST             144 (63)
           3264 LOAD_CONST             249 (225)
           3267 LOAD_CONST             161 (123)
           3270 LOAD_CONST              37 (246)
           3273 LOAD_CONST             154 (249)
           3276 BUILD_LIST             255
           3279 STORE_NAME               5 (k)

  6        3282 SETUP_LOOP             101 (to 3386)

  7     >> 3285 LOAD_NAME                3 (i)
           3288 LOAD_NAME                6 (len)
           3291 LOAD_NAME                1 (d)
           3294 CALL_FUNCTION            1
           3297 COMPARE_OP               5 (>=)
           3300 POP_JUMP_IF_FALSE     3307
           3303 BREAK_LOOP          
           3304 JUMP_FORWARD             0 (to 3307)

  8     >> 3307 LOAD_NAME                4 (j)
           3310 LOAD_NAME                6 (len)
           3313 LOAD_NAME                5 (k)
           3316 CALL_FUNCTION            1
           3319 COMPARE_OP               5 (>=)
           3322 POP_JUMP_IF_FALSE     3334
           3325 LOAD_CONST             199 (0)
           3328 STORE_NAME               4 (j)
           3331 JUMP_FORWARD             0 (to 3334)

  9     >> 3334 LOAD_NAME                2 (e)
           3337 LOAD_NAME                7 (chr)
           3340 LOAD_NAME                1 (d)
           3343 LOAD_NAME                3 (i)
           3346 BINARY_SUBSCR       
           3347 LOAD_NAME                5 (k)
           3350 LOAD_NAME                4 (j)
           3353 BINARY_SUBSCR       
           3354 BINARY_XOR          
           3355 CALL_FUNCTION            1
           3358 INPLACE_ADD         
           3359 STORE_NAME               2 (e)

 10        3362 LOAD_NAME                3 (i)
           3365 LOAD_CONST             146 (1)
           3368 INPLACE_ADD         
           3369 STORE_NAME               3 (i)

 11        3372 LOAD_NAME                4 (j)
           3375 LOAD_CONST             146 (1)
           3378 INPLACE_ADD         
           3379 STORE_NAME               4 (j)
           3382 JUMP_ABSOLUTE         3285
           3385 POP_BLOCK           

 12     >> 3386 LOAD_NAME                0 (marshal)
           3389 LOAD_ATTR                8 (loads)
           3392 LOAD_NAME                2 (e)
           3395 CALL_FUNCTION            1
           3398 LOAD_CONST               1 (None)
           3401 DUP_TOP             
           3402 EXEC_STMT           
           3403 LOAD_CONST               1 (None)
           3406 RETURN_VALUE        
   consts
      -1
      None
      6
      110
      165
      42
      96
      70
      13
      198
      86
      252
      168
      197
      220
      191
      128
      74
      66
      83
      132
      55
      190
      35
      146
      25
      72
      169
      32
      68
      189
      95
      113
      121
      87
      171
      210
      246
      2
      176
      3
      199
      120
      236
      207
      229
      224
      222
      104
      44
      114
      200
      139
      50
      221
      130
      145
      213
      100
      218
      160
      8
      154
      17
      178
      23
      195
      65
      138
      109
      103
      188
      214
      133
      98
      115
      255
      89
      85
      105
      108
      235
      209
      232
      170
      78
      112
      196
      36
      192
      57
      82
      163
      7
      231
      77
      56
      38
      97
      226
      127
      164
      230
      148
      99
      125
      174
      247
      60
      167
      144
      219
      88
      12
      21
      131
      156
      126
      239
      223
      33
      161
      248
      122
      241
      159
      215
      47
      119
      244
      106
      216
      61
      48
      19
      28
      10
      238
      9
      129
      204
      206
      124
      45
      63
      59
      1
      20
      147
      75
      183
      73
      166
      194
      249
      186
      242
      243
      102
      64
      24
      123
      39
      14
      201
      26
      117
      237
      11
      27
      69
      52
      91
      173
      150
      101
      175
      162
      137
      187
      94
      254
      177
      49
      212
      71
      22
      30
      76
      84
      37
      180
      140
      43
      93
      81
      153
      157
      227
      0
      203
      118
      51
      182
      54
      193
      16
      234
      90
      135
      31
      185
      5
      143
      134
      228
      41
      251
      211
      79
      4
      181
      250
      205
      111
      53
      179
      208
      18
      142
      141
      34
      202
      158
      253
      40
      136
      107
      184
      67
      92
      149
      58
      ''
      29
      217
      245
      116
      151
      225
   names ('marshal', 'd', 'e', 'i', 'j', 'k', 'len', 'chr', 'loads')
   varnames ()
   freevars ()
   cellvars ()
   filename '<script>'
   name '<module>'
   firstlineno 1
   lnotab
      0c01ff00ff00ff00ff00ff00ff00ff00ff00ff00b40106011201ff00ff00
      ff000601030112000401120009011c010a010e01
